Workbook

Sheet 2026 Budget >>>

Sheet P&L
C2: 2026 Forecast
C3: Income Statement
C5: ($ in actual) | D5: 46023 | E5: =EOMONTH(D5,0)+1 -> 46054 | F5: =EOMONTH(E5,0)+1 -> 46082 | G5: =EOMONTH(F5,0)+1 -> 46113 | H5: =EOMONTH(G5,0)+1 -> 46143 | I5: =EOMONTH(H5,0)+1 -> 46174 | J5: =EOMONTH(I5,0)+1 -> 46204 | K5: =EOMONTH(J5,0)+1 -> 46235 | L5: =EOMONTH(K5,0)+1 -> 46266 | ... O5: =EOMONTH(N5,0)+1 -> 46357 | Q5: Q1 '26 | R5: Q2 '26 | S5: Q3 '26 | T5: Q4 '26 | V5: 2026E | W5: Steady State
C7: Revenue
C8: AI Monitoring | D8: ='Sales Forecast'!D37+'Sales Forecast'!D43 -> 0 | E8: ='Sales Forecast'!E37+'Sales Forecast'!E43 -> 0 | F8: ='Sales Forecast'!F37+'Sales Forecast'!F43 -> 0 | G8: ='Sales Forecast'!G37+'Sales Forecast'!G43 -> 7500 | H8: ='Sales Forecast'!H37+'Sales Forecast'!H43 -> 15000 | I8: ='Sales Forecast'!I37+'Sales Forecast'!I43 -> 22500 | J8: ='Sales Forecast'!J37+'Sales Forecast'!J43 -> 45000 | K8: ='Sales Forecast'!K37+'Sales Forecast'!K43 -> 82500 | ... O8: ='Sales Forecast'!O37+'Sales Forecast'!O43 -> 375000 | Q8: =SUM(D8:F8) -> 0 | R8: =SUM(G8:I8) -> 45000 | S8: =SUM(J8:L8) -> 255000 | T8: =SUM(M8:O8) -> 862500 | V8: =SUM(Q8:T8) -> 1162500 | W8: =SUM('Sales Forecast'!D7:O7)*'Solution Offering'!J5*'Product & Pricing List'!P5*12+SUM('Sales Forecast'!D8:O8)*'Solution Offering'!J5*'Product & Pricing List'!P6*12 -> 8280000
C9: Integration Fee | D9: ='Sales Forecast'!D38+'Sales Forecast'!D44 -> 0 | E9: ='Sales Forecast'!E38+'Sales Forecast'!E44 -> 0 | F9: ='Sales Forecast'!F38+'Sales Forecast'!F44 -> 0 | G9: ='Sales Forecast'!G38+'Sales Forecast'!G44 -> 0 | H9: ='Sales Forecast'!H38+'Sales Forecast'!H44 -> 0 | I9: ='Sales Forecast'!I38+'Sales Forecast'!I44 -> 0 | J9: ='Sales Forecast'!J38+'Sales Forecast'!J44 -> 0 | K9: ='Sales Forecast'!K38+'Sales Forecast'!K44 -> 0 | ... O9: ='Sales Forecast'!O38+'Sales Forecast'!O44 -> 0 | Q9: =SUM(D9:F9) -> 0 | R9: =SUM(G9:I9) -> 0 | S9: =SUM(J9:L9) -> 0 | T9: =SUM(M9:O9) -> 0 | V9: =SUM(Q9:T9) -> 0 | W9: 0
C10: Professional Services - Implementation | D10: ='Sales Forecast'!D39+'Sales Forecast'!D45 -> 0 | E10: ='Sales Forecast'!E39+'Sales Forecast'!E45 -> 765 | F10: ='Sales Forecast'!F39+'Sales Forecast'!F45 -> 765 | G10: ='Sales Forecast'!G39+'Sales Forecast'!G45 -> 2295 | H10: ='Sales Forecast'!H39+'Sales Forecast'!H45 -> 3825 | I10: ='Sales Forecast'!I39+'Sales Forecast'!I45 -> 4590 | J10: ='Sales Forecast'!J39+'Sales Forecast'!J45 -> 7650 | K10: ='Sales Forecast'!K39+'Sales Forecast'!K45 -> 8415 | ... O10: ='Sales Forecast'!O39+'Sales Forecast'!O45 -> 11475 | Q10: =SUM(D10:F10) -> 1530 | R10: =SUM(G10:I10) -> 10710 | S10: =SUM(J10:L10) -> 25245 | T10: =SUM(M10:O10) -> 32130 | V10: =SUM(Q10:T10) -> 69615 | W10: 0
C11: Professional Services - Monthly | D11: ='Sales Forecast'!D40+'Sales Forecast'!D46 -> 0 | E11: ='Sales Forecast'!E40+'Sales Forecast'!E46 -> 0 | F11: ='Sales Forecast'!F40+'Sales Forecast'!F46 -> 0 | G11: ='Sales Forecast'!G40+'Sales Forecast'!G46 -> 765 | H11: ='Sales Forecast'!H40+'Sales Forecast'!H46 -> 1530 | I11: ='Sales Forecast'!I40+'Sales Forecast'!I46 -> 2295 | J11: ='Sales Forecast'!J40+'Sales Forecast'!J46 -> 4590 | K11: ='Sales Forecast'!K40+'Sales Forecast'!K46 -> 8415 | ... O11: ='Sales Forecast'!O40+'Sales Forecast'!O46 -> 38250 | Q11: =SUM(D11:F11) -> 0 | R11: =SUM(G11:I11) -> 4590 | S11: =SUM(J11:L11) -> 26010 | T11: =SUM(M11:O11) -> 87975 | V11: =SUM(Q11:T11) -> 118575 | W11: =SUM('Sales Forecast'!D7:O7)*'Solution Offering'!J8*'Product & Pricing List'!P8*12+SUM('Sales Forecast'!D8:O8)*'Solution Offering'!J8*'Product & Pricing List'!P8*12 -> 844560
C12: Total Revenue | D12: =SUM(D8:D11) -> 0 | E12: =SUM(E8:E11) -> 765 | F12: =SUM(F8:F11) -> 765 | G12: =SUM(G8:G11) -> 10560 | H12: =SUM(H8:H11) -> 20355 | I12: =SUM(I8:I11) -> 29385 | J12: =SUM(J8:J11) -> 57240 | K12: =SUM(K8:K11) -> 99330 | ... O12: =SUM(O8:O11) -> 424725 | Q12: =SUM(Q8:Q11) -> 1530 | R12: =SUM(R8:R11) -> 60300 | S12: =SUM(S8:S11) -> 306255 | T12: =SUM(T8:T11) -> 982605 | V12: =SUM(V8:V11) -> 1350690 | W12: =SUM(W8:W11) -> 9124560
C13: ARR | D13: =SUM(D8:D8)*12 -> 0 | E13: =SUM(E8:E8)*12 -> 0 | F13: =SUM(F8:F8)*12 -> 0 | G13: =SUM(G8:G8)*12 -> 90000 | H13: =SUM(H8:H8)*12 -> 180000 | I13: =SUM(I8:I8)*12 -> 270000 | J13: =SUM(J8:J8)*12 -> 540000 | K13: =SUM(K8:K8)*12 -> 990000 | ... O13: =SUM(O8:O8)*12 -> 4500000 | Q13: =F13 -> 0 | R13: =I13 -> 270000 | S13: =L13 -> 1530000 | T13: =O13 -> 4500000 | V13: =T13 -> 4500000 | W13: =SUM(W8:W8) -> 8280000
C14: Software % of Total Revenue | D14: =IFERROR(SUM(D8:D8)/D$12,"nm") -> nm | E14: =IFERROR(SUM(E8:E8)/E$12,"nm") -> 0 | F14: =IFERROR(SUM(F8:F8)/F$12,"nm") -> 0 | G14: =IFERROR(SUM(G8:G8)/G$12,"nm") -> 0.71022727 | H14: =IFERROR(SUM(H8:H8)/H$12,"nm") -> 0.73691968 | I14: =IFERROR(SUM(I8:I8)/I$12,"nm") -> 0.76569678 | J14: =IFERROR(SUM(J8:J8)/J$12,"nm") -> 0.78616352 | K14: =IFERROR(SUM(K8:K8)/K$12,"nm") -> 0.83056478 | ... O14: =IFERROR(SUM(O8:O8)/O$12,"nm") -> 0.88292425 | Q14: =IFERROR(SUM(Q8:Q8)/Q$12,"nm") -> 0 | R14: =IFERROR(SUM(R8:R8)/R$12,"nm") -> 0.74626866 | S14: =IFERROR(SUM(S8:S8)/S$12,"nm") -> 0.83263947 | T14: =IFERROR(SUM(T8:T8)/T$12,"nm") -> 0.87776879 | V14: =IFERROR(SUM(V8:V8)/V$12,"nm") -> 0.86067121 | W14: =IFERROR(SUM(W8:W8)/W$12,"nm") -> 0.90744102
C15: Services % of Total Revenue | D15: =IFERROR(SUM(D9:D11)/D$12,"nm") -> nm | E15: =IFERROR(SUM(E9:E11)/E$12,"nm") -> 1 | F15: =IFERROR(SUM(F9:F11)/F$12,"nm") -> 1 | G15: =IFERROR(SUM(G9:G11)/G$12,"nm") -> 0.28977273 | H15: =IFERROR(SUM(H9:H11)/H$12,"nm") -> 0.26308032 | I15: =IFERROR(SUM(I9:I11)/I$12,"nm") -> 0.23430322 | J15: =IFERROR(SUM(J9:J11)/J$12,"nm") -> 0.21383648 | K15: =IFERROR(SUM(K9:K11)/K$12,"nm") -> 0.16943522 | ... O15: =IFERROR(SUM(O9:O11)/O$12,"nm") -> 0.11707575 | Q15: =IFERROR(SUM(Q9:Q11)/Q$12,"nm") -> 1 | R15: =IFERROR(SUM(R9:R11)/R$12,"nm") -> 0.25373134 | S15: =IFERROR(SUM(S9:S11)/S$12,"nm") -> 0.16736053 | T15: =IFERROR(SUM(T9:T11)/T$12,"nm") -> 0.12223121 | V15: =IFERROR(SUM(V9:V11)/V$12,"nm") -> 0.13932879 | W15: =IFERROR(SUM(W9:W11)/W$12,"nm") -> 0.092558984
C17: Cost of Goods Sold
C18: AI Monitoring | D18: =Labor!F40+Labor!F46+'Third Party Software'!E24+'Third Party Software'!E30+'Hosting & Internet Fees'!F22+'Hosting & Internet Fees'!F30+Other!E14+Other!E20 -> 350 | E18: =Labor!G40+Labor!G46+'Third Party Software'!F24+'Third Party Software'!F30+'Hosting & Internet Fees'!G22+'Hosting & Internet Fees'!G30+Other!F14+Other!F20 -> 367.5 | F18: =Labor!H40+Labor!H46+'Third Party Software'!G24+'Third Party Software'!G30+'Hosting & Internet Fees'!H22+'Hosting & Internet Fees'!H30+Other!G14+Other!G20 -> 385.875 | G18: =Labor!I40+Labor!I46+'Third Party Software'!H24+'Third Party Software'!H30+'Hosting & Internet Fees'!I22+'Hosting & Internet Fees'!I30+Other!H14+Other!H20 -> 31395.679 | H18: =Labor!J40+Labor!J46+'Third Party Software'!I24+'Third Party Software'!I30+'Hosting & Internet Fees'!J22+'Hosting & Internet Fees'!J30+Other!I14+Other!I20 -> 62458.541 | I18: =Labor!K40+Labor!K46+'Third Party Software'!J24+'Third Party Software'!J30+'Hosting & Internet Fees'!K22+'Hosting & Internet Fees'!K30+Other!J14+Other!J20 -> 93549.138 | J18: =Labor!L40+Labor!L46+'Third Party Software'!K24+'Third Party Software'!K30+'Hosting & Internet Fees'!L22+'Hosting & Internet Fees'!L30+Other!K14+Other!K20 -> 186751.59 | K18: =Labor!M40+Labor!M46+'Third Party Software'!L24+'Third Party Software'!L30+'Hosting & Internet Fees'!M22+'Hosting & Internet Fees'!M30+Other!L14+Other!L20 -> 343431.23 | ... O18: =Labor!Q40+Labor!Q46+'Third Party Software'!P24+'Third Party Software'!P30+'Hosting & Internet Fees'!Q22+'Hosting & Internet Fees'!Q30+Other!P14+Other!P20 -> 1563338.3 | Q18: =SUM(D18:F18) -> 1103.375 | R18: =SUM(G18:I18) -> 187403.36 | S18: =SUM(J18:L18) -> 1060261.6 | T18: =SUM(M18:O18) -> 3591596.5 | V18: =SUM(Q18:T18) -> 4840364.9 | W18: =O18*12 -> 18760059
C19: Integration Fee | D19: =Labor!F41+Labor!F47+'Third Party Software'!E25+'Third Party Software'!E31+'Hosting & Internet Fees'!F23+'Hosting & Internet Fees'!F31+Other!E15+Other!E21 -> 0 | E19: =Labor!G41+Labor!G47+'Third Party Software'!F25+'Third Party Software'!F31+'Hosting & Internet Fees'!G23+'Hosting & Internet Fees'!G31+Other!F15+Other!F21 -> 0 | F19: =Labor!H41+Labor!H47+'Third Party Software'!G25+'Third Party Software'!G31+'Hosting & Internet Fees'!H23+'Hosting & Internet Fees'!H31+Other!G15+Other!G21 -> 0 | G19: =Labor!I41+Labor!I47+'Third Party Software'!H25+'Third Party Software'!H31+'Hosting & Internet Fees'!I23+'Hosting & Internet Fees'!I31+Other!H15+Other!H21 -> 0 | H19: =Labor!J41+Labor!J47+'Third Party Software'!I25+'Third Party Software'!I31+'Hosting & Internet Fees'!J23+'Hosting & Internet Fees'!J31+Other!I15+Other!I21 -> 0 | I19: =Labor!K41+Labor!K47+'Third Party Software'!J25+'Third Party Software'!J31+'Hosting & Internet Fees'!K23+'Hosting & Internet Fees'!K31+Other!J15+Other!J21 -> 0 | J19: =Labor!L41+Labor!L47+'Third Party Software'!K25+'Third Party Software'!K31+'Hosting & Internet Fees'!L23+'Hosting & Internet Fees'!L31+Other!K15+Other!K21 -> 0 | K19: =Labor!M41+Labor!M47+'Third Party Software'!L25+'Third Party Software'!L31+'Hosting & Internet Fees'!M23+'Hosting & Internet Fees'!M31+Other!L15+Other!L21 -> 0 | ... O19: =Labor!Q41+Labor!Q47+'Third Party Software'!P25+'Third Party Software'!P31+'Hosting & Internet Fees'!Q23+'Hosting & Internet Fees'!Q31+Other!P15+Other!P21 -> 0 | Q19: =SUM(D19:F19) -> 0 | R19: =SUM(G19:I19) -> 0 | S19: =SUM(J19:L19) -> 0 | T19: =SUM(M19:O19) -> 0 | V19: =SUM(Q19:T19) -> 0 | W19: 0
C20: Professional Services - Implementation | D20: =Labor!F42+Labor!F48+'Third Party Software'!E26+'Third Party Software'!E32+'Hosting & Internet Fees'!F24+'Hosting & Internet Fees'!F32+Other!E16+Other!E22 -> 0 | E20: =Labor!G42+Labor!G48+'Third Party Software'!F26+'Third Party Software'!F32+'Hosting & Internet Fees'!G24+'Hosting & Internet Fees'!G32+Other!F16+Other!F22 -> 462.8726 | F20: =Labor!H42+Labor!H48+'Third Party Software'!G26+'Third Party Software'!G32+'Hosting & Internet Fees'!H24+'Hosting & Internet Fees'!H32+Other!G16+Other!G22 -> 462.8726 | G20: =Labor!I42+Labor!I48+'Third Party Software'!H26+'Third Party Software'!H32+'Hosting & Internet Fees'!I24+'Hosting & Internet Fees'!I32+Other!H16+Other!H22 -> 1388.6178 | H20: =Labor!J42+Labor!J48+'Third Party Software'!I26+'Third Party Software'!I32+'Hosting & Internet Fees'!J24+'Hosting & Internet Fees'!J32+Other!I16+Other!I22 -> 2314.363 | I20: =Labor!K42+Labor!K48+'Third Party Software'!J26+'Third Party Software'!J32+'Hosting & Internet Fees'!K24+'Hosting & Internet Fees'!K32+Other!J16+Other!J22 -> 2777.2356 | J20: =Labor!L42+Labor!L48+'Third Party Software'!K26+'Third Party Software'!K32+'Hosting & Internet Fees'!L24+'Hosting & Internet Fees'!L32+Other!K16+Other!K22 -> 4628.726 | K20: =Labor!M42+Labor!M48+'Third Party Software'!L26+'Third Party Software'!L32+'Hosting & Internet Fees'!M24+'Hosting & Internet Fees'!M32+Other!L16+Other!L22 -> 5091.5986 | ... O20: =Labor!Q42+Labor!Q48+'Third Party Software'!P26+'Third Party Software'!P32+'Hosting & Internet Fees'!Q24+'Hosting & Internet Fees'!Q32+Other!P16+Other!P22 -> 6943.0889 | Q20: =SUM(D20:F20) -> 925.74519 | R20: =SUM(G20:I20) -> 6480.2163 | S20: =SUM(J20:L20) -> 15274.796 | T20: =SUM(M20:O20) -> 19440.649 | V20: =SUM(Q20:T20) -> 42121.406 | W20: 0
C21: Professional Services - Monthly | D21: =Labor!F43+Labor!F49+'Third Party Software'!E27+'Third Party Software'!E33+'Hosting & Internet Fees'!F25+'Hosting & Internet Fees'!F33+Other!E17+Other!E23 -> 0 | E21: =Labor!G43+Labor!G49+'Third Party Software'!F27+'Third Party Software'!F33+'Hosting & Internet Fees'!G25+'Hosting & Internet Fees'!G33+Other!F17+Other!F23 -> 0 | F21: =Labor!H43+Labor!H49+'Third Party Software'!G27+'Third Party Software'!G33+'Hosting & Internet Fees'!H25+'Hosting & Internet Fees'!H33+Other!G17+Other!G23 -> 0 | G21: =Labor!I43+Labor!I49+'Third Party Software'!H27+'Third Party Software'!H33+'Hosting & Internet Fees'!I25+'Hosting & Internet Fees'!I33+Other!H17+Other!H23 -> 462.8726 | H21: =Labor!J43+Labor!J49+'Third Party Software'!I27+'Third Party Software'!I33+'Hosting & Internet Fees'!J25+'Hosting & Internet Fees'!J33+Other!I17+Other!I23 -> 925.74519 | I21: =Labor!K43+Labor!K49+'Third Party Software'!J27+'Third Party Software'!J33+'Hosting & Internet Fees'!K25+'Hosting & Internet Fees'!K33+Other!J17+Other!J23 -> 1388.6178 | J21: =Labor!L43+Labor!L49+'Third Party Software'!K27+'Third Party Software'!K33+'Hosting & Internet Fees'!L25+'Hosting & Internet Fees'!L33+Other!K17+Other!K23 -> 2777.2356 | K21: =Labor!M43+Labor!M49+'Third Party Software'!L27+'Third Party Software'!L33+'Hosting & Internet Fees'!M25+'Hosting & Internet Fees'!M33+Other!L17+Other!L23 -> 5091.5986 | ... O21: =Labor!Q43+Labor!Q49+'Third Party Software'!P27+'Third Party Software'!P33+'Hosting & Internet Fees'!Q25+'Hosting & Internet Fees'!Q33+Other!P17+Other!P23 -> 23143.63 | Q21: =SUM(D21:F21) -> 0 | R21: =SUM(G21:I21) -> 2777.2356 | S21: =SUM(J21:L21) -> 15737.668 | T21: =SUM(M21:O21) -> 53230.349 | V21: =SUM(Q21:T21) -> 71745.252 | W21: =SUM('Sales Forecast'!D7:O8)*'Solution Offering'!J8*Labor!X20*12 -> 511011.35
C22: Total Cost of Goods Sold | D22: =SUM(D18:D21) -> 350 | E22: =SUM(E18:E21) -> 830.3726 | F22: =SUM(F18:F21) -> 848.7476 | G22: =SUM(G18:G21) -> 33247.17 | H22: =SUM(H18:H21) -> 65698.65 | I22: =SUM(I18:I21) -> 97714.992 | J22: =SUM(J18:J21) -> 194157.55 | K22: =SUM(K18:K21) -> 353614.43 | ... O22: =SUM(O18:O21) -> 1593425 | Q22: =SUM(Q18:Q21) -> 2029.1202 | R22: =SUM(R18:R21) -> 196660.81 | S22: =SUM(S18:S21) -> 1091274.1 | T22: =SUM(T18:T21) -> 3664267.5 | V22: =SUM(V18:V21) -> 4954231.6 | W22: =SUM(W18:W21) -> 19271070
C23: % of Total Revenue | D23: =IFERROR(D22/D$12,"nm") -> nm | E23: =IFERROR(E22/E$12,"nm") -> 1.0854544 | F23: =IFERROR(F22/F$12,"nm") -> 1.109474 | G23: =IFERROR(G22/G$12,"nm") -> 3.1484062 | H23: =IFERROR(H22/H$12,"nm") -> 3.2276418 | I23: =IFERROR(I22/I$12,"nm") -> 3.3253358 | J23: =IFERROR(J22/J$12,"nm") -> 3.3919908 | K23: =IFERROR(K22/K$12,"nm") -> 3.5599963 | ... O23: =IFERROR(O22/O$12,"nm") -> 3.7516628 | Q23: =IFERROR(Q22/Q$12,"nm") -> 1.3262223 | R23: =IFERROR(R22/R$12,"nm") -> 3.2613733 | S23: =IFERROR(S22/S$12,"nm") -> 3.5632859 | T23: =IFERROR(T22/T$12,"nm") -> 3.7291358 | V23: =IFERROR(V22/V$12,"nm") -> 3.6679264 | W23: =IFERROR(W22/W$12,"nm") -> 2.112
C25: Gross Profit | D25: =D12-D22 -> -350 | E25: =E12-E22 -> -65.372596 | F25: =F12-F22 -> -83.747596 | G25: =G12-G22 -> -22687.17 | H25: =H12-H22 -> -45343.65 | I25: =I12-I22 -> -68329.992 | J25: =J12-J22 -> -136917.55 | K25: =K12-K22 -> -254284.43 | ... O25: =O12-O22 -> -1168700 | Q25: =Q12-Q22 -> -499.12019 | R25: =R12-R22 -> -136360.81 | S25: =S12-S22 -> -785019.11 | T25: =T12-T22 -> -2681662.5 | V25: =V12-V22 -> -3603541.6 | W25: =W12-W22 -> -10146510
C26: AFFIRM Base Subscription % Margin | D26: =IFERROR((#REF!-#REF!)/#REF!,"nm") -> nm | E26: =IFERROR((#REF!-#REF!)/#REF!,"nm") -> nm | F26: =IFERROR((#REF!-#REF!)/#REF!,"nm") -> nm | G26: =IFERROR((#REF!-#REF!)/#REF!,"nm") -> nm | H26: =IFERROR((#REF!-#REF!)/#REF!,"nm") -> nm | I26: =IFERROR((#REF!-#REF!)/#REF!,"nm") -> nm | J26: =IFERROR((#REF!-#REF!)/#REF!,"nm") -> nm | K26: =IFERROR((#REF!-#REF!)/#REF!,"nm") -> nm | ... O26: =IFERROR((#REF!-#REF!)/#REF!,"nm") -> nm | Q26: =IFERROR((#REF!-#REF!)/#REF!,"nm") -> nm | R26: =IFERROR((#REF!-#REF!)/#REF!,"nm") -> nm | S26: =IFERROR((#REF!-#REF!)/#REF!,"nm") -> nm | T26: =IFERROR((#REF!-#REF!)/#REF!,"nm") -> nm | V26: =IFERROR((#REF!-#REF!)/#REF!,"nm") -> nm | W26: =IFERROR((#REF!-#REF!)/#REF!,"nm") -> nm
C27: Framework Pack % Margin | D27: =IFERROR((#REF!-#REF!)/#REF!,"nm") -> nm | E27: =IFERROR((#REF!-#REF!)/#REF!,"nm") -> nm | F27: =IFERROR((#REF!-#REF!)/#REF!,"nm") -> nm | G27: =IFERROR((#REF!-#REF!)/#REF!,"nm") -> nm | H27: =IFERROR((#REF!-#REF!)/#REF!,"nm") -> nm | I27: =IFERROR((#REF!-#REF!)/#REF!,"nm") -> nm | J27: =IFERROR((#REF!-#REF!)/#REF!,"nm") -> nm | K27: =IFERROR((#REF!-#REF!)/#REF!,"nm") -> nm | ... O27: =IFERROR((#REF!-#REF!)/#REF!,"nm") -> nm | Q27: =IFERROR((#REF!-#REF!)/#REF!,"nm") -> nm | R27: =IFERROR((#REF!-#REF!)/#REF!,"nm") -> nm | S27: =IFERROR((#REF!-#REF!)/#REF!,"nm") -> nm | T27: =IFERROR((#REF!-#REF!)/#REF!,"nm") -> nm | V27: =IFERROR((#REF!-#REF!)/#REF!,"nm") -> nm | W27: =IFERROR((#REF!-#REF!)/#REF!,"nm") -> nm
C28: AI Monitoring % Margin | D28: =IFERROR((D8-D18)/D8,"nm") -> nm | E28: =IFERROR((E8-E18)/E8,"nm") -> nm | F28: =IFERROR((F8-F18)/F8,"nm") -> nm | G28: =IFERROR((G8-G18)/G8,"nm") -> -3.1860906 | H28: =IFERROR((H8-H18)/H8,"nm") -> -3.1639028 | I28: =IFERROR((I8-I18)/I8,"nm") -> -3.1577395 | J28: =IFERROR((J8-J18)/J8,"nm") -> -3.1500354 | K28: =IFERROR((K8-K18)/K8,"nm") -> -3.1628028 | ... O28: =IFERROR((O8-O18)/O8,"nm") -> -3.168902 | Q28: =IFERROR((Q8-Q18)/Q8,"nm") -> nm | R28: =IFERROR((R8-R18)/R8,"nm") -> -3.1645191 | S28: =IFERROR((S8-S18)/S8,"nm") -> -3.1578888 | T28: =IFERROR((T8-T18)/T8,"nm") -> -3.1641699 | V28: =IFERROR((V8-V18)/V8,"nm") -> -3.1637548 | W28: =IFERROR((W8-W18)/W8,"nm") -> -1.2657076
C29: Usage Fee % Margin | D29: =IFERROR((#REF!-#REF!)/#REF!,"nm") -> nm | E29: =IFERROR((#REF!-#REF!)/#REF!,"nm") -> nm | F29: =IFERROR((#REF!-#REF!)/#REF!,"nm") -> nm | G29: =IFERROR((#REF!-#REF!)/#REF!,"nm") -> nm | H29: =IFERROR((#REF!-#REF!)/#REF!,"nm") -> nm | I29: =IFERROR((#REF!-#REF!)/#REF!,"nm") -> nm | J29: =IFERROR((#REF!-#REF!)/#REF!,"nm") -> nm | K29: =IFERROR((#REF!-#REF!)/#REF!,"nm") -> nm | ... O29: =IFERROR((#REF!-#REF!)/#REF!,"nm") -> nm | Q29: =IFERROR((#REF!-#REF!)/#REF!,"nm") -> nm | R29: =IFERROR((#REF!-#REF!)/#REF!,"nm") -> nm | S29: =IFERROR((#REF!-#REF!)/#REF!,"nm") -> nm | T29: =IFERROR((#REF!-#REF!)/#REF!,"nm") -> nm | V29: =IFERROR((#REF!-#REF!)/#REF!,"nm") -> nm | W29: =IFERROR((#REF!-#REF!)/#REF!,"nm") -> nm
C30: Integration Fee % Margin | D30: =IFERROR((D9-D19)/D9,"nm") -> nm | E30: =IFERROR((E9-E19)/E9,"nm") -> nm | F30: =IFERROR((F9-F19)/F9,"nm") -> nm | G30: =IFERROR((G9-G19)/G9,"nm") -> nm | H30: =IFERROR((H9-H19)/H9,"nm") -> nm | I30: =IFERROR((I9-I19)/I9,"nm") -> nm | J30: =IFERROR((J9-J19)/J9,"nm") -> nm | K30: =IFERROR((K9-K19)/K9,"nm") -> nm | ... O30: =IFERROR((O9-O19)/O9,"nm") -> nm | Q30: =IFERROR((Q9-Q19)/Q9,"nm") -> nm | R30: =IFERROR((R9-R19)/R9,"nm") -> nm | S30: =IFERROR((S9-S19)/S9,"nm") -> nm | T30: =IFERROR((T9-T19)/T9,"nm") -> nm | V30: =IFERROR((V9-V19)/V9,"nm") -> nm | W30: =IFERROR((W9-W19)/W9,"nm") -> nm
C31: Professional Services - Implementation % Margin | D31: =IFERROR((D10-D20)/D10,"nm") -> nm | E31: =IFERROR((E10-E20)/E10,"nm") -> 0.39493778 | F31: =IFERROR((F10-F20)/F10,"nm") -> 0.39493778 | G31: =IFERROR((G10-G20)/G10,"nm") -> 0.39493778 | H31: =IFERROR((H10-H20)/H10,"nm") -> 0.39493778 | I31: =IFERROR((I10-I20)/I10,"nm") -> 0.39493778 | J31: =IFERROR((J10-J20)/J10,"nm") -> 0.39493778 | K31: =IFERROR((K10-K20)/K10,"nm") -> 0.39493778 | ... O31: =IFERROR((O10-O20)/O10,"nm") -> 0.39493778 | Q31: =IFERROR((Q10-Q20)/Q10,"nm") -> 0.39493778 | R31: =IFERROR((R10-R20)/R10,"nm") -> 0.39493778 | S31: =IFERROR((S10-S20)/S10,"nm") -> 0.39493778 | T31: =IFERROR((T10-T20)/T10,"nm") -> 0.39493778 | V31: =IFERROR((V10-V20)/V10,"nm") -> 0.39493778 | W31: =IFERROR((W10-W20)/W10,"nm") -> nm
C32: Professional Services - Monthly % Margin | D32: =IFERROR((D11-D21)/D11,"nm") -> nm | E32: =IFERROR((E11-E21)/E11,"nm") -> nm | F32: =IFERROR((F11-F21)/F11,"nm") -> nm | G32: =IFERROR((G11-G21)/G11,"nm") -> 0.39493778 | H32: =IFERROR((H11-H21)/H11,"nm") -> 0.39493778 | I32: =IFERROR((I11-I21)/I11,"nm") -> 0.39493778 | J32: =IFERROR((J11-J21)/J11,"nm") -> 0.39493778 | K32: =IFERROR((K11-K21)/K11,"nm") -> 0.39493778 | ... O32: =IFERROR((O11-O21)/O11,"nm") -> 0.39493778 | Q32: =IFERROR((Q11-Q21)/Q11,"nm") -> nm | R32: =IFERROR((R11-R21)/R11,"nm") -> 0.39493778 | S32: =IFERROR((S11-S21)/S11,"nm") -> 0.39493778 | T32: =IFERROR((T11-T21)/T11,"nm") -> 0.39493778 | V32: =IFERROR((V11-V21)/V11,"nm") -> 0.39493778 | W32: =IFERROR((W11-W21)/W11,"nm") -> 0.39493778
C33: Total % Margin | D33: =IFERROR(D25/D$12,"nm") -> nm | E33: =IFERROR(E25/E$12,"nm") -> -0.085454374 | F33: =IFERROR(F25/F$12,"nm") -> -0.10947398 | G33: =IFERROR(G25/G$12,"nm") -> -2.1484062 | H33: =IFERROR(H25/H$12,"nm") -> -2.2276418 | I33: =IFERROR(I25/I$12,"nm") -> -2.3253358 | J33: =IFERROR(J25/J$12,"nm") -> -2.3919908 | K33: =IFERROR(K25/K$12,"nm") -> -2.5599963 | ... O33: =IFERROR(O25/O$12,"nm") -> -2.7516628 | Q33: =IFERROR(Q25/Q$12,"nm") -> -0.32622235 | R33: =IFERROR(R25/R$12,"nm") -> -2.2613733 | S33: =IFERROR(S25/S$12,"nm") -> -2.5632859 | T33: =IFERROR(T25/T$12,"nm") -> -2.7291358 | V33: =IFERROR(V25/V$12,"nm") -> -2.6679264 | W33: =IFERROR(W25/W$12,"nm") -> -1.112
C35: Operating Expenses
C36: Salaries, Wages, & Benefits | D36: ='Salaries, Wages, & Benefits'!F52 -> 106535.84 | E36: ='Salaries, Wages, & Benefits'!G52 -> 104570.28 | F36: ='Salaries, Wages, & Benefits'!H52 -> 101192.7 | G36: ='Salaries, Wages, & Benefits'!I52 -> 98889.929 | H36: ='Salaries, Wages, & Benefits'!J52 -> 93087.17 | I36: ='Salaries, Wages, & Benefits'!K52 -> 86743.45 | J36: ='Salaries, Wages, & Benefits'!L52 -> 69457.96 | K36: ='Salaries, Wages, & Benefits'!M52 -> 41193.778 | ... O36: ='Salaries, Wages, & Benefits'!Q52 -> -178950.33 | Q36: =SUM(D36:F36) -> 312298.83 | R36: =SUM(G36:I36) -> 278720.55 | S36: =SUM(J36:L36) -> 117945.16 | T36: =SUM(M36:O36) -> -339334.89 | V36: =SUM(Q36:T36) -> 369629.64 | W36: =V36 -> 369629.64
C37: Sales Commissions | D37: ='Sales Forecast'!D63 -> 0 | E37: ='Sales Forecast'!E63 -> 153 | F37: ='Sales Forecast'!F63 -> 153 | G37: ='Sales Forecast'!G63 -> 2112 | H37: ='Sales Forecast'!H63 -> 4071 | I37: ='Sales Forecast'!I63 -> 5877 | J37: ='Sales Forecast'!J63 -> 11448 | K37: ='Sales Forecast'!K63 -> 19866 | ... O37: ='Sales Forecast'!O63 -> 84945 | Q37: =SUM(D37:F37) -> 306 | R37: =SUM(G37:I37) -> 12060 | S37: =SUM(J37:L37) -> 61251 | T37: =SUM(M37:O37) -> 196521 | V37: =SUM(Q37:T37) -> 270138 | W37: 0
C38: Contract Labor | D38: ='Contract Labor'!I25 -> 104440 | E38: ='Contract Labor'!J25 -> 104440 | F38: ='Contract Labor'!K25 -> 104440 | G38: ='Contract Labor'!L25 -> 104440 | H38: ='Contract Labor'!M25 -> 104440 | I38: ='Contract Labor'!N25 -> 104440 | J38: ='Contract Labor'!O25 -> 104440 | K38: ='Contract Labor'!P25 -> 104440 | ... O38: ='Contract Labor'!T25 -> 104440 | Q38: =SUM(D38:F38) -> 313320 | R38: =SUM(G38:I38) -> 313320 | S38: =SUM(J38:L38) -> 313320 | T38: =SUM(M38:O38) -> 313320 | V38: =SUM(Q38:T38) -> 1253280 | W38: =V38 -> 1253280
C39: Professional Fees | D39: ='Professional Fees'!E10 -> 4500 | E39: ='Professional Fees'!F10 -> 9500 | F39: ='Professional Fees'!G10 -> 9500 | G39: ='Professional Fees'!H10 -> 9500 | H39: ='Professional Fees'!I10 -> 4500 | I39: ='Professional Fees'!J10 -> 7000 | J39: ='Professional Fees'!K10 -> 7000 | K39: ='Professional Fees'!L10 -> 7000 | ... O39: ='Professional Fees'!P10 -> 7000 | Q39: =SUM(D39:F39) -> 23500 | R39: =SUM(G39:I39) -> 21000 | S39: =SUM(J39:L39) -> 21000 | T39: =SUM(M39:O39) -> 21000 | V39: =SUM(Q39:T39) -> 86500 | W39: =V39 -> 86500
C40: Office Expenses | D40: ='Office Expenses'!E31 -> 4401 | E40: ='Office Expenses'!F31 -> 5149.11 | F40: ='Office Expenses'!G31 -> 3376 | G40: ='Office Expenses'!H31 -> 5836 | H40: ='Office Expenses'!I31 -> 7418 | I40: ='Office Expenses'!J31 -> 4216 | J40: ='Office Expenses'!K31 -> 3376 | K40: ='Office Expenses'!L31 -> 3376 | ... O40: ='Office Expenses'!P31 -> 3376 | Q40: =SUM(D40:F40) -> 12926.11 | R40: =SUM(G40:I40) -> 17470 | S40: =SUM(J40:L40) -> 13128 | T40: =SUM(M40:O40) -> 10128 | V40: =SUM(Q40:T40) -> 53652.11 | W40: =V40 -> 53652.11
C41: Advertising & Marketing | D41: ='Advertising & Marketing'!E12 -> 1279 | E41: ='Advertising & Marketing'!F12 -> 4279 | F41: ='Advertising & Marketing'!G12 -> 4279 | G41: ='Advertising & Marketing'!H12 -> 4279 | H41: ='Advertising & Marketing'!I12 -> 4279 | I41: ='Advertising & Marketing'!J12 -> 4279 | J41: ='Advertising & Marketing'!K12 -> 4279 | K41: ='Advertising & Marketing'!L12 -> 4279 | ... O41: ='Advertising & Marketing'!P12 -> 4279 | Q41: =SUM(D41:F41) -> 9837 | R41: =SUM(G41:I41) -> 12837 | S41: =SUM(J41:L41) -> 12837 | T41: =SUM(M41:O41) -> 12837 | V41: =SUM(Q41:T41) -> 48348 | W41: =V41 -> 48348
C42: Employee Travel | D42: ='Employee Travel'!D14 -> 12400 | E42: ='Employee Travel'!E14 -> 12250 | F42: ='Employee Travel'!F14 -> 12200 | G42: ='Employee Travel'!G14 -> 12200 | H42: ='Employee Travel'!H14 -> 12200 | I42: ='Employee Travel'!I14 -> 12200 | J42: ='Employee Travel'!J14 -> 12200 | K42: ='Employee Travel'!K14 -> 12200 | ... O42: ='Employee Travel'!O14 -> 12200 | Q42: =SUM(D42:F42) -> 36850 | R42: =SUM(G42:I42) -> 36600 | S42: =SUM(J42:L42) -> 36600 | T42: =SUM(M42:O42) -> 36600 | V42: =SUM(Q42:T42) -> 146650 | W42: =V42 -> 146650
C43: Other Operating Expenses | D43: ='Other Operating Expenses'!E22 -> 2212 | E43: ='Other Operating Expenses'!F22 -> 3210 | F43: ='Other Operating Expenses'!G22 -> 2812 | G43: ='Other Operating Expenses'!H22 -> 3212 | H43: ='Other Operating Expenses'!I22 -> 2712 | I43: ='Other Operating Expenses'!J22 -> 2712 | J43: ='Other Operating Expenses'!K22 -> 3309 | K43: ='Other Operating Expenses'!L22 -> 2712 | ... O43: ='Other Operating Expenses'!P22 -> 2712 | Q43: =SUM(D43:F43) -> 8234 | R43: =SUM(G43:I43) -> 8636 | S43: =SUM(J43:L43) -> 8733 | T43: =SUM(M43:O43) -> 8136 | V43: =SUM(Q43:T43) -> 33739 | W43: =V43 -> 33739
C44: Total Operating Expenses | D44: =SUM(D36:D43) -> 235767.84 | E44: =SUM(E36:E43) -> 243551.39 | F44: =SUM(F36:F43) -> 237952.7 | G44: =SUM(G36:G43) -> 240468.93 | H44: =SUM(H36:H43) -> 232707.17 | I44: =SUM(I36:I43) -> 227467.45 | J44: =SUM(J36:J43) -> 215509.96 | K44: =SUM(K36:K43) -> 195066.78 | ... O44: =SUM(O36:O43) -> 40001.667 | Q44: =SUM(Q36:Q43) -> 717271.94 | R44: =SUM(R36:R43) -> 700643.55 | S44: =SUM(S36:S43) -> 584814.16 | T44: =SUM(T36:T43) -> 259207.11 | V44: =SUM(V36:V43) -> 2261936.8 | W44: =SUM(W36:W43) -> 1991798.8
C45: % of Total Revenue | D45: =IFERROR(D44/D$12,"nm") -> nm | E45: =IFERROR(E44/E$12,"nm") -> 318.36783 | F45: =IFERROR(F44/F$12,"nm") -> 311.04928 | G45: =IFERROR(G44/G$12,"nm") -> 22.771679 | H45: =IFERROR(H44/H$12,"nm") -> 11.432433 | I45: =IFERROR(I44/I$12,"nm") -> 7.7409375 | J45: =IFERROR(J44/J$12,"nm") -> 3.7650238 | K45: =IFERROR(K44/K$12,"nm") -> 1.9638254 | ... O45: =IFERROR(O44/O$12,"nm") -> 0.094182512 | Q45: =IFERROR(Q44/Q$12,"nm") -> 468.80519 | R45: =IFERROR(R44/R$12,"nm") -> 11.619296 | S45: =IFERROR(S44/S$12,"nm") -> 1.9095661 | T45: =IFERROR(T44/T$12,"nm") -> 0.26379584 | V45: =IFERROR(V44/V$12,"nm") -> 1.6746528 | W45: =IFERROR(W44/W$12,"nm") -> 0.21828984
C47: Other Income | D47: -226.25 | E47: -226.25 | F47: -226.25 | G47: -226.25 | H47: -226.25 | I47: -226.25 | J47: -226.25 | K47: -226.25 | L47: -226.25 | M47: -226.25 | N47: -226.25 | O47: -226.25 | Q47: =SUM(D47:F47) -> -678.75 | R47: =SUM(G47:I47) -> -678.75 | S47: =SUM(J47:L47) -> -678.75 | T47: =SUM(M47:O47) -> -678.75 | V47: =SUM(Q47:T47) -> -2715 | W47: =O47*12 -> -2715
C49: Net Income | D49: =D25-D44+D47 -> -236344.09 | E49: =E25-E44+E47 -> -243843.02 | F49: =F25-F44+F47 -> -238262.7 | G49: =G25-G44+G47 -> -263382.35 | H49: =H25-H44+H47 -> -278277.07 | I49: =I25-I44+I47 -> -296023.69 | J49: =J25-J44+J47 -> -352653.76 | K49: =K25-K44+K47 -> -449577.46 | ... O49: =O25-O44+O47 -> -1208927.9 | Q49: =Q25-Q44+Q47 -> -718449.81 | R49: =R25-R44+R47 -> -837683.11 | S49: =S25-S44+S47 -> -1370512 | T49: =T25-T44+T47 -> -2941548.4 | V49: =V25-V44+V47 -> -5868193.3 | W49: =W25-W44+W47 -> -12141024
C50: % of Total Revenue | D50: =IFERROR(D49/D$12,"nm") -> nm | E50: =IFERROR(E49/E$12,"nm") -> -318.74904 | F50: =IFERROR(F49/F$12,"nm") -> -311.45451 | G50: =IFERROR(G49/G$12,"nm") -> -24.94151 | H50: =IFERROR(H49/H$12,"nm") -> -13.67119 | I50: =IFERROR(I49/I$12,"nm") -> -10.073973 | J50: =IFERROR(J49/J$12,"nm") -> -6.1609672 | K50: =IFERROR(K49/K$12,"nm") -> -4.5260995 | ... O50: =IFERROR(O49/O$12,"nm") -> -2.846378 | Q50: =IFERROR(Q49/Q$12,"nm") -> -469.57504 | R50: =IFERROR(R49/R$12,"nm") -> -13.891926 | S50: =IFERROR(S49/S$12,"nm") -> -4.4750682 | T50: =IFERROR(T49/T$12,"nm") -> -2.9936224 | V50: =IFERROR(V49/V$12,"nm") -> -4.3445893 | W50: =IFERROR(W49/W$12,"nm") -> -1.3305874

Sheet CF
C2: 2026 Forecast
C3: Cash Flow Statement
C5: ($ in actual) | D5: 46023 | E5: =EOMONTH(D5,0)+1 -> 46054 | F5: =EOMONTH(E5,0)+1 -> 46082 | G5: =EOMONTH(F5,0)+1 -> 46113 | H5: =EOMONTH(G5,0)+1 -> 46143 | I5: =EOMONTH(H5,0)+1 -> 46174 | J5: =EOMONTH(I5,0)+1 -> 46204 | K5: =EOMONTH(J5,0)+1 -> 46235 | L5: =EOMONTH(K5,0)+1 -> 46266 | ... O5: =EOMONTH(N5,0)+1 -> 46357 | Q5: Q1 '26 | R5: Q2 '26 | S5: Q3 '26 | T5: Q4 '26 | V5: 2026E
C7: Operating Activities
C8: Net Income | D8: ='P&L'!D49 -> -236344.09 | E8: ='P&L'!E49 -> -243843.02 | F8: ='P&L'!F49 -> -238262.7 | G8: ='P&L'!G49 -> -263382.35 | H8: ='P&L'!H49 -> -278277.07 | I8: ='P&L'!I49 -> -296023.69 | J8: ='P&L'!J49 -> -352653.76 | K8: ='P&L'!K49 -> -449577.46 | ... O8: ='P&L'!O49 -> -1208927.9 | Q8: =SUM(D8:F8) -> -718449.81 | R8: =SUM(G8:I8) -> -837683.11 | S8: =SUM(J8:L8) -> -1370512 | T8: =SUM(M8:O8) -> -2941548.4 | V8: =SUM(Q8:T8) -> -5868193.3
C9: Depreciation & Amortization | D9: =-'P&L'!D47 -> 226.25 | E9: =-'P&L'!E47 -> 226.25 | F9: =-'P&L'!F47 -> 226.25 | G9: =-'P&L'!G47 -> 226.25 | H9: =-'P&L'!H47 -> 226.25 | I9: =-'P&L'!I47 -> 226.25 | J9: =-'P&L'!J47 -> 226.25 | K9: =-'P&L'!K47 -> 226.25 | ... O9: =-'P&L'!O47 -> 226.25 | Q9: =SUM(D9:F9) -> 678.75 | R9: =SUM(G9:I9) -> 678.75 | S9: =SUM(J9:L9) -> 678.75 | T9: =SUM(M9:O9) -> 678.75 | V9: =SUM(Q9:T9) -> 2715
C10: Accounts Receivable | D10: 0 | E10: 15200 | F10: ='Sales Forecast'!F59-'Sales Forecast'!F49 -> 0 | G10: ='Sales Forecast'!G59-'Sales Forecast'!G49 -> -9795 | H10: ='Sales Forecast'!H59-'Sales Forecast'!H49 -> -9795 | I10: ='Sales Forecast'!I59-'Sales Forecast'!I49 -> -9030 | J10: ='Sales Forecast'!J59-'Sales Forecast'!J49 -> -27855 | K10: ='Sales Forecast'!K59-'Sales Forecast'!K49 -> -42090 | L10: ='Sales Forecast'!L59-'Sales Forecast'!L49 -> -50355 | M10: ='Sales Forecast'!M59-'Sales Forecast'!M49 -> -83415 | ... O10: ='Sales Forecast'!O59-'Sales Forecast'!O49 -> -99945 | Q10: =SUM(D10:F10) -> 15200 | R10: =SUM(G10:I10) -> -28620 | S10: =SUM(J10:L10) -> -120300 | T10: =SUM(M10:O10) -> -275040 | V10: =SUM(Q10:T10) -> -408760
C11: Accounts Payable | D11: 0 | E11: 0 | F11: 0 | G11: 0 | H11: 0 | I11: 0 | J11: 0 | K11: 0 | L11: 0 | M11: 0 | N11: 0 | O11: 0 | Q11: =SUM(D11:F11) -> 0 | R11: =SUM(G11:I11) -> 0 | S11: =SUM(J11:L11) -> 0 | T11: =SUM(M11:O11) -> 0 | V11: =SUM(Q11:T11) -> 0
C12: Credit Card | D12: 0 | E12: 0 | F12: 0 | G12: 0 | H12: 0 | I12: 0 | J12: 0 | K12: 0 | L12: 0 | M12: 0 | N12: 0 | O12: 0 | Q12: =SUM(D12:F12) -> 0 | R12: =SUM(G12:I12) -> 0 | S12: =SUM(J12:L12) -> 0 | T12: =SUM(M12:O12) -> 0 | V12: =SUM(Q12:T12) -> 0
C13: Prepaid Expenses | D13: 0 | E13: 0 | F13: 0 | G13: 0 | H13: 0 | I13: 0 | J13: 0 | K13: 0 | L13: 0 | M13: 0 | N13: 0 | O13: 0 | Q13: =SUM(D13:F13) -> 0 | R13: =SUM(G13:I13) -> 0 | S13: =SUM(J13:L13) -> 0 | T13: =SUM(M13:O13) -> 0 | V13: =SUM(Q13:T13) -> 0
C14: Accrued Payroll | D14: ='Sales Forecast'!D63-'Sales Forecast'!D64+'Salaries, Wages, & Benefits'!F27 -> 0 | E14: ='Sales Forecast'!E63-'Sales Forecast'!E64+'Salaries, Wages, & Benefits'!G27 -> 153 | F14: ='Sales Forecast'!F63-'Sales Forecast'!F64+'Salaries, Wages, & Benefits'!H27 -> 0 | G14: ='Sales Forecast'!G63-'Sales Forecast'!G64+'Salaries, Wages, & Benefits'!I27 -> 1959 | H14: ='Sales Forecast'!H63-'Sales Forecast'!H64+'Salaries, Wages, & Benefits'!J27 -> 1959 | I14: ='Sales Forecast'!I63-'Sales Forecast'!I64+'Salaries, Wages, & Benefits'!K27 -> 1806 | J14: ='Sales Forecast'!J63-'Sales Forecast'!J64+'Salaries, Wages, & Benefits'!L27 -> 5571 | K14: ='Sales Forecast'!K63-'Sales Forecast'!K64+'Salaries, Wages, & Benefits'!M27 -> 8418 | ... N14: ='Sales Forecast'!N63-'Sales Forecast'!N64+'Salaries, Wages, & Benefits'!P27 -> 18336 | O14: ='Sales Forecast'!O63-'Sales Forecast'!O64-SUM('Salaries, Wages, & Benefits'!F27:Q27) -> 19989 | Q14: =SUM(D14:F14) -> 153 | R14: =SUM(G14:I14) -> 5724 | S14: =SUM(J14:L14) -> 24060 | T14: =SUM(M14:O14) -> 55008 | V14: =SUM(Q14:T14) -> 84945
C15: Other | D15: 0 | E15: 0 | F15: 0 | G15: 0 | H15: 0 | I15: 0 | J15: 0 | K15: 0 | L15: 0 | M15: 0 | N15: 0 | O15: 0 | Q15: =SUM(D15:F15) -> 0 | R15: =SUM(G15:I15) -> 0 | S15: =SUM(J15:L15) -> 0 | T15: =SUM(M15:O15) -> 0 | V15: =SUM(Q15:T15) -> 0
C16: Cash from Operations | D16: =SUM(D8:D15) -> -236117.84 | E16: =SUM(E8:E15) -> -228263.77 | F16: =SUM(F8:F15) -> -238036.45 | G16: =SUM(G8:G15) -> -270992.1 | H16: =SUM(H8:H15) -> -285886.82 | I16: =SUM(I8:I15) -> -303021.44 | J16: =SUM(J8:J15) -> -374711.51 | K16: =SUM(K8:K15) -> -483023.21 | ... O16: =SUM(O8:O15) -> -1288657.6 | Q16: =SUM(Q8:Q15) -> -702418.06 | R16: =SUM(R8:R15) -> -859900.36 | S16: =SUM(S8:S15) -> -1466073.3 | T16: =SUM(T8:T15) -> -3160901.6 | V16: =SUM(V8:V15) -> -6189293.3
C18: Investing Activities
C19: Office Equipment | D19: -1000 | E19: -1000 | F19: -1000 | G19: -1000 | H19: -1000 | I19: -1000 | J19: -1000 | K19: -1000 | L19: -1000 | M19: -1000 | N19: -1000 | O19: -1000 | Q19: =SUM(D19:F19) -> -3000 | R19: =SUM(G19:I19) -> -3000 | S19: =SUM(J19:L19) -> -3000 | T19: =SUM(M19:O19) -> -3000 | V19: =SUM(Q19:T19) -> -12000
C20: Other | D20: 0 | E20: 0 | F20: 0 | G20: 0 | H20: 0 | I20: 0 | J20: 0 | K20: 0 | L20: 0 | M20: 0 | N20: 0 | O20: 0 | Q20: =SUM(D20:F20) -> 0 | R20: =SUM(G20:I20) -> 0 | S20: =SUM(J20:L20) -> 0 | T20: =SUM(M20:O20) -> 0 | V20: =SUM(Q20:T20) -> 0
C21: Cash from Investing | D21: =SUM(D19:D20) -> -1000 | E21: =SUM(E19:E20) -> -1000 | F21: =SUM(F19:F20) -> -1000 | G21: =SUM(G19:G20) -> -1000 | H21: =SUM(H19:H20) -> -1000 | I21: =SUM(I19:I20) -> -1000 | J21: =SUM(J19:J20) -> -1000 | K21: =SUM(K19:K20) -> -1000 | ... O21: =SUM(O19:O20) -> -1000 | Q21: =SUM(Q19:Q20) -> -3000 | R21: =SUM(R19:R20) -> -3000 | S21: =SUM(S19:S20) -> -3000 | T21: =SUM(T19:T20) -> -3000 | V21: =SUM(V19:V20) -> -12000
C23: Financing Activities
C24: Loans from Officers | D24: 0 | E24: 0 | F24: 0 | G24: 0 | H24: 0 | I24: 0 | J24: 0 | K24: 0 | L24: 0 | M24: 0 | N24: 0 | O24: 0 | Q24: =SUM(D24:F24) -> 0 | R24: =SUM(G24:I24) -> 0 | S24: =SUM(J24:L24) -> 0 | T24: =SUM(M24:O24) -> 0 | V24: =SUM(Q24:T24) -> 0
C25: SAFE | D25: 0 | E25: 0 | F25: 0 | G25: 1000000 | H25: 1000000 | I25: 0 | J25: 0 | K25: 0 | L25: 0 | M25: 0 | N25: 0 | O25: 0 | Q25: =SUM(D25:F25) -> 0 | R25: =SUM(G25:I25) -> 2000000 | S25: =SUM(J25:L25) -> 0 | T25: =SUM(M25:O25) -> 0 | V25: =SUM(Q25:T25) -> 2000000
C26: Other | D26: 0 | E26: 0 | F26: 0 | G26: 0 | H26: 0 | I26: 0 | J26: 0 | K26: 0 | L26: 0 | M26: 0 | N26: 0 | O26: 0 | Q26: =SUM(D26:F26) -> 0 | R26: =SUM(G26:I26) -> 0 | S26: =SUM(J26:L26) -> 0 | T26: =SUM(M26:O26) -> 0 | V26: =SUM(Q26:T26) -> 0
C27: Cash from Financing | D27: =SUM(D24:D26) -> 0 | E27: =SUM(E24:E26) -> 0 | F27: =SUM(F24:F26) -> 0 | G27: =SUM(G24:G26) -> 1000000 | H27: =SUM(H24:H26) -> 1000000 | I27: =SUM(I24:I26) -> 0 | J27: =SUM(J24:J26) -> 0 | K27: =SUM(K24:K26) -> 0 | ... O27: =SUM(O24:O26) -> 0 | Q27: =SUM(Q24:Q26) -> 0 | R27: =SUM(R24:R26) -> 2000000 | S27: =SUM(S24:S26) -> 0 | T27: =SUM(T24:T26) -> 0 | V27: =SUM(V24:V26) -> 2000000
C29: Net Increase in Cash | D29: =D16+D21+D27 -> -237117.84 | E29: =E16+E21+E27 -> -229263.77 | F29: =F16+F21+F27 -> -239036.45 | G29: =G16+G21+G27 -> 728007.9 | H29: =H16+H21+H27 -> 713113.18 | I29: =I16+I21+I27 -> -304021.44 | J29: =J16+J21+J27 -> -375711.51 | K29: =K16+K21+K27 -> -484023.21 | ... O29: =O16+O21+O27 -> -1289657.6 | Q29: =SUM(D29:F29) -> -705418.06 | R29: =SUM(G29:I29) -> 1137099.6 | S29: =SUM(J29:L29) -> -1469073.3 | T29: =SUM(M29:O29) -> -3163901.6 | V29: =SUM(Q29:T29) -> -4201293.3
C30: Beginning Cash Balance | D30: 2200000 | E30: =D31 -> 1962882.2 | F30: =E31 -> 1733618.4 | G30: =F31 -> 1494581.9 | H30: =G31 -> 2222589.8 | I30: =H31 -> 2935703 | J30: =I31 -> 2631681.6 | K30: =J31 -> 2255970.1 | L30: =K31 -> 1771946.9 | ... O30: =N31 -> -711635.68 | Q30: =D30 -> 2200000 | R30: =G30 -> 1494581.9 | S30: =J30 -> 2631681.6 | T30: =M30 -> 1162608.3 | V30: =D30 -> 2200000
C31: Ending Cash Balance | D31: =SUM(D29:D30) -> 1962882.2 | E31: =SUM(E29:E30) -> 1733618.4 | F31: =SUM(F29:F30) -> 1494581.9 | G31: =SUM(G29:G30) -> 2222589.8 | H31: =SUM(H29:H30) -> 2935703 | I31: =SUM(I29:I30) -> 2631681.6 | J31: =SUM(J29:J30) -> 2255970.1 | K31: =SUM(K29:K30) -> 1771946.9 | ... O31: =SUM(O29:O30) -> -2001293.3 | Q31: =SUM(Q29:Q30) -> 1494581.9 | R31: =SUM(R29:R30) -> 2631681.6 | S31: =SUM(S29:S30) -> 1162608.3 | T31: =SUM(T29:T30) -> -2001293.3 | V31: =SUM(V29:V30) -> -2001293.3
C32: Remaining Cash Burn (Months) | D32: =ROUNDDOWN(D31/-D16,0) -> 8 | E32: =ROUNDDOWN(E31/-E16,0) -> 7 | F32: =ROUNDDOWN(F31/-F16,0) -> 6 | G32: =ROUNDDOWN(G31/-G16,0) -> 8 | H32: =ROUNDDOWN(H31/-H16,0) -> 10 | I32: =ROUNDDOWN(I31/-I16,0) -> 8 | J32: =ROUNDDOWN(J31/-J16,0) -> 6 | K32: =ROUNDDOWN(K31/-K16,0) -> 3 | ... O32: =ROUNDDOWN(O31/-O16,0) -> -1

Sheet Revenue >>>

Sheet Product & Pricing List
G1: Scenario: | H1: Base | I1: =IF(H1="Low",1,IF(H1="Base",2,3)) -> 2
H3: Pricing | K3: Annualized | P3: Active
C4: Product | D4: Customer | E4: Type | F4: Frequency | G4: Metric | H4: Low | I4: Base | J4: High | K4: Low | L4: Base | M4: High | P4: Scenario
C5: AI Monitoring | D5: Federal | E5: Recurring | F5: Monthly | G5: Per AI Model | H5: 1500 | I5: 1500 | J5: 1500 | K5: =H5*12 -> 18000 | L5: =I5*12 -> 18000 | M5: =J5*12 -> 18000 | P5: =CHOOSE($I$1,H5,I5,J5) -> 1500
C6: AI Monitoring | D6: Commercial | E6: Recurring | F6: Monthly | G6: Per AI Model | H6: 1500 | I6: 1500 | J6: 1500 | K6: =H6*12 -> 18000 | L6: =I6*12 -> 18000 | M6: =J6*12 -> 18000 | P6: =CHOOSE($I$1,H6,I6,J6) -> 1500
C7: Integration Fee | D7: Both | E7: Non-Recurring | F7: Upfront | G7: Per AI Model | H7: 0 | I7: 0 | J7: 0 | P7: =CHOOSE($I$1,H7,I7,J7) -> 0
C8: Professional Services | D8: Both | E8: Non-Recurring | F8: Upfront | G8: Per Hour | H8: 255 | I8: 255 | J8: 255 | P8: =CHOOSE($I$1,H8,I8,J8) -> 255
C10: FedRAMP Path | D10: High
C11: AFFIRM Base Subscription - High | D11: 100000

Sheet Solution Offering
D1: Scenario: | E1: High | F1: =IF(E1="Low",1,IF(E1="Base",2,3)) -> 3
E3: # of Units | J3: Active
C4: Product | D4: Unit | E4: Low | F4: Base | G4: High | J4: Scenario
C5: AI Monitoring | D5: Subscription | E5: 5 | F5: 5 | G5: 5 | J5: =CHOOSE($F$1,E5,F5,G5) -> 5
C6: Integration Fee | D6: AI Model | E6: 0 | F6: 0 | G6: 0 | J6: =CHOOSE($F$1,E6,F6,G6) -> 0
C7: Professional Services - Implementation | D7: Hours | E7: 3 | F7: 3 | G7: 3 | J7: =CHOOSE($F$1,E7,F7,G7) -> 3
C8: Professional Services - Monthly | D8: Hours | E8: 2.5 | F8: 3 | G8: 3 | J8: =CHOOSE($F$1,E8,F8,G8) -> 3
E10: Month
C11: Professional Services Split | E11: 1 | F11: 2 | G11: 3+
C12: =C7 -> Professional Services - Implementation | E12: 1 | F12: 0 | G12: 0
C13: =C8 -> Professional Services - Monthly | E13: 0 | F13: 0 | G13: 1
C15: Annualized Solution Offering - Federal
C16: =C5 -> AI Monitoring | E16: =E5*'Product & Pricing List'!H5*12 -> 90000 | F16: =F5*'Product & Pricing List'!I5*12 -> 90000 | G16: =G5*'Product & Pricing List'!J5*12 -> 90000 | J16: =CHOOSE($F$1,E16,F16,G16) -> 90000
C17: =C6 -> Integration Fee | E17: =E6*'Product & Pricing List'!H7 -> 0 | F17: =F6*'Product & Pricing List'!I7 -> 0 | G17: =G6*'Product & Pricing List'!J7 -> 0 | J17: =CHOOSE($F$1,E17,F17,G17) -> 0
C18: =C7 -> Professional Services - Implementation | E18: =E7*'Product & Pricing List'!H8 -> 765 | F18: =F7*'Product & Pricing List'!I8 -> 765 | G18: =G7*'Product & Pricing List'!J8 -> 765 | J18: =CHOOSE($F$1,E18,F18,G18) -> 765
C19: =C8 -> Professional Services - Monthly | E19: =E8*'Product & Pricing List'!H8*12 -> 7650 | F19: =F8*'Product & Pricing List'!I8*12 -> 9180 | G19: =G8*'Product & Pricing List'!J8*12 -> 9180 | J19: =CHOOSE($F$1,E19,F19,G19) -> 9180
C20: Total Annualized Solution Offering - Federal | E20: =SUM(E16:E19) -> 98415 | F20: =SUM(F16:F19) -> 99945 | G20: =SUM(G16:G19) -> 99945 | J20: =SUM(J16:J19) -> 99945
C21: % Software | E21: =SUM(E16:E16)/E20 -> 0.91449474 | F21: =SUM(F16:F16)/F20 -> 0.90049527 | G21: =SUM(G16:G16)/G20 -> 0.90049527 | J21: =SUM(J16:J16)/J20 -> 0.90049527
C22: % Services | E22: =SUM(E17:E19)/E20 -> 0.085505258 | F22: =SUM(F17:F19)/F20 -> 0.099504728 | G22: =SUM(G17:G19)/G20 -> 0.099504728 | J22: =SUM(J17:J19)/J20 -> 0.099504728
C24: Annualized Solution Offering - Commercial
C25: =C16 -> AI Monitoring | E25: =E5*'Product & Pricing List'!H6*12 -> 90000 | F25: =F5*'Product & Pricing List'!I6*12 -> 90000 | G25: =G5*'Product & Pricing List'!J6*12 -> 90000 | J25: =CHOOSE($F$1,E25,F25,G25) -> 90000
C26: =C17 -> Integration Fee | E26: =E6*'Product & Pricing List'!H7 -> 0 | F26: =F6*'Product & Pricing List'!I7 -> 0 | G26: =G6*'Product & Pricing List'!J7 -> 0 | J26: =CHOOSE($F$1,E26,F26,G26) -> 0
C27: =C18 -> Professional Services - Implementation | E27: =E7*'Product & Pricing List'!H8 -> 765 | F27: =F7*'Product & Pricing List'!I8 -> 765 | G27: =G7*'Product & Pricing List'!J8 -> 765 | J27: =CHOOSE($F$1,E27,F27,G27) -> 765
C28: =C19 -> Professional Services - Monthly | E28: =E8*'Product & Pricing List'!H8*12 -> 7650 | F28: =F8*'Product & Pricing List'!I8*12 -> 9180 | G28: =G8*'Product & Pricing List'!J8*12 -> 9180 | J28: =CHOOSE($F$1,E28,F28,G28) -> 9180
C29: Total Annualized Solution Offering - Commercial | E29: =SUM(E25:E28) -> 98415 | F29: =SUM(F25:F28) -> 99945 | G29: =SUM(G25:G28) -> 99945 | J29: =SUM(J25:J28) -> 99945
C30: % Software | E30: =SUM(E25:E25)/E29 -> 0.91449474 | F30: =SUM(F25:F25)/F29 -> 0.90049527 | G30: =SUM(G25:G25)/G29 -> 0.90049527 | J30: =SUM(J25:J25)/J29 -> 0.90049527
C31: % Services | E31: =SUM(E26:E28)/E29 -> 0.085505258 | F31: =SUM(F26:F28)/F29 -> 0.099504728 | G31: =SUM(G26:G28)/G29 -> 0.099504728 | J31: =SUM(J26:J28)/J29 -> 0.099504728

Sheet Sales Forecast
C2: 2026 Forecast
C3: Sales Forecast
D5: 46023 | E5: =EOMONTH(D5,0)+1 -> 46054 | F5: =EOMONTH(E5,0)+1 -> 46082 | G5: =EOMONTH(F5,0)+1 -> 46113 | H5: =EOMONTH(G5,0)+1 -> 46143 | I5: =EOMONTH(H5,0)+1 -> 46174 | J5: =EOMONTH(I5,0)+1 -> 46204 | K5: =EOMONTH(J5,0)+1 -> 46235 | L5: =EOMONTH(K5,0)+1 -> 46266 | ... O5: =EOMONTH(N5,0)+1 -> 46357 | Q5: Q1 '26 | R5: Q2 '26 | S5: Q3 '26 | T5: Q4 '26 | V5: 2026E
C7: Govt / International Customers | D7: 0 | E7: 0 | F7: 0 | G7: 0 | H7: 0 | I7: 1 | J7: 0 | K7: 1 | L7: 0 | M7: 1 | N7: 0 | O7: 1 | Q7: =SUM(D7:F7) -> 0 | R7: =SUM(G7:I7) -> 1 | S7: =SUM(J7:L7) -> 1 | T7: =SUM(M7:O7) -> 2 | V7: =SUM(Q7:T7) -> 4
C8: Commercial Customers | D8: 1 | E8: 1 | F8: 1 | G8: 3 | H8: 5 | I8: 5 | J8: 10 | K8: 10 | L8: 12 | M8: 12 | N8: 14 | O8: 14 | Q8: =SUM(D8:F8) -> 3 | R8: =SUM(G8:I8) -> 13 | S8: =SUM(J8:L8) -> 32 | T8: =SUM(M8:O8) -> 40 | V8: =SUM(Q8:T8) -> 88
C9: Cumulative - Federal | D9: =SUM($D$7:D7) -> 0 | E9: =SUM($D$7:E7) -> 0 | F9: =SUM($D$7:F7) -> 0 | G9: =SUM($D$7:G7) -> 0 | H9: =SUM($D$7:H7) -> 0 | I9: =SUM($D$7:I7) -> 1 | J9: =SUM($D$7:J7) -> 1 | K9: =SUM($D$7:K7) -> 2 | ... O9: =SUM($D$7:O7) -> 4 | Q9: =F9 -> 0 | R9: =I9 -> 1 | S9: =L9 -> 2 | T9: =O9 -> 4 | V9: =T9 -> 4
C10: Cumulative - Commercial | D10: =SUM($D$8:D8) -> 1 | E10: =SUM($D$8:E8) -> 2 | F10: =SUM($D$8:F8) -> 3 | G10: =SUM($D$8:G8) -> 6 | H10: =SUM($D$8:H8) -> 11 | I10: =SUM($D$8:I8) -> 16 | J10: =SUM($D$8:J8) -> 26 | K10: =SUM($D$8:K8) -> 36 | ... O10: =SUM($D$8:O8) -> 88 | Q10: =F10 -> 3 | R10: =I10 -> 16 | S10: =L10 -> 48 | T10: =O10 -> 88 | V10: =T10 -> 88
C11: Cumulative - Total | D11: =SUM(D9:D10) -> 1 | E11: =SUM(E9:E10) -> 2 | F11: =SUM(F9:F10) -> 3 | G11: =SUM(G9:G10) -> 6 | H11: =SUM(H9:H10) -> 11 | I11: =SUM(I9:I10) -> 17 | J11: =SUM(J9:J10) -> 27 | K11: =SUM(K9:K10) -> 38 | ... O11: =SUM(O9:O10) -> 92 | Q11: =F11 -> 3 | R11: =I11 -> 17 | S11: =L11 -> 50 | T11: =O11 -> 92 | V11: =T11 -> 92
C13: Customers by Phase
C14: Govt Customers
C15: Month 1 | D15: =SUM($D$7:D7) -> 0 | E15: =SUM($D$7:E7) -> 0 | F15: =SUM($D$7:F7) -> 0 | G15: =SUM($D$7:G7) -> 0 | H15: =SUM($D$7:H7) -> 0 | I15: =SUM($D$7:I7) -> 1 | J15: =SUM($D$7:J7) -> 1 | K15: =SUM($D$7:K7) -> 2 | ... O15: =SUM($D$7:O7) -> 4 | Q15: =F15 -> 0 | R15: =I15 -> 1 | S15: =L15 -> 2 | T15: =O15 -> 4 | V15: =T15 -> 4
C16: Month 2 | D16: 0 | E16: 0 | F16: =SUM($D$7:D7) -> 0 | G16: =SUM($D$7:E7) -> 0 | H16: =SUM($D$7:F7) -> 0 | I16: =SUM($D$7:G7) -> 0 | J16: =SUM($D$7:H7) -> 0 | K16: =SUM($D$7:I7) -> 1 | L16: =SUM($D$7:J7) -> 1 | M16: =SUM($D$7:K7) -> 2 | ... O16: =SUM($D$7:M7) -> 3 | Q16: =F16 -> 0 | R16: =I16 -> 0 | S16: =L16 -> 1 | T16: =O16 -> 3 | V16: =T16 -> 3
C17: Month 3+ | D17: 0 | E17: 0 | F17: 0 | G17: =SUM($D$7:D7) -> 0 | H17: =SUM($D$7:E7) -> 0 | I17: =SUM($D$7:F7) -> 0 | J17: =SUM($D$7:G7) -> 0 | K17: =SUM($D$7:H7) -> 0 | L17: =SUM($D$7:I7) -> 1 | M17: =SUM($D$7:J7) -> 1 | N17: =SUM($D$7:K7) -> 2 | O17: =SUM($D$7:L7) -> 2 | Q17: =F17 -> 0 | R17: =I17 -> 0 | S17: =L17 -> 1 | T17: =O17 -> 2 | V17: =T17 -> 2
C18: Commercial
C19: Month 1 | D19: =SUM($D$8:D8) -> 1 | E19: =SUM($D$8:E8) -> 2 | F19: =SUM($D$8:F8) -> 3 | G19: =SUM($D$8:G8) -> 6 | H19: =SUM($D$8:H8) -> 11 | I19: =SUM($D$8:I8) -> 16 | J19: =SUM($D$8:J8) -> 26 | K19: =SUM($D$8:K8) -> 36 | ... O19: =SUM($D$8:O8) -> 88 | Q19: =F19 -> 3 | R19: =I19 -> 16 | S19: =L19 -> 48 | T19: =O19 -> 88 | V19: =T19 -> 88
C20: Month 2 | D20: 0 | E20: 0 | F20: =SUM($D$8:D8) -> 1 | G20: =SUM($D$8:E8) -> 2 | H20: =SUM($D$8:F8) -> 3 | I20: =SUM($D$8:G8) -> 6 | J20: =SUM($D$8:H8) -> 11 | K20: =SUM($D$8:I8) -> 16 | L20: =SUM($D$8:J8) -> 26 | M20: =SUM($D$8:K8) -> 36 | ... O20: =SUM($D$8:M8) -> 60 | Q20: =F20 -> 1 | R20: =I20 -> 6 | S20: =L20 -> 26 | T20: =O20 -> 60 | V20: =T20 -> 60
C21: Month 3+ | D21: 0 | E21: 0 | F21: 0 | G21: =SUM($D$8:D8) -> 1 | H21: =SUM($D$8:E8) -> 2 | I21: =SUM($D$8:F8) -> 3 | J21: =SUM($D$8:G8) -> 6 | K21: =SUM($D$8:H8) -> 11 | L21: =SUM($D$8:I8) -> 16 | M21: =SUM($D$8:J8) -> 26 | N21: =SUM($D$8:K8) -> 36 | O21: =SUM($D$8:L8) -> 48 | Q21: =F21 -> 0 | R21: =I21 -> 3 | S21: =L21 -> 16 | T21: =O21 -> 48 | V21: =T21 -> 48
C23: Products
C24: Federal
C25: AI Monitoring | D25: =D17*'Solution Offering'!$J5 -> 0 | E25: =E17*'Solution Offering'!$J5 -> 0 | F25: =F17*'Solution Offering'!$J5 -> 0 | G25: =G17*'Solution Offering'!$J5 -> 0 | H25: =H17*'Solution Offering'!$J5 -> 0 | I25: =I17*'Solution Offering'!$J5 -> 0 | J25: =J17*'Solution Offering'!$J5 -> 0 | K25: =K17*'Solution Offering'!$J5 -> 0 | ... O25: =O17*'Solution Offering'!$J5 -> 10 | Q25: =F25 -> 0 | R25: =I25 -> 0 | S25: =L25 -> 5 | T25: =O25 -> 10 | V25: =T25 -> 10
C26: Integration Fee | D26: 0 | E26: =(E25-D25)*'Solution Offering'!$J6 -> 0 | F26: =(F25-E25)*'Solution Offering'!$J6 -> 0 | G26: =(G25-F25)*'Solution Offering'!$J6 -> 0 | H26: =(H25-G25)*'Solution Offering'!$J6 -> 0 | I26: =(I25-H25)*'Solution Offering'!$J6 -> 0 | J26: =(J25-I25)*'Solution Offering'!$J6 -> 0 | K26: =(K25-J25)*'Solution Offering'!$J6 -> 0 | L26: =(L25-K25)*'Solution Offering'!$J6 -> 0 | ... O26: =(O25-N25)*'Solution Offering'!$J6 -> 0 | Q26: =SUM(D26:F26) -> 0 | R26: =SUM(G26:I26) -> 0 | S26: =SUM(J26:L26) -> 0 | T26: =SUM(M26:O26) -> 0 | V26: =SUM(Q26:T26) -> 0
C27: Professional Services - Implementation | D27: 0 | E27: =(E15-D15)*'Solution Offering'!$J7*'Solution Offering'!$E$12+(E16-D16)*'Solution Offering'!$J7*'Solution Offering'!$F$12+('Sales Forecast'!E17-'Sales Forecast'!D17)*'Solution Offering'!$J7*'Solution Offering'!$G$12 -> 0 | F27: =(F15-E15)*'Solution Offering'!$J7*'Solution Offering'!$E$12+(F16-E16)*'Solution Offering'!$J7*'Solution Offering'!$F$12+('Sales Forecast'!F17-'Sales Forecast'!E17)*'Solution Offering'!$J7*'Solution Offering'!$G$12 -> 0 | G27: =(G15-F15)*'Solution Offering'!$J7*'Solution Offering'!$E$12+(G16-F16)*'Solution Offering'!$J7*'Solution Offering'!$F$12+('Sales Forecast'!G17-'Sales Forecast'!F17)*'Solution Offering'!$J7*'Solution Offering'!$G$12 -> 0 | H27: =(H15-G15)*'Solution Offering'!$J7*'Solution Offering'!$E$12+(H16-G16)*'Solution Offering'!$J7*'Solution Offering'!$F$12+('Sales Forecast'!H17-'Sales Forecast'!G17)*'Solution Offering'!$J7*'Solution Offering'!$G$12 -> 0 | I27: =(I15-H15)*'Solution Offering'!$J7*'Solution Offering'!$E$12+(I16-H16)*'Solution Offering'!$J7*'Solution Offering'!$F$12+('Sales Forecast'!I17-'Sales Forecast'!H17)*'Solution Offering'!$J7*'Solution Offering'!$G$12 -> 3 | J27: =(J15-I15)*'Solution Offering'!$J7*'Solution Offering'!$E$12+(J16-I16)*'Solution Offering'!$J7*'Solution Offering'!$F$12+('Sales Forecast'!J17-'Sales Forecast'!I17)*'Solution Offering'!$J7*'Solution Offering'!$G$12 -> 0 | K27: =(K15-J15)*'Solution Offering'!$J7*'Solution Offering'!$E$12+(K16-J16)*'Solution Offering'!$J7*'Solution Offering'!$F$12+('Sales Forecast'!K17-'Sales Forecast'!J17)*'Solution Offering'!$J7*'Solution Offering'!$G$12 -> 3 | L27: =(L15-K15)*'Solution Offering'!$J7*'Solution Offering'!$E$12+(L16-K16)*'Solution Offering'!$J7*'Solution Offering'!$F$12+('Sales Forecast'!L17-'Sales Forecast'!K17)*'Solution Offering'!$J7*'Solution Offering'!$G$12 -> 0 | ... O27: =(O15-N15)*'Solution Offering'!$J7*'Solution Offering'!$E$12+(O16-N16)*'Solution Offering'!$J7*'Solution Offering'!$F$12+('Sales Forecast'!O17-'Sales Forecast'!N17)*'Solution Offering'!$J7*'Solution Offering'!$G$12 -> 3 | Q27: =SUM(D27:F27) -> 0 | R27: =SUM(G27:I27) -> 3 | S27: =SUM(J27:L27) -> 3 | T27: =SUM(M27:O27) -> 6 | V27: =SUM(Q27:T27) -> 12
C28: Professional Services - Monthly | D28: =D15*'Solution Offering'!$J8*'Solution Offering'!$E$13+'Sales Forecast'!D16*'Solution Offering'!$J8*'Solution Offering'!$F$13+'Sales Forecast'!D17*'Solution Offering'!$J8*'Solution Offering'!$G$13 -> 0 | E28: =E15*'Solution Offering'!$J8*'Solution Offering'!$E$13+'Sales Forecast'!E16*'Solution Offering'!$J8*'Solution Offering'!$F$13+'Sales Forecast'!E17*'Solution Offering'!$J8*'Solution Offering'!$G$13 -> 0 | F28: =F15*'Solution Offering'!$J8*'Solution Offering'!$E$13+'Sales Forecast'!F16*'Solution Offering'!$J8*'Solution Offering'!$F$13+'Sales Forecast'!F17*'Solution Offering'!$J8*'Solution Offering'!$G$13 -> 0 | G28: =G15*'Solution Offering'!$J8*'Solution Offering'!$E$13+'Sales Forecast'!G16*'Solution Offering'!$J8*'Solution Offering'!$F$13+'Sales Forecast'!G17*'Solution Offering'!$J8*'Solution Offering'!$G$13 -> 0 | H28: =H15*'Solution Offering'!$J8*'Solution Offering'!$E$13+'Sales Forecast'!H16*'Solution Offering'!$J8*'Solution Offering'!$F$13+'Sales Forecast'!H17*'Solution Offering'!$J8*'Solution Offering'!$G$13 -> 0 | I28: =I15*'Solution Offering'!$J8*'Solution Offering'!$E$13+'Sales Forecast'!I16*'Solution Offering'!$J8*'Solution Offering'!$F$13+'Sales Forecast'!I17*'Solution Offering'!$J8*'Solution Offering'!$G$13 -> 0 | J28: =J15*'Solution Offering'!$J8*'Solution Offering'!$E$13+'Sales Forecast'!J16*'Solution Offering'!$J8*'Solution Offering'!$F$13+'Sales Forecast'!J17*'Solution Offering'!$J8*'Solution Offering'!$G$13 -> 0 | K28: =K15*'Solution Offering'!$J8*'Solution Offering'!$E$13+'Sales Forecast'!K16*'Solution Offering'!$J8*'Solution Offering'!$F$13+'Sales Forecast'!K17*'Solution Offering'!$J8*'Solution Offering'!$G$13 -> 0 | ... O28: =O15*'Solution Offering'!$J8*'Solution Offering'!$E$13+'Sales Forecast'!O16*'Solution Offering'!$J8*'Solution Offering'!$F$13+'Sales Forecast'!O17*'Solution Offering'!$J8*'Solution Offering'!$G$13 -> 6 | Q28: =SUM(D28:F28) -> 0 | R28: =SUM(G28:I28) -> 0 | S28: =SUM(J28:L28) -> 3 | T28: =SUM(M28:O28) -> 15 | V28: =SUM(Q28:T28) -> 18
C29: Commercial
C30: AI Monitoring | D30: =D21*'Solution Offering'!$J5 -> 0 | E30: =E21*'Solution Offering'!$J5 -> 0 | F30: =F21*'Solution Offering'!$J5 -> 0 | G30: =G21*'Solution Offering'!$J5 -> 5 | H30: =H21*'Solution Offering'!$J5 -> 10 | I30: =I21*'Solution Offering'!$J5 -> 15 | J30: =J21*'Solution Offering'!$J5 -> 30 | K30: =K21*'Solution Offering'!$J5 -> 55 | ... O30: =O21*'Solution Offering'!$J5 -> 240 | Q30: =F30 -> 0 | R30: =I30 -> 15 | S30: =L30 -> 80 | T30: =O30 -> 240 | V30: =T30 -> 240
C31: Integration Fee | D31: 0 | E31: =(E30-D30)*'Solution Offering'!$J6 -> 0 | F31: =(F30-E30)*'Solution Offering'!$J6 -> 0 | G31: =(G30-F30)*'Solution Offering'!$J6 -> 0 | H31: =(H30-G30)*'Solution Offering'!$J6 -> 0 | I31: =(I30-H30)*'Solution Offering'!$J6 -> 0 | J31: =(J30-I30)*'Solution Offering'!$J6 -> 0 | K31: =(K30-J30)*'Solution Offering'!$J6 -> 0 | L31: =(L30-K30)*'Solution Offering'!$J6 -> 0 | ... O31: =(O30-N30)*'Solution Offering'!$J6 -> 0 | Q31: =SUM(D31:F31) -> 0 | R31: =SUM(G31:I31) -> 0 | S31: =SUM(J31:L31) -> 0 | T31: =SUM(M31:O31) -> 0 | V31: =SUM(Q31:T31) -> 0
C32: Professional Services - Implementation | D32: 0 | E32: =(E19-D19)*'Solution Offering'!$J7*'Solution Offering'!$E$12+('Sales Forecast'!E20-'Sales Forecast'!D20)*'Solution Offering'!$J7*'Solution Offering'!$F$12+('Sales Forecast'!E21-'Sales Forecast'!D21)*'Solution Offering'!$J7*'Solution Offering'!$G$12 -> 3 | F32: =(F19-E19)*'Solution Offering'!$J7*'Solution Offering'!$E$12+('Sales Forecast'!F20-'Sales Forecast'!E20)*'Solution Offering'!$J7*'Solution Offering'!$F$12+('Sales Forecast'!F21-'Sales Forecast'!E21)*'Solution Offering'!$J7*'Solution Offering'!$G$12 -> 3 | G32: =(G19-F19)*'Solution Offering'!$J7*'Solution Offering'!$E$12+('Sales Forecast'!G20-'Sales Forecast'!F20)*'Solution Offering'!$J7*'Solution Offering'!$F$12+('Sales Forecast'!G21-'Sales Forecast'!F21)*'Solution Offering'!$J7*'Solution Offering'!$G$12 -> 9 | H32: =(H19-G19)*'Solution Offering'!$J7*'Solution Offering'!$E$12+('Sales Forecast'!H20-'Sales Forecast'!G20)*'Solution Offering'!$J7*'Solution Offering'!$F$12+('Sales Forecast'!H21-'Sales Forecast'!G21)*'Solution Offering'!$J7*'Solution Offering'!$G$12 -> 15 | I32: =(I19-H19)*'Solution Offering'!$J7*'Solution Offering'!$E$12+('Sales Forecast'!I20-'Sales Forecast'!H20)*'Solution Offering'!$J7*'Solution Offering'!$F$12+('Sales Forecast'!I21-'Sales Forecast'!H21)*'Solution Offering'!$J7*'Solution Offering'!$G$12 -> 15 | J32: =(J19-I19)*'Solution Offering'!$J7*'Solution Offering'!$E$12+('Sales Forecast'!J20-'Sales Forecast'!I20)*'Solution Offering'!$J7*'Solution Offering'!$F$12+('Sales Forecast'!J21-'Sales Forecast'!I21)*'Solution Offering'!$J7*'Solution Offering'!$G$12 -> 30 | K32: =(K19-J19)*'Solution Offering'!$J7*'Solution Offering'!$E$12+('Sales Forecast'!K20-'Sales Forecast'!J20)*'Solution Offering'!$J7*'Solution Offering'!$F$12+('Sales Forecast'!K21-'Sales Forecast'!J21)*'Solution Offering'!$J7*'Solution Offering'!$G$12 -> 30 | L32: =(L19-K19)*'Solution Offering'!$J7*'Solution Offering'!$E$12+('Sales Forecast'!L20-'Sales Forecast'!K20)*'Solution Offering'!$J7*'Solution Offering'!$F$12+('Sales Forecast'!L21-'Sales Forecast'!K21)*'Solution Offering'!$J7*'Solution Offering'!$G$12 -> 36 | ... O32: =(O19-N19)*'Solution Offering'!$J7*'Solution Offering'!$E$12+('Sales Forecast'!O20-'Sales Forecast'!N20)*'Solution Offering'!$J7*'Solution Offering'!$F$12+('Sales Forecast'!O21-'Sales Forecast'!N21)*'Solution Offering'!$J7*'Solution Offering'!$G$12 -> 42 | Q32: =SUM(D32:F32) -> 6 | R32: =SUM(G32:I32) -> 39 | S32: =SUM(J32:L32) -> 96 | T32: =SUM(M32:O32) -> 120 | V32: =SUM(Q32:T32) -> 261
C33: Professional Services - Monthly | D33: =D19*'Solution Offering'!$J8*'Solution Offering'!$E$13+'Sales Forecast'!D20*'Solution Offering'!$J8*'Solution Offering'!$F$13+'Sales Forecast'!D21*'Solution Offering'!$J8*'Solution Offering'!$G$13 -> 0 | E33: =E19*'Solution Offering'!$J8*'Solution Offering'!$E$13+'Sales Forecast'!E20*'Solution Offering'!$J8*'Solution Offering'!$F$13+'Sales Forecast'!E21*'Solution Offering'!$J8*'Solution Offering'!$G$13 -> 0 | F33: =F19*'Solution Offering'!$J8*'Solution Offering'!$E$13+'Sales Forecast'!F20*'Solution Offering'!$J8*'Solution Offering'!$F$13+'Sales Forecast'!F21*'Solution Offering'!$J8*'Solution Offering'!$G$13 -> 0 | G33: =G19*'Solution Offering'!$J8*'Solution Offering'!$E$13+'Sales Forecast'!G20*'Solution Offering'!$J8*'Solution Offering'!$F$13+'Sales Forecast'!G21*'Solution Offering'!$J8*'Solution Offering'!$G$13 -> 3 | H33: =H19*'Solution Offering'!$J8*'Solution Offering'!$E$13+'Sales Forecast'!H20*'Solution Offering'!$J8*'Solution Offering'!$F$13+'Sales Forecast'!H21*'Solution Offering'!$J8*'Solution Offering'!$G$13 -> 6 | I33: =I19*'Solution Offering'!$J8*'Solution Offering'!$E$13+'Sales Forecast'!I20*'Solution Offering'!$J8*'Solution Offering'!$F$13+'Sales Forecast'!I21*'Solution Offering'!$J8*'Solution Offering'!$G$13 -> 9 | J33: =J19*'Solution Offering'!$J8*'Solution Offering'!$E$13+'Sales Forecast'!J20*'Solution Offering'!$J8*'Solution Offering'!$F$13+'Sales Forecast'!J21*'Solution Offering'!$J8*'Solution Offering'!$G$13 -> 18 | K33: =K19*'Solution Offering'!$J8*'Solution Offering'!$E$13+'Sales Forecast'!K20*'Solution Offering'!$J8*'Solution Offering'!$F$13+'Sales Forecast'!K21*'Solution Offering'!$J8*'Solution Offering'!$G$13 -> 33 | ... O33: =O19*'Solution Offering'!$J8*'Solution Offering'!$E$13+'Sales Forecast'!O20*'Solution Offering'!$J8*'Solution Offering'!$F$13+'Sales Forecast'!O21*'Solution Offering'!$J8*'Solution Offering'!$G$13 -> 144 | Q33: =SUM(D33:F33) -> 0 | R33: =SUM(G33:I33) -> 18 | S33: =SUM(J33:L33) -> 99 | T33: =SUM(M33:O33) -> 330 | V33: =SUM(Q33:T33) -> 447
C35: Revenue
C36: Federal
C37: AI Monitoring | D37: =D25*'Product & Pricing List'!$P5 -> 0 | E37: =E25*'Product & Pricing List'!$P5 -> 0 | F37: =F25*'Product & Pricing List'!$P5 -> 0 | G37: =G25*'Product & Pricing List'!$P5 -> 0 | H37: =H25*'Product & Pricing List'!$P5 -> 0 | I37: =I25*'Product & Pricing List'!$P5 -> 0 | J37: =J25*'Product & Pricing List'!$P5 -> 0 | K37: =K25*'Product & Pricing List'!$P5 -> 0 | ... O37: =O25*'Product & Pricing List'!$P5 -> 15000 | Q37: =SUM(D37:F37) -> 0 | R37: =SUM(G37:I37) -> 0 | S37: =SUM(J37:L37) -> 7500 | T37: =SUM(M37:O37) -> 37500 | V37: =SUM(Q37:T37) -> 45000
C38: Integration Fee | D38: =D26*'Product & Pricing List'!$P7 -> 0 | E38: =E26*'Product & Pricing List'!$P7 -> 0 | F38: =F26*'Product & Pricing List'!$P7 -> 0 | G38: =G26*'Product & Pricing List'!$P7 -> 0 | H38: =H26*'Product & Pricing List'!$P7 -> 0 | I38: =I26*'Product & Pricing List'!$P7 -> 0 | J38: =J26*'Product & Pricing List'!$P7 -> 0 | K38: =K26*'Product & Pricing List'!$P7 -> 0 | ... O38: =O26*'Product & Pricing List'!$P7 -> 0 | Q38: =SUM(D38:F38) -> 0 | R38: =SUM(G38:I38) -> 0 | S38: =SUM(J38:L38) -> 0 | T38: =SUM(M38:O38) -> 0 | V38: =SUM(Q38:T38) -> 0
C39: Professional Services - Implementation | D39: =D27*'Product & Pricing List'!$P8 -> 0 | E39: =E27*'Product & Pricing List'!$P8 -> 0 | F39: =F27*'Product & Pricing List'!$P8 -> 0 | G39: =G27*'Product & Pricing List'!$P8 -> 0 | H39: =H27*'Product & Pricing List'!$P8 -> 0 | I39: =I27*'Product & Pricing List'!$P8 -> 765 | J39: =J27*'Product & Pricing List'!$P8 -> 0 | K39: =K27*'Product & Pricing List'!$P8 -> 765 | ... O39: =O27*'Product & Pricing List'!$P8 -> 765 | Q39: =SUM(D39:F39) -> 0 | R39: =SUM(G39:I39) -> 765 | S39: =SUM(J39:L39) -> 765 | T39: =SUM(M39:O39) -> 1530 | V39: =SUM(Q39:T39) -> 3060
C40: Professional Services - Monthly | D40: =D28*'Product & Pricing List'!$P8 -> 0 | E40: =E28*'Product & Pricing List'!$P8 -> 0 | F40: =F28*'Product & Pricing List'!$P8 -> 0 | G40: =G28*'Product & Pricing List'!$P8 -> 0 | H40: =H28*'Product & Pricing List'!$P8 -> 0 | I40: =I28*'Product & Pricing List'!$P8 -> 0 | J40: =J28*'Product & Pricing List'!$P8 -> 0 | K40: =K28*'Product & Pricing List'!$P8 -> 0 | ... O40: =O28*'Product & Pricing List'!$P8 -> 1530 | Q40: =SUM(D40:F40) -> 0 | R40: =SUM(G40:I40) -> 0 | S40: =SUM(J40:L40) -> 765 | T40: =SUM(M40:O40) -> 3825 | V40: =SUM(Q40:T40) -> 4590
C41: Total Revenue - Federal | D41: =SUM(D37:D40) -> 0 | E41: =SUM(E37:E40) -> 0 | F41: =SUM(F37:F40) -> 0 | G41: =SUM(G37:G40) -> 0 | H41: =SUM(H37:H40) -> 0 | I41: =SUM(I37:I40) -> 765 | J41: =SUM(J37:J40) -> 0 | K41: =SUM(K37:K40) -> 765 | ... O41: =SUM(O37:O40) -> 17295 | Q41: =SUM(Q37:Q40) -> 0 | R41: =SUM(R37:R40) -> 765 | S41: =SUM(S37:S40) -> 9030 | T41: =SUM(T37:T40) -> 42855 | V41: =SUM(V37:V40) -> 52650
C42: Commercial
C43: AI Monitoring | D43: =D30*'Product & Pricing List'!$P6 -> 0 | E43: =E30*'Product & Pricing List'!$P6 -> 0 | F43: =F30*'Product & Pricing List'!$P6 -> 0 | G43: =G30*'Product & Pricing List'!$P6 -> 7500 | H43: =H30*'Product & Pricing List'!$P6 -> 15000 | I43: =I30*'Product & Pricing List'!$P6 -> 22500 | J43: =J30*'Product & Pricing List'!$P6 -> 45000 | K43: =K30*'Product & Pricing List'!$P6 -> 82500 | ... O43: =O30*'Product & Pricing List'!$P6 -> 360000 | Q43: =SUM(D43:F43) -> 0 | R43: =SUM(G43:I43) -> 45000 | S43: =SUM(J43:L43) -> 247500 | T43: =SUM(M43:O43) -> 825000 | V43: =SUM(Q43:T43) -> 1117500
C44: Integration Fee | D44: =D31*'Product & Pricing List'!$P7 -> 0 | E44: =E31*'Product & Pricing List'!$P7 -> 0 | F44: =F31*'Product & Pricing List'!$P7 -> 0 | G44: =G31*'Product & Pricing List'!$P7 -> 0 | H44: =H31*'Product & Pricing List'!$P7 -> 0 | I44: =I31*'Product & Pricing List'!$P7 -> 0 | J44: =J31*'Product & Pricing List'!$P7 -> 0 | K44: =K31*'Product & Pricing List'!$P7 -> 0 | ... O44: =O31*'Product & Pricing List'!$P7 -> 0 | Q44: =SUM(D44:F44) -> 0 | R44: =SUM(G44:I44) -> 0 | S44: =SUM(J44:L44) -> 0 | T44: =SUM(M44:O44) -> 0 | V44: =SUM(Q44:T44) -> 0
C45: Professional Services - Implementation | D45: =D32*'Product & Pricing List'!$P8 -> 0 | E45: =E32*'Product & Pricing List'!$P8 -> 765 | F45: =F32*'Product & Pricing List'!$P8 -> 765 | G45: =G32*'Product & Pricing List'!$P8 -> 2295 | H45: =H32*'Product & Pricing List'!$P8 -> 3825 | I45: =I32*'Product & Pricing List'!$P8 -> 3825 | J45: =J32*'Product & Pricing List'!$P8 -> 7650 | K45: =K32*'Product & Pricing List'!$P8 -> 7650 | ... O45: =O32*'Product & Pricing List'!$P8 -> 10710 | Q45: =SUM(D45:F45) -> 1530 | R45: =SUM(G45:I45) -> 9945 | S45: =SUM(J45:L45) -> 24480 | T45: =SUM(M45:O45) -> 30600 | V45: =SUM(Q45:T45) -> 66555
C46: Professional Services - Monthly | D46: =D33*'Product & Pricing List'!$P8 -> 0 | E46: =E33*'Product & Pricing List'!$P8 -> 0 | F46: =F33*'Product & Pricing List'!$P8 -> 0 | G46: =G33*'Product & Pricing List'!$P8 -> 765 | H46: =H33*'Product & Pricing List'!$P8 -> 1530 | I46: =I33*'Product & Pricing List'!$P8 -> 2295 | J46: =J33*'Product & Pricing List'!$P8 -> 4590 | K46: =K33*'Product & Pricing List'!$P8 -> 8415 | ... O46: =O33*'Product & Pricing List'!$P8 -> 36720 | Q46: =SUM(D46:F46) -> 0 | R46: =SUM(G46:I46) -> 4590 | S46: =SUM(J46:L46) -> 25245 | T46: =SUM(M46:O46) -> 84150 | V46: =SUM(Q46:T46) -> 113985
C47: Total Revenue - Commercial | D47: =SUM(D43:D46) -> 0 | E47: =SUM(E43:E46) -> 765 | F47: =SUM(F43:F46) -> 765 | G47: =SUM(G43:G46) -> 10560 | H47: =SUM(H43:H46) -> 20355 | I47: =SUM(I43:I46) -> 28620 | J47: =SUM(J43:J46) -> 57240 | K47: =SUM(K43:K46) -> 98565 | ... O47: =SUM(O43:O46) -> 407430 | Q47: =SUM(Q43:Q46) -> 1530 | R47: =SUM(R43:R46) -> 59535 | S47: =SUM(S43:S46) -> 297225 | T47: =SUM(T43:T46) -> 939750 | V47: =SUM(V43:V46) -> 1298040
C49: Total Revenue | D49: =D41+D47 -> 0 | E49: =E41+E47 -> 765 | F49: =F41+F47 -> 765 | G49: =G41+G47 -> 10560 | H49: =H41+H47 -> 20355 | I49: =I41+I47 -> 29385 | J49: =J41+J47 -> 57240 | K49: =K41+K47 -> 99330 | ... O49: =O41+O47 -> 424725 | Q49: =Q41+Q47 -> 1530 | R49: =R41+R47 -> 60300 | S49: =S41+S47 -> 306255 | T49: =T41+T47 -> 982605 | V49: =V41+V47 -> 1350690
C50: ARR | D50: =SUM(D37:D37,D43:D43)*12 -> 0 | E50: =SUM(E37:E37,E43:E43)*12 -> 0 | F50: =SUM(F37:F37,F43:F43)*12 -> 0 | G50: =SUM(G37:G37,G43:G43)*12 -> 90000 | H50: =SUM(H37:H37,H43:H43)*12 -> 180000 | I50: =SUM(I37:I37,I43:I43)*12 -> 270000 | J50: =SUM(J37:J37,J43:J43)*12 -> 540000 | K50: =SUM(K37:K37,K43:K43)*12 -> 990000 | ... O50: =SUM(O37:O37,O43:O43)*12 -> 4500000 | Q50: =F50 -> 0 | R50: =I50 -> 270000 | S50: =L50 -> 1530000 | T50: =O50 -> 4500000 | V50: =T50 -> 4500000
C51: Software % of Total Revenue | D51: =IFERROR(SUM(D37:D37,D43:D43)/D$49,"nm") -> nm | E51: =IFERROR(SUM(E37:E37,E43:E43)/E$49,"nm") -> 0 | F51: =IFERROR(SUM(F37:F37,F43:F43)/F$49,"nm") -> 0 | G51: =IFERROR(SUM(G37:G37,G43:G43)/G$49,"nm") -> 0.71022727 | H51: =IFERROR(SUM(H37:H37,H43:H43)/H$49,"nm") -> 0.73691968 | I51: =IFERROR(SUM(I37:I37,I43:I43)/I$49,"nm") -> 0.76569678 | J51: =IFERROR(SUM(J37:J37,J43:J43)/J$49,"nm") -> 0.78616352 | K51: =IFERROR(SUM(K37:K37,K43:K43)/K$49,"nm") -> 0.83056478 | ... O51: =IFERROR(SUM(O37:O37,O43:O43)/O$49,"nm") -> 0.88292425 | Q51: =IFERROR(SUM(Q37:Q37,Q43:Q43)/Q$49,"nm") -> 0 | R51: =IFERROR(SUM(R37:R37,R43:R43)/R$49,"nm") -> 0.74626866 | S51: =IFERROR(SUM(S37:S37,S43:S43)/S$49,"nm") -> 0.83263947 | T51: =IFERROR(SUM(T37:T37,T43:T43)/T$49,"nm") -> 0.87776879 | V51: =IFERROR(SUM(V37:V37,V43:V43)/V$49,"nm") -> 0.86067121
C52: Services % of Total Revenue | D52: =IFERROR(SUM(D38:D40,D44:D46)/D$49,"nm") -> nm | E52: =IFERROR(SUM(E38:E40,E44:E46)/E$49,"nm") -> 1 | F52: =IFERROR(SUM(F38:F40,F44:F46)/F$49,"nm") -> 1 | G52: =IFERROR(SUM(G38:G40,G44:G46)/G$49,"nm") -> 0.28977273 | H52: =IFERROR(SUM(H38:H40,H44:H46)/H$49,"nm") -> 0.26308032 | I52: =IFERROR(SUM(I38:I40,I44:I46)/I$49,"nm") -> 0.23430322 | J52: =IFERROR(SUM(J38:J40,J44:J46)/J$49,"nm") -> 0.21383648 | K52: =IFERROR(SUM(K38:K40,K44:K46)/K$49,"nm") -> 0.16943522 | ... O52: =IFERROR(SUM(O38:O40,O44:O46)/O$49,"nm") -> 0.11707575 | Q52: =IFERROR(SUM(Q38:Q40,Q44:Q46)/Q$49,"nm") -> 1 | R52: =IFERROR(SUM(R38:R40,R44:R46)/R$49,"nm") -> 0.25373134 | S52: =IFERROR(SUM(S38:S40,S44:S46)/S$49,"nm") -> 0.16736053 | T52: =IFERROR(SUM(T38:T40,T44:T46)/T$49,"nm") -> 0.12223121 | V52: =IFERROR(SUM(V38:V40,V44:V46)/V$49,"nm") -> 0.13932879
C54: Payments
C55: AI Monitoring | D55: 0 | E55: =D37+D43 -> 0 | F55: =E37+E43 -> 0 | G55: =F37+F43 -> 0 | H55: =G37+G43 -> 7500 | I55: =H37+H43 -> 15000 | J55: =I37+I43 -> 22500 | K55: =J37+J43 -> 45000 | L55: =K37+K43 -> 82500 | ... O55: =N37+N43 -> 285000 | Q55: =SUM(D55:F55) -> 0 | R55: =SUM(G55:I55) -> 22500 | S55: =SUM(J55:L55) -> 150000 | T55: =SUM(M55:O55) -> 615000 | V55: =SUM(Q55:T55) -> 787500
C56: Integration Fee | D56: 0 | E56: =D38+D44 -> 0 | F56: =E38+E44 -> 0 | G56: =F38+F44 -> 0 | H56: =G38+G44 -> 0 | I56: =H38+H44 -> 0 | J56: =I38+I44 -> 0 | K56: =J38+J44 -> 0 | L56: =K38+K44 -> 0 | ... O56: =N38+N44 -> 0 | Q56: =SUM(D56:F56) -> 0 | R56: =SUM(G56:I56) -> 0 | S56: =SUM(J56:L56) -> 0 | T56: =SUM(M56:O56) -> 0 | V56: =SUM(Q56:T56) -> 0
C57: Professional Services - Implementation | D57: 0 | E57: =D39+D45 -> 0 | F57: =E39+E45 -> 765 | G57: =F39+F45 -> 765 | H57: =G39+G45 -> 2295 | I57: =H39+H45 -> 3825 | J57: =I39+I45 -> 4590 | K57: =J39+J45 -> 7650 | L57: =K39+K45 -> 8415 | ... O57: =N39+N45 -> 10710 | Q57: =SUM(D57:F57) -> 765 | R57: =SUM(G57:I57) -> 6885 | S57: =SUM(J57:L57) -> 20655 | T57: =SUM(M57:O57) -> 29835 | V57: =SUM(Q57:T57) -> 58140
C58: Professional Services - Monthly | D58: 0 | E58: =D40+D46 -> 0 | F58: =E40+E46 -> 0 | G58: =F40+F46 -> 0 | H58: =G40+G46 -> 765 | I58: =H40+H46 -> 1530 | J58: =I40+I46 -> 2295 | K58: =J40+J46 -> 4590 | L58: =K40+K46 -> 8415 | ... O58: =N40+N46 -> 29070 | Q58: =SUM(D58:F58) -> 0 | R58: =SUM(G58:I58) -> 2295 | S58: =SUM(J58:L58) -> 15300 | T58: =SUM(M58:O58) -> 62730 | V58: =SUM(Q58:T58) -> 80325
C59: Total Payments | D59: =SUM(D55:D58) -> 0 | E59: =SUM(E55:E58) -> 0 | F59: =SUM(F55:F58) -> 765 | G59: =SUM(G55:G58) -> 765 | H59: =SUM(H55:H58) -> 10560 | I59: =SUM(I55:I58) -> 20355 | J59: =SUM(J55:J58) -> 29385 | K59: =SUM(K55:K58) -> 57240 | ... O59: =SUM(O55:O58) -> 324780 | Q59: =SUM(Q55:Q58) -> 765 | R59: =SUM(R55:R58) -> 31680 | S59: =SUM(S55:S58) -> 185955 | T59: =SUM(T55:T58) -> 707565 | V59: =SUM(V55:V58) -> 925965
C61: Sales Commissions
C62: Commission Percentage | D62: 0.2 | E62: 0.2 | F62: 0.2 | G62: 0.2 | H62: 0.2 | I62: 0.2 | J62: 0.2 | K62: 0.2 | L62: 0.2 | M62: 0.2 | N62: 0.2 | O62: 0.2
C63: Accrued Commissions | D63: =D62*D49 -> 0 | E63: =E62*E49 -> 153 | F63: =F62*F49 -> 153 | G63: =G62*G49 -> 2112 | H63: =H62*H49 -> 4071 | I63: =I62*I49 -> 5877 | J63: =J62*J49 -> 11448 | K63: =K62*K49 -> 19866 | ... O63: =O62*O49 -> 84945 | Q63: =SUM(D63:F63) -> 306 | R63: =SUM(G63:I63) -> 12060 | S63: =SUM(J63:L63) -> 61251 | T63: =SUM(M63:O63) -> 196521 | V63: =SUM(Q63:T63) -> 270138
C64: Cash Commissions | D64: =D59*D62 -> 0 | E64: =E59*E62 -> 0 | F64: =F59*F62 -> 153 | G64: =G59*G62 -> 153 | H64: =H59*H62 -> 2112 | I64: =I59*I62 -> 4071 | J64: =J59*J62 -> 5877 | K64: =K59*K62 -> 11448 | ... O64: =O59*O62 -> 64956 | Q64: =SUM(D64:F64) -> 153 | R64: =SUM(G64:I64) -> 6336 | S64: =SUM(J64:L64) -> 37191 | T64: =SUM(M64:O64) -> 141513 | V64: =SUM(Q64:T64) -> 185193

Sheet CoGS >>>

Sheet Labor
C2: 2026 Forecast
C3: Cost of Goods Sold - Labor
C5: Job Title | D5: Hourly Rate | E5: Weighting | F5: 45658 | G5: =EOMONTH(F5,0)+1 -> 45689 | H5: =EOMONTH(G5,0)+1 -> 45717 | I5: =EOMONTH(H5,0)+1 -> 45748 | J5: =EOMONTH(I5,0)+1 -> 45778 | K5: =EOMONTH(J5,0)+1 -> 45809 | L5: =EOMONTH(K5,0)+1 -> 45839 | M5: =EOMONTH(L5,0)+1 -> 45870 | N5: =EOMONTH(M5,0)+1 -> 45901 | ... Q5: =EOMONTH(P5,0)+1 -> 45992 | S5: Q1 '25 | T5: Q2 '25 | U5: Q3 '25 | V5: Q4 '25 | X5: 2025E
C7: Chief Strategy Officer | D7: 96.153846 | E7: 0.05 | F7: =$D7 -> 96.153846 | G7: =$D7 -> 96.153846 | H7: =$D7 -> 96.153846 | I7: =$D7 -> 96.153846 | J7: =$D7 -> 96.153846 | K7: =$D7 -> 96.153846 | L7: =$D7 -> 96.153846 | M7: =$D7 -> 96.153846 | ... Q7: =$D7 -> 96.153846 | S7: =AVERAGE(F7:H7) -> 96.153846 | T7: =AVERAGE(I7:K7) -> 96.153846 | U7: =AVERAGE(L7:N7) -> 96.153846 | V7: =AVERAGE(O7:Q7) -> 96.153846 | X7: =AVERAGE(S7:V7) -> 96.153846
C8: Chief Technology Officer | D8: 96.153846 | E8: 0.05 | F8: =$D8 -> 96.153846 | G8: =$D8 -> 96.153846 | H8: =$D8 -> 96.153846 | I8: =$D8 -> 96.153846 | J8: =$D8 -> 96.153846 | K8: =$D8 -> 96.153846 | L8: =$D8 -> 96.153846 | M8: =$D8 -> 96.153846 | ... Q8: =$D8 -> 96.153846 | S8: =AVERAGE(F8:H8) -> 96.153846 | T8: =AVERAGE(I8:K8) -> 96.153846 | U8: =AVERAGE(L8:N8) -> 96.153846 | V8: =AVERAGE(O8:Q8) -> 96.153846 | X8: =AVERAGE(S8:V8) -> 96.153846
C9: VP of AI Governance & Product Manager | D9: 86.538462 | E9: 0.05 | F9: =$D9 -> 86.538462 | G9: =$D9 -> 86.538462 | H9: =$D9 -> 86.538462 | I9: =$D9 -> 86.538462 | J9: =$D9 -> 86.538462 | K9: =$D9 -> 86.538462 | L9: =$D9 -> 86.538462 | M9: =$D9 -> 86.538462 | ... Q9: =$D9 -> 86.538462 | S9: =AVERAGE(F9:H9) -> 86.538462 | T9: =AVERAGE(I9:K9) -> 86.538462 | U9: =AVERAGE(L9:N9) -> 86.538462 | V9: =AVERAGE(O9:Q9) -> 86.538462 | X9: =AVERAGE(S9:V9) -> 86.538462
C10: Director of AI Governance & Product Research | D10: 79.326923 | E10: 0.1 | F10: =$D10 -> 79.326923 | G10: =$D10 -> 79.326923 | H10: =$D10 -> 79.326923 | I10: =$D10 -> 79.326923 | J10: =$D10 -> 79.326923 | K10: =$D10 -> 79.326923 | L10: =$D10 -> 79.326923 | M10: =$D10 -> 79.326923 | ... Q10: =$D10 -> 79.326923 | S10: =AVERAGE(F10:H10) -> 79.326923 | T10: =AVERAGE(I10:K10) -> 79.326923 | U10: =AVERAGE(L10:N10) -> 79.326923 | V10: =AVERAGE(O10:Q10) -> 79.326923 | X10: =AVERAGE(S10:V10) -> 79.326923
C11: Director of Sales | D11: 43.269231 | E11: 0.05 | F11: =$D11 -> 43.269231 | G11: =$D11 -> 43.269231 | H11: =$D11 -> 43.269231 | I11: =$D11 -> 43.269231 | J11: =$D11 -> 43.269231 | K11: =$D11 -> 43.269231 | L11: =$D11 -> 43.269231 | M11: =$D11 -> 43.269231 | ... Q11: =$D11 -> 43.269231 | S11: =AVERAGE(F11:H11) -> 43.269231 | T11: =AVERAGE(I11:K11) -> 43.269231 | U11: =AVERAGE(L11:N11) -> 43.269231 | V11: =AVERAGE(O11:Q11) -> 43.269231 | X11: =AVERAGE(S11:V11) -> 43.269231
C12: Director of Channel Sales | D12: 43.269231 | E12: 0.05 | F12: =$D12 -> 43.269231 | G12: =$D12 -> 43.269231 | H12: =$D12 -> 43.269231 | I12: =$D12 -> 43.269231 | J12: =$D12 -> 43.269231 | K12: =$D12 -> 43.269231 | L12: =$D12 -> 43.269231 | M12: =$D12 -> 43.269231 | ... Q12: =$D12 -> 43.269231 | S12: =AVERAGE(F12:H12) -> 43.269231 | T12: =AVERAGE(I12:K12) -> 43.269231 | U12: =AVERAGE(L12:N12) -> 43.269231 | V12: =AVERAGE(O12:Q12) -> 43.269231 | X12: =AVERAGE(S12:V12) -> 43.269231
C13: Customer Success Manager | D13: 31.25 | E13: 0.05 | F13: =$D13 -> 31.25 | G13: =$D13 -> 31.25 | H13: =$D13 -> 31.25 | I13: =$D13 -> 31.25 | J13: =$D13 -> 31.25 | K13: =$D13 -> 31.25 | L13: =$D13 -> 31.25 | M13: =$D13 -> 31.25 | ... Q13: =$D13 -> 31.25 | S13: =AVERAGE(F13:H13) -> 31.25 | T13: =AVERAGE(I13:K13) -> 31.25 | U13: =AVERAGE(L13:N13) -> 31.25 | V13: =AVERAGE(O13:Q13) -> 31.25 | X13: =AVERAGE(S13:V13) -> 31.25
C14: Independent Contractor | D14: 125 | E14: 0.3 | F14: =$D14 -> 125 | G14: =$D14 -> 125 | H14: =$D14 -> 125 | I14: =$D14 -> 125 | J14: =$D14 -> 125 | K14: =$D14 -> 125 | L14: =$D14 -> 125 | M14: =$D14 -> 125 | ... Q14: =$D14 -> 125 | S14: =AVERAGE(F14:H14) -> 125 | T14: =AVERAGE(I14:K14) -> 125 | U14: =AVERAGE(L14:N14) -> 125 | V14: =AVERAGE(O14:Q14) -> 125 | X14: =AVERAGE(S14:V14) -> 125
C15: Partner | D15: 250 | E15: 0.3 | F15: =$D15 -> 250 | G15: =$D15 -> 250 | H15: =$D15 -> 250 | I15: =$D15 -> 250 | J15: =$D15 -> 250 | K15: =$D15 -> 250 | L15: =$D15 -> 250 | M15: =$D15 -> 250 | ... Q15: =$D15 -> 250 | S15: =AVERAGE(F15:H15) -> 250 | T15: =AVERAGE(I15:K15) -> 250 | U15: =AVERAGE(L15:N15) -> 250 | V15: =AVERAGE(O15:Q15) -> 250 | X15: =AVERAGE(S15:V15) -> 250
C16: Blended Hourly Rate | F16: =SUMPRODUCT(F$7:F$15,$E$7:$E$15) -> 140.26442 | G16: =SUMPRODUCT(G$7:G$15,$E$7:$E$15) -> 140.26442 | H16: =SUMPRODUCT(H$7:H$15,$E$7:$E$15) -> 140.26442 | I16: =SUMPRODUCT(I$7:I$15,$E$7:$E$15) -> 140.26442 | J16: =SUMPRODUCT(J$7:J$15,$E$7:$E$15) -> 140.26442 | K16: =SUMPRODUCT(K$7:K$15,$E$7:$E$15) -> 140.26442 | L16: =SUMPRODUCT(L$7:L$15,$E$7:$E$15) -> 140.26442 | M16: =SUMPRODUCT(M$7:M$15,$E$7:$E$15) -> 140.26442 | ... Q16: =SUMPRODUCT(Q$7:Q$15,$E$7:$E$15) -> 140.26442 | S16: =SUMPRODUCT(S7:S15,$E$7:$E$15) -> 140.26442 | T16: =SUMPRODUCT(T7:T15,$E$7:$E$15) -> 140.26442 | U16: =SUMPRODUCT(U7:U15,$E$7:$E$15) -> 140.26442 | V16: =SUMPRODUCT(V7:V15,$E$7:$E$15) -> 140.26442 | X16: =SUMPRODUCT(X7:X15,$E$7:$E$15) -> 140.26442
C18: Adjustment Factor | D18: 0.1 | F18: =$D18 -> 0.1 | G18: =$D18 -> 0.1 | H18: =$D18 -> 0.1 | I18: =$D18 -> 0.1 | J18: =$D18 -> 0.1 | K18: =$D18 -> 0.1 | L18: =$D18 -> 0.1 | M18: =$D18 -> 0.1 | ... Q18: =$D18 -> 0.1 | S18: =$D18 -> 0.1 | T18: =$D18 -> 0.1 | U18: =$D18 -> 0.1 | V18: =$D18 -> 0.1 | X18: =$D18 -> 0.1
C20: Adjusted Blended Hourly Rate | F20: =F16*(1+F18) -> 154.29087 | G20: =G16*(1+G18) -> 154.29087 | H20: =H16*(1+H18) -> 154.29087 | I20: =I16*(1+I18) -> 154.29087 | J20: =J16*(1+J18) -> 154.29087 | K20: =K16*(1+K18) -> 154.29087 | L20: =L16*(1+L18) -> 154.29087 | M20: =M16*(1+M18) -> 154.29087 | ... Q20: =Q16*(1+Q18) -> 154.29087 | S20: =S16*(1+S18) -> 154.29087 | T20: =T16*(1+T18) -> 154.29087 | U20: =U16*(1+U18) -> 154.29087 | V20: =V16*(1+V18) -> 154.29087 | X20: =X16*(1+X18) -> 154.29087
C22: Labor Hours
C23: Federal
C24: AI Monitoring | D24: 40 | E24: AI Model | F24: ='Sales Forecast'!D25*Labor!$D24 -> 0 | G24: ='Sales Forecast'!E25*Labor!$D24 -> 0 | H24: ='Sales Forecast'!F25*Labor!$D24 -> 0 | I24: ='Sales Forecast'!G25*Labor!$D24 -> 0 | J24: ='Sales Forecast'!H25*Labor!$D24 -> 0 | K24: ='Sales Forecast'!I25*Labor!$D24 -> 0 | L24: ='Sales Forecast'!J25*Labor!$D24 -> 0 | M24: ='Sales Forecast'!K25*Labor!$D24 -> 0 | ... Q24: ='Sales Forecast'!O25*Labor!$D24 -> 400 | S24: =SUM(F24:H24) -> 0 | T24: =SUM(I24:K24) -> 0 | U24: =SUM(L24:N24) -> 200 | V24: =SUM(O24:Q24) -> 1000 | X24: =SUM(S24:V24) -> 1200
C25: Integration Fee | D25: 40 | E25: AI Model | F25: ='Sales Forecast'!D26*Labor!$D25 -> 0 | G25: ='Sales Forecast'!E26*Labor!$D25 -> 0 | H25: ='Sales Forecast'!F26*Labor!$D25 -> 0 | I25: ='Sales Forecast'!G26*Labor!$D25 -> 0 | J25: ='Sales Forecast'!H26*Labor!$D25 -> 0 | K25: ='Sales Forecast'!I26*Labor!$D25 -> 0 | L25: ='Sales Forecast'!J26*Labor!$D25 -> 0 | M25: ='Sales Forecast'!K26*Labor!$D25 -> 0 | ... Q25: ='Sales Forecast'!O26*Labor!$D25 -> 0 | S25: =SUM(F25:H25) -> 0 | T25: =SUM(I25:K25) -> 0 | U25: =SUM(L25:N25) -> 0 | V25: =SUM(O25:Q25) -> 0 | X25: =SUM(S25:V25) -> 0
C26: Professional Services - Implementation | D26: 10 | E26: Customer | F26: ='Sales Forecast'!D27 -> 0 | G26: ='Sales Forecast'!E27 -> 0 | H26: ='Sales Forecast'!F27 -> 0 | I26: ='Sales Forecast'!G27 -> 0 | J26: ='Sales Forecast'!H27 -> 0 | K26: ='Sales Forecast'!I27 -> 3 | L26: ='Sales Forecast'!J27 -> 0 | M26: ='Sales Forecast'!K27 -> 3 | ... Q26: ='Sales Forecast'!O27 -> 3 | S26: =SUM(F26:H26) -> 0 | T26: =SUM(I26:K26) -> 3 | U26: =SUM(L26:N26) -> 3 | V26: =SUM(O26:Q26) -> 6 | X26: =SUM(S26:V26) -> 12
C27: Professional Services - Monthly | D27: 10 | E27: Customer | F27: ='Sales Forecast'!D28 -> 0 | G27: ='Sales Forecast'!E28 -> 0 | H27: ='Sales Forecast'!F28 -> 0 | I27: ='Sales Forecast'!G28 -> 0 | J27: ='Sales Forecast'!H28 -> 0 | K27: ='Sales Forecast'!I28 -> 0 | L27: ='Sales Forecast'!J28 -> 0 | M27: ='Sales Forecast'!K28 -> 0 | ... Q27: ='Sales Forecast'!O28 -> 6 | S27: =SUM(F27:H27) -> 0 | T27: =SUM(I27:K27) -> 0 | U27: =SUM(L27:N27) -> 3 | V27: =SUM(O27:Q27) -> 15 | X27: =SUM(S27:V27) -> 18
C28: Total Labor Hours - Federal | F28: =SUM(F24:F27) -> 0 | G28: =SUM(G24:G27) -> 0 | H28: =SUM(H24:H27) -> 0 | I28: =SUM(I24:I27) -> 0 | J28: =SUM(J24:J27) -> 0 | K28: =SUM(K24:K27) -> 3 | L28: =SUM(L24:L27) -> 0 | M28: =SUM(M24:M27) -> 3 | ... Q28: =SUM(Q24:Q27) -> 409 | S28: =SUM(S24:S27) -> 0 | T28: =SUM(T24:T27) -> 3 | U28: =SUM(U24:U27) -> 206 | V28: =SUM(V24:V27) -> 1021 | X28: =SUM(X24:X27) -> 1230
C29: Commercial
C30: AI Monitoring | D30: 40 | E30: AI Model | F30: ='Sales Forecast'!D30*Labor!$D30 -> 0 | G30: ='Sales Forecast'!E30*Labor!$D30 -> 0 | H30: ='Sales Forecast'!F30*Labor!$D30 -> 0 | I30: ='Sales Forecast'!G30*Labor!$D30 -> 200 | J30: ='Sales Forecast'!H30*Labor!$D30 -> 400 | K30: ='Sales Forecast'!I30*Labor!$D30 -> 600 | L30: ='Sales Forecast'!J30*Labor!$D30 -> 1200 | M30: ='Sales Forecast'!K30*Labor!$D30 -> 2200 | ... Q30: ='Sales Forecast'!O30*Labor!$D30 -> 9600 | S30: =SUM(F30:H30) -> 0 | T30: =SUM(I30:K30) -> 1200 | U30: =SUM(L30:N30) -> 6600 | V30: =SUM(O30:Q30) -> 22000 | X30: =SUM(S30:V30) -> 29800
C31: Integration Fee | D31: 40 | E31: AI Model | F31: ='Sales Forecast'!D31*Labor!$D31 -> 0 | G31: ='Sales Forecast'!E31*Labor!$D31 -> 0 | H31: ='Sales Forecast'!F31*Labor!$D31 -> 0 | I31: ='Sales Forecast'!G31*Labor!$D31 -> 0 | J31: ='Sales Forecast'!H31*Labor!$D31 -> 0 | K31: ='Sales Forecast'!I31*Labor!$D31 -> 0 | L31: ='Sales Forecast'!J31*Labor!$D31 -> 0 | M31: ='Sales Forecast'!K31*Labor!$D31 -> 0 | ... Q31: ='Sales Forecast'!O31*Labor!$D31 -> 0 | S31: =SUM(F31:H31) -> 0 | T31: =SUM(I31:K31) -> 0 | U31: =SUM(L31:N31) -> 0 | V31: =SUM(O31:Q31) -> 0 | X31: =SUM(S31:V31) -> 0
C32: Professional Services - Implementation | D32: 10 | E32: Customer | F32: ='Sales Forecast'!D32 -> 0 | G32: ='Sales Forecast'!E32 -> 3 | H32: ='Sales Forecast'!F32 -> 3 | I32: ='Sales Forecast'!G32 -> 9 | J32: ='Sales Forecast'!H32 -> 15 | K32: ='Sales Forecast'!I32 -> 15 | L32: ='Sales Forecast'!J32 -> 30 | M32: ='Sales Forecast'!K32 -> 30 | ... Q32: ='Sales Forecast'!O32 -> 42 | S32: =SUM(F32:H32) -> 6 | T32: =SUM(I32:K32) -> 39 | U32: =SUM(L32:N32) -> 96 | V32: =SUM(O32:Q32) -> 120 | X32: =SUM(S32:V32) -> 261
C33: Professional Services - Monthly | D33: 10 | E33: Customer | F33: ='Sales Forecast'!D33 -> 0 | G33: ='Sales Forecast'!E33 -> 0 | H33: ='Sales Forecast'!F33 -> 0 | I33: ='Sales Forecast'!G33 -> 3 | J33: ='Sales Forecast'!H33 -> 6 | K33: ='Sales Forecast'!I33 -> 9 | L33: ='Sales Forecast'!J33 -> 18 | M33: ='Sales Forecast'!K33 -> 33 | ... Q33: ='Sales Forecast'!O33 -> 144 | S33: =SUM(F33:H33) -> 0 | T33: =SUM(I33:K33) -> 18 | U33: =SUM(L33:N33) -> 99 | V33: =SUM(O33:Q33) -> 330 | X33: =SUM(S33:V33) -> 447
C34: Total Labor Hours - Commercial | F34: =SUM(F30:F33) -> 0 | G34: =SUM(G30:G33) -> 3 | H34: =SUM(H30:H33) -> 3 | I34: =SUM(I30:I33) -> 212 | J34: =SUM(J30:J33) -> 421 | K34: =SUM(K30:K33) -> 624 | L34: =SUM(L30:L33) -> 1248 | M34: =SUM(M30:M33) -> 2263 | ... Q34: =SUM(Q30:Q33) -> 9786 | S34: =SUM(S30:S33) -> 6 | T34: =SUM(T30:T33) -> 1257 | U34: =SUM(U30:U33) -> 6795 | V34: =SUM(V30:V33) -> 22450 | X34: =SUM(X30:X33) -> 30508
C36: Total Labor Hours | F36: =F28+F34 -> 0 | G36: =G28+G34 -> 3 | H36: =H28+H34 -> 3 | I36: =I28+I34 -> 212 | J36: =J28+J34 -> 421 | K36: =K28+K34 -> 627 | L36: =L28+L34 -> 1248 | M36: =M28+M34 -> 2266 | ... Q36: =Q28+Q34 -> 10195 | S36: =S28+S34 -> 6 | T36: =T28+T34 -> 1260 | U36: =U28+U34 -> 7001 | V36: =V28+V34 -> 23471 | X36: =X28+X34 -> 31738
C38: Cost of Goods Sold - Labor
C39: Federal
C40: AI Monitoring | F40: =F24*F$20 -> 0 | G40: =G24*G$20 -> 0 | H40: =H24*H$20 -> 0 | I40: =I24*I$20 -> 0 | J40: =J24*J$20 -> 0 | K40: =K24*K$20 -> 0 | L40: =L24*L$20 -> 0 | M40: =M24*M$20 -> 0 | ... Q40: =Q24*Q$20 -> 61716.346 | S40: =SUM(F40:H40) -> 0 | T40: =SUM(I40:K40) -> 0 | U40: =SUM(L40:N40) -> 30858.173 | V40: =SUM(O40:Q40) -> 154290.87 | X40: =SUM(S40:V40) -> 185149.04
C41: Integration Fee | F41: =F25*F$20 -> 0 | G41: =G25*G$20 -> 0 | H41: =H25*H$20 -> 0 | I41: =I25*I$20 -> 0 | J41: =J25*J$20 -> 0 | K41: =K25*K$20 -> 0 | L41: =L25*L$20 -> 0 | M41: =M25*M$20 -> 0 | ... Q41: =Q25*Q$20 -> 0 | S41: =SUM(F41:H41) -> 0 | T41: =SUM(I41:K41) -> 0 | U41: =SUM(L41:N41) -> 0 | V41: =SUM(O41:Q41) -> 0 | X41: =SUM(S41:V41) -> 0
C42: Professional Services - Implementation | F42: =F26*F$20 -> 0 | G42: =G26*G$20 -> 0 | H42: =H26*H$20 -> 0 | I42: =I26*I$20 -> 0 | J42: =J26*J$20 -> 0 | K42: =K26*K$20 -> 462.8726 | L42: =L26*L$20 -> 0 | M42: =M26*M$20 -> 462.8726 | ... Q42: =Q26*Q$20 -> 462.8726 | S42: =SUM(F42:H42) -> 0 | T42: =SUM(I42:K42) -> 462.8726 | U42: =SUM(L42:N42) -> 462.8726 | V42: =SUM(O42:Q42) -> 925.74519 | X42: =SUM(S42:V42) -> 1851.4904
C43: Professional Services - Monthly | F43: =F27*F$20 -> 0 | G43: =G27*G$20 -> 0 | H43: =H27*H$20 -> 0 | I43: =I27*I$20 -> 0 | J43: =J27*J$20 -> 0 | K43: =K27*K$20 -> 0 | L43: =L27*L$20 -> 0 | M43: =M27*M$20 -> 0 | ... Q43: =Q27*Q$20 -> 925.74519 | S43: =SUM(F43:H43) -> 0 | T43: =SUM(I43:K43) -> 0 | U43: =SUM(L43:N43) -> 462.8726 | V43: =SUM(O43:Q43) -> 2314.363 | X43: =SUM(S43:V43) -> 2777.2356
C44: Total Federal Cost of Goods Sold - Labor | F44: =SUM(F40:F43) -> 0 | G44: =SUM(G40:G43) -> 0 | H44: =SUM(H40:H43) -> 0 | I44: =SUM(I40:I43) -> 0 | J44: =SUM(J40:J43) -> 0 | K44: =SUM(K40:K43) -> 462.8726 | L44: =SUM(L40:L43) -> 0 | M44: =SUM(M40:M43) -> 462.8726 | ... Q44: =SUM(Q40:Q43) -> 63104.964 | S44: =SUM(S40:S43) -> 0 | T44: =SUM(T40:T43) -> 462.8726 | U44: =SUM(U40:U43) -> 31783.918 | V44: =SUM(V40:V43) -> 157530.97 | X44: =SUM(S44:V44) -> 189777.76
C45: Commercial
C46: AI Monitoring | F46: =F30*F$20 -> 0 | G46: =G30*G$20 -> 0 | H46: =H30*H$20 -> 0 | I46: =I30*I$20 -> 30858.173 | J46: =J30*J$20 -> 61716.346 | K46: =K30*K$20 -> 92574.519 | L46: =L30*L$20 -> 185149.04 | M46: =M30*M$20 -> 339439.9 | ... Q46: =Q30*Q$20 -> 1481192.3 | S46: =SUM(F46:H46) -> 0 | T46: =SUM(I46:K46) -> 185149.04 | U46: =SUM(L46:N46) -> 1018319.7 | V46: =SUM(O46:Q46) -> 3394399 | X46: =SUM(S46:V46) -> 4597867.8
C47: Integration Fee | F47: =F31*F$20 -> 0 | G47: =G31*G$20 -> 0 | H47: =H31*H$20 -> 0 | I47: =I31*I$20 -> 0 | J47: =J31*J$20 -> 0 | K47: =K31*K$20 -> 0 | L47: =L31*L$20 -> 0 | M47: =M31*M$20 -> 0 | ... Q47: =Q31*Q$20 -> 0 | S47: =SUM(F47:H47) -> 0 | T47: =SUM(I47:K47) -> 0 | U47: =SUM(L47:N47) -> 0 | V47: =SUM(O47:Q47) -> 0 | X47: =SUM(S47:V47) -> 0
C48: Professional Services - Implementation | F48: =F32*F$20 -> 0 | G48: =G32*G$20 -> 462.8726 | H48: =H32*H$20 -> 462.8726 | I48: =I32*I$20 -> 1388.6178 | J48: =J32*J$20 -> 2314.363 | K48: =K32*K$20 -> 2314.363 | L48: =L32*L$20 -> 4628.726 | M48: =M32*M$20 -> 4628.726 | ... Q48: =Q32*Q$20 -> 6480.2163 | S48: =SUM(F48:H48) -> 925.74519 | T48: =SUM(I48:K48) -> 6017.3438 | U48: =SUM(L48:N48) -> 14811.923 | V48: =SUM(O48:Q48) -> 18514.904 | X48: =SUM(S48:V48) -> 40269.916
C49: Professional Services - Monthly | F49: =F33*F$20 -> 0 | G49: =G33*G$20 -> 0 | H49: =H33*H$20 -> 0 | I49: =I33*I$20 -> 462.8726 | J49: =J33*J$20 -> 925.74519 | K49: =K33*K$20 -> 1388.6178 | L49: =L33*L$20 -> 2777.2356 | M49: =M33*M$20 -> 5091.5986 | ... Q49: =Q33*Q$20 -> 22217.885 | S49: =SUM(F49:H49) -> 0 | T49: =SUM(I49:K49) -> 2777.2356 | U49: =SUM(L49:N49) -> 15274.796 | V49: =SUM(O49:Q49) -> 50915.986 | X49: =SUM(S49:V49) -> 68968.017
C50: Total Commercial Cost of Goods Sold - Labor | F50: =SUM(F46:F49) -> 0 | G50: =SUM(G46:G49) -> 462.8726 | H50: =SUM(H46:H49) -> 462.8726 | I50: =SUM(I46:I49) -> 32709.663 | J50: =SUM(J46:J49) -> 64956.454 | K50: =SUM(K46:K49) -> 96277.5 | L50: =SUM(L46:L49) -> 192555 | M50: =SUM(M46:M49) -> 349160.23 | ... Q50: =SUM(Q46:Q49) -> 1509890.4 | S50: =SUM(S46:S49) -> 925.74519 | T50: =SUM(T46:T49) -> 193943.62 | U50: =SUM(U46:U49) -> 1048406.4 | V50: =SUM(V46:V49) -> 3463829.9 | X50: =SUM(S50:V50) -> 4707105.7
C52: Total Cost of Goods Sold - Labor | F52: =F44+F50 -> 0 | G52: =G44+G50 -> 462.8726 | H52: =H44+H50 -> 462.8726 | I52: =I44+I50 -> 32709.663 | J52: =J44+J50 -> 64956.454 | K52: =K44+K50 -> 96740.373 | L52: =L44+L50 -> 192555 | M52: =M44+M50 -> 349623.1 | ... Q52: =Q44+Q50 -> 1572995.4 | S52: =S44+S50 -> 925.74519 | T52: =T44+T50 -> 194406.49 | U52: =U44+U50 -> 1080190.3 | V52: =V44+V50 -> 3621360.9 | X52: =X44+X50 -> 4896883.5

Sheet Third Party Software
C2: 2026 Forecast
C3: Cost of Goods Sold - Third Party Software
C5: Vendor Name | D5: Description | E5: 46023 | F5: =EOMONTH(E5,0)+1 -> 46054 | G5: =EOMONTH(F5,0)+1 -> 46082 | H5: =EOMONTH(G5,0)+1 -> 46113 | I5: =EOMONTH(H5,0)+1 -> 46143 | J5: =EOMONTH(I5,0)+1 -> 46174 | K5: =EOMONTH(J5,0)+1 -> 46204 | L5: =EOMONTH(K5,0)+1 -> 46235 | M5: =EOMONTH(L5,0)+1 -> 46266 | ... P5: =EOMONTH(O5,0)+1 -> 46357 | R5: Q1 '26 | S5: Q2 '26 | T5: Q3 '26 | U5: Q4 '26 | W5: 2026E
C7: OpenAI | D7: Prompt | E7: 0 | F7: 0 | G7: 0 | H7: 0 | I7: 0 | J7: 0 | K7: 0 | L7: 0 | M7: 0 | N7: 0 | O7: 0 | P7: 0 | R7: =SUM(E7:G7) -> 0 | S7: =SUM(H7:J7) -> 0 | T7: =SUM(K7:M7) -> 0 | U7: =SUM(N7:P7) -> 0 | W7: =SUM(R7:U7) -> 0
C8: Total Cost of Goods Sold - Third Party Software | E8: =SUM(E7:E7) -> 0 | F8: =SUM(F7:F7) -> 0 | G8: =SUM(G7:G7) -> 0 | H8: =SUM(H7:H7) -> 0 | I8: =SUM(I7:I7) -> 0 | J8: =SUM(J7:J7) -> 0 | K8: =SUM(K7:K7) -> 0 | L8: =SUM(L7:L7) -> 0 | ... P8: =SUM(P7:P7) -> 0 | R8: =SUM(R7:R7) -> 0 | S8: =SUM(S7:S7) -> 0 | T8: =SUM(T7:T7) -> 0 | U8: =SUM(U7:U7) -> 0 | W8: =SUM(W7:W7) -> 0
C10: Cost of Goods Sold - Third Party Software Allocation
C11: AI Monitoring 1 | E11: 0.6 | F11: 0.6 | G11: 0.6 | H11: 0.6 | I11: 0.6 | J11: 0.6 | K11: 0.6 | L11: 0.6 | M11: 0.6 | N11: 0.6 | O11: 0.6 | P11: 0.6 | R11: =AVERAGE(E11:G11) -> 0.6 | S11: =AVERAGE(H11:J11) -> 0.6 | T11: =AVERAGE(K11:M11) -> 0.6 | U11: =AVERAGE(N11:P11) -> 0.6 | W11: =AVERAGE(R11:U11) -> 0.6
C12: AI Monitoring 2 | E12: 0.3 | F12: 0.3 | G12: 0.3 | H12: 0.3 | I12: 0.3 | J12: 0.3 | K12: 0.3 | L12: 0.3 | M12: 0.3 | N12: 0.3 | O12: 0.3 | P12: 0.3 | R12: =AVERAGE(E12:G12) -> 0.3 | S12: =AVERAGE(H12:J12) -> 0.3 | T12: =AVERAGE(K12:M12) -> 0.3 | U12: =AVERAGE(N12:P12) -> 0.3 | W12: =AVERAGE(R12:U12) -> 0.3
C13: GRC | E13: 0.1 | F13: 0.1 | G13: 0.1 | H13: 0.1 | I13: 0.1 | J13: 0.1 | K13: 0.1 | L13: 0.1 | M13: 0.1 | N13: 0.1 | O13: 0.1 | P13: 0.1 | R13: =AVERAGE(E13:G13) -> 0.1 | S13: =AVERAGE(H13:J13) -> 0.1 | T13: =AVERAGE(K13:M13) -> 0.1 | U13: =AVERAGE(N13:P13) -> 0.1 | W13: =AVERAGE(R13:U13) -> 0.1
C14: Integration Fee | E14: 0 | F14: 0 | G14: 0 | H14: 0 | I14: 0 | J14: 0 | K14: 0 | L14: 0 | M14: 0 | N14: 0 | O14: 0 | P14: 0 | R14: =AVERAGE(E14:G14) -> 0 | S14: =AVERAGE(H14:J14) -> 0 | T14: =AVERAGE(K14:M14) -> 0 | U14: =AVERAGE(N14:P14) -> 0 | W14: =AVERAGE(R14:U14) -> 0
C15: Professional Services - Implementation | E15: 0 | F15: 0 | G15: 0 | H15: 0 | I15: 0 | J15: 0 | K15: 0 | L15: 0 | M15: 0 | N15: 0 | O15: 0 | P15: 0 | R15: =AVERAGE(E15:G15) -> 0 | S15: =AVERAGE(H15:J15) -> 0 | T15: =AVERAGE(K15:M15) -> 0 | U15: =AVERAGE(N15:P15) -> 0 | W15: =AVERAGE(R15:U15) -> 0
C16: Professional Services - Monthly | E16: 0 | F16: 0 | G16: 0 | H16: 0 | I16: 0 | J16: 0 | K16: 0 | L16: 0 | M16: 0 | N16: 0 | O16: 0 | P16: 0 | R16: =AVERAGE(E16:G16) -> 0 | S16: =AVERAGE(H16:J16) -> 0 | T16: =AVERAGE(K16:M16) -> 0 | U16: =AVERAGE(N16:P16) -> 0 | W16: =AVERAGE(R16:U16) -> 0
C17: Total Cost of Goods Sold - Third Party Software Allocation | E17: =SUM(E11:E16) -> 1 | F17: =SUM(F11:F16) -> 1 | G17: =SUM(G11:G16) -> 1 | H17: =SUM(H11:H16) -> 1 | I17: =SUM(I11:I16) -> 1 | J17: =SUM(J11:J16) -> 1 | K17: =SUM(K11:K16) -> 1 | L17: =SUM(L11:L16) -> 1 | ... P17: =SUM(P11:P16) -> 1 | R17: =SUM(R11:R16) -> 1 | S17: =SUM(S11:S16) -> 1 | T17: =SUM(T11:T16) -> 1 | U17: =SUM(U11:U16) -> 1 | W17: =SUM(W11:W16) -> 1
C19: Split to Federal | E19: 0.5 | F19: 0.5 | G19: 0.5 | H19: 0.5 | I19: 0.5 | J19: 0.5 | K19: 0.5 | L19: 0.5 | M19: 0.5 | N19: 0.5 | O19: 0.5 | P19: 0.5 | R19: =AVERAGE(E19:G19) -> 0.5 | S19: =AVERAGE(H19:J19) -> 0.5 | T19: =AVERAGE(K19:M19) -> 0.5 | U19: =AVERAGE(N19:P19) -> 0.5 | W19: =AVERAGE(R19:U19) -> 0.5
C20: Split to Commercial | E20: 0.5 | F20: 0.5 | G20: 0.5 | H20: 0.5 | I20: 0.5 | J20: 0.5 | K20: 0.5 | L20: 0.5 | M20: 0.5 | N20: 0.5 | O20: 0.5 | P20: 0.5 | R20: =AVERAGE(E20:G20) -> 0.5 | S20: =AVERAGE(H20:J20) -> 0.5 | T20: =AVERAGE(K20:M20) -> 0.5 | U20: =AVERAGE(N20:P20) -> 0.5 | W20: =AVERAGE(R20:U20) -> 0.5
C22: Cost of Goods Sold - Third Party Software
C23: Federal
C24: AI Monitoring | E24: =E$8*E13*E$19 -> 0 | F24: =F$8*F13*F$19 -> 0 | G24: =G$8*G13*G$19 -> 0 | H24: =H$8*H13*H$19 -> 0 | I24: =I$8*I13*I$19 -> 0 | J24: =J$8*J13*J$19 -> 0 | K24: =K$8*K13*K$19 -> 0 | L24: =L$8*L13*L$19 -> 0 | ... P24: =P$8*P13*P$19 -> 0 | R24: =SUM(E24:G24) -> 0 | S24: =SUM(H24:J24) -> 0 | T24: =SUM(K24:M24) -> 0 | U24: =SUM(N24:P24) -> 0 | W24: =SUM(R24:U24) -> 0
C25: Integration Fee | E25: =E$8*E14*E$19 -> 0 | F25: =F$8*F14*F$19 -> 0 | G25: =G$8*G14*G$19 -> 0 | H25: =H$8*H14*H$19 -> 0 | I25: =I$8*I14*I$19 -> 0 | J25: =J$8*J14*J$19 -> 0 | K25: =K$8*K14*K$19 -> 0 | L25: =L$8*L14*L$19 -> 0 | ... P25: =P$8*P14*P$19 -> 0 | R25: =SUM(E25:G25) -> 0 | S25: =SUM(H25:J25) -> 0 | T25: =SUM(K25:M25) -> 0 | U25: =SUM(N25:P25) -> 0 | W25: =SUM(R25:U25) -> 0
C26: Professional Services - Implementation | E26: =E$8*E15*E$19 -> 0 | F26: =F$8*F15*F$19 -> 0 | G26: =G$8*G15*G$19 -> 0 | H26: =H$8*H15*H$19 -> 0 | I26: =I$8*I15*I$19 -> 0 | J26: =J$8*J15*J$19 -> 0 | K26: =K$8*K15*K$19 -> 0 | L26: =L$8*L15*L$19 -> 0 | ... P26: =P$8*P15*P$19 -> 0 | R26: =SUM(E26:G26) -> 0 | S26: =SUM(H26:J26) -> 0 | T26: =SUM(K26:M26) -> 0 | U26: =SUM(N26:P26) -> 0 | W26: =SUM(R26:U26) -> 0
C27: Professional Services - Monthly | E27: =E$8*E16*E$19 -> 0 | F27: =F$8*F16*F$19 -> 0 | G27: =G$8*G16*G$19 -> 0 | H27: =H$8*H16*H$19 -> 0 | I27: =I$8*I16*I$19 -> 0 | J27: =J$8*J16*J$19 -> 0 | K27: =K$8*K16*K$19 -> 0 | L27: =L$8*L16*L$19 -> 0 | ... P27: =P$8*P16*P$19 -> 0 | R27: =SUM(E27:G27) -> 0 | S27: =SUM(H27:J27) -> 0 | T27: =SUM(K27:M27) -> 0 | U27: =SUM(N27:P27) -> 0 | W27: =SUM(R27:U27) -> 0
C28: Total Federal Cost of Goods Sold - Third Party Software | E28: =SUM(E24:E27) -> 0 | F28: =SUM(F24:F27) -> 0 | G28: =SUM(G24:G27) -> 0 | H28: =SUM(H24:H27) -> 0 | I28: =SUM(I24:I27) -> 0 | J28: =SUM(J24:J27) -> 0 | K28: =SUM(K24:K27) -> 0 | L28: =SUM(L24:L27) -> 0 | ... P28: =SUM(P24:P27) -> 0 | R28: =SUM(R24:R27) -> 0 | S28: =SUM(S24:S27) -> 0 | T28: =SUM(T24:T27) -> 0 | U28: =SUM(U24:U27) -> 0 | W28: =SUM(W24:W27) -> 0
C29: Commercial
C30: AI Monitoring | E30: =E$8*E13*E$20 -> 0 | F30: =F$8*F13*F$20 -> 0 | G30: =G$8*G13*G$20 -> 0 | H30: =H$8*H13*H$20 -> 0 | I30: =I$8*I13*I$20 -> 0 | J30: =J$8*J13*J$20 -> 0 | K30: =K$8*K13*K$20 -> 0 | L30: =L$8*L13*L$20 -> 0 | ... P30: =P$8*P13*P$20 -> 0 | R30: =SUM(E30:G30) -> 0 | S30: =SUM(H30:J30) -> 0 | T30: =SUM(K30:M30) -> 0 | U30: =SUM(N30:P30) -> 0 | W30: =SUM(R30:U30) -> 0
C31: Integration Fee | E31: =E$8*E14*E$20 -> 0 | F31: =F$8*F14*F$20 -> 0 | G31: =G$8*G14*G$20 -> 0 | H31: =H$8*H14*H$20 -> 0 | I31: =I$8*I14*I$20 -> 0 | J31: =J$8*J14*J$20 -> 0 | K31: =K$8*K14*K$20 -> 0 | L31: =L$8*L14*L$20 -> 0 | ... P31: =P$8*P14*P$20 -> 0 | R31: =SUM(E31:G31) -> 0 | S31: =SUM(H31:J31) -> 0 | T31: =SUM(K31:M31) -> 0 | U31: =SUM(N31:P31) -> 0 | W31: =SUM(R31:U31) -> 0
C32: Professional Services - Implementation | E32: =E$8*E15*E$20 -> 0 | F32: =F$8*F15*F$20 -> 0 | G32: =G$8*G15*G$20 -> 0 | H32: =H$8*H15*H$20 -> 0 | I32: =I$8*I15*I$20 -> 0 | J32: =J$8*J15*J$20 -> 0 | K32: =K$8*K15*K$20 -> 0 | L32: =L$8*L15*L$20 -> 0 | ... P32: =P$8*P15*P$20 -> 0 | R32: =SUM(E32:G32) -> 0 | S32: =SUM(H32:J32) -> 0 | T32: =SUM(K32:M32) -> 0 | U32: =SUM(N32:P32) -> 0 | W32: =SUM(R32:U32) -> 0
C33: Professional Services - Monthly | E33: =E$8*E16*E$20 -> 0 | F33: =F$8*F16*F$20 -> 0 | G33: =G$8*G16*G$20 -> 0 | H33: =H$8*H16*H$20 -> 0 | I33: =I$8*I16*I$20 -> 0 | J33: =J$8*J16*J$20 -> 0 | K33: =K$8*K16*K$20 -> 0 | L33: =L$8*L16*L$20 -> 0 | ... P33: =P$8*P16*P$20 -> 0 | R33: =SUM(E33:G33) -> 0 | S33: =SUM(H33:J33) -> 0 | T33: =SUM(K33:M33) -> 0 | U33: =SUM(N33:P33) -> 0 | W33: =SUM(R33:U33) -> 0
C34: Total Commercial Cost of Goods Sold - Third Party Software | E34: =SUM(E30:E33) -> 0 | F34: =SUM(F30:F33) -> 0 | G34: =SUM(G30:G33) -> 0 | H34: =SUM(H30:H33) -> 0 | I34: =SUM(I30:I33) -> 0 | J34: =SUM(J30:J33) -> 0 | K34: =SUM(K30:K33) -> 0 | L34: =SUM(L30:L33) -> 0 | ... P34: =SUM(P30:P33) -> 0 | R34: =SUM(R30:R33) -> 0 | S34: =SUM(S30:S33) -> 0 | T34: =SUM(T30:T33) -> 0 | U34: =SUM(U30:U33) -> 0 | W34: =SUM(W30:W33) -> 0
C36: Total Cost of Goods Sold - Third Party Software | E36: =E28+E34 -> 0 | F36: =F28+F34 -> 0 | G36: =G28+G34 -> 0 | H36: =H28+H34 -> 0 | I36: =I28+I34 -> 0 | J36: =J28+J34 -> 0 | K36: =K28+K34 -> 0 | L36: =L28+L34 -> 0 | ... P36: =P28+P34 -> 0 | R36: =R28+R34 -> 0 | S36: =S28+S34 -> 0 | T36: =T28+T34 -> 0 | U36: =U28+U34 -> 0 | W36: =W28+W34 -> 0
C37: Check | E37: =E8-E28-E34 -> 0 | F37: =F8-F28-F34 -> 0 | G37: =G8-G28-G34 -> 0 | H37: =H8-H28-H34 -> 0 | I37: =I8-I28-I34 -> 0 | J37: =J8-J28-J34 -> 0 | K37: =K8-K28-K34 -> 0 | L37: =L8-L28-L34 -> 0 | ... P37: =P8-P28-P34 -> 0

Sheet Hosting & Internet Fees
C2: 2026 Forecast
C3: Cost of Goods Sold - Hosting & Internet Fees
D5: Metric | E5: Unit | F5: 46023 | G5: =EOMONTH(F5,0)+1 -> 46054 | H5: =EOMONTH(G5,0)+1 -> 46082 | I5: =EOMONTH(H5,0)+1 -> 46113 | J5: =EOMONTH(I5,0)+1 -> 46143 | K5: =EOMONTH(J5,0)+1 -> 46174 | L5: =EOMONTH(K5,0)+1 -> 46204 | M5: =EOMONTH(L5,0)+1 -> 46235 | N5: =EOMONTH(M5,0)+1 -> 46266 | ... Q5: =EOMONTH(P5,0)+1 -> 46357 | S5: Q1 '26 | T5: Q2 '26 | U5: Q3 '26 | V5: Q4 '26 | X5: 2026E
C7: Azure Commercial Cloud | D7: 0.05 | E7: Per Customer | F7: 3500 | G7: =F7*(1+$D7*'Sales Forecast'!E8) -> 3675 | H7: =G7*(1+$D7*'Sales Forecast'!F8) -> 3858.75 | I7: =H7*(1+$D7*'Sales Forecast'!G8) -> 4437.5625 | J7: =I7*(1+$D7*'Sales Forecast'!H8) -> 5546.9531 | K7: =J7*(1+$D7*'Sales Forecast'!I8) -> 6933.6914 | L7: =K7*(1+$D7*'Sales Forecast'!J8) -> 10400.537 | M7: =L7*(1+$D7*'Sales Forecast'!K8) -> 15600.806 | N7: =M7*(1+$D7*'Sales Forecast'!L8) -> 24961.289 | ... Q7: =P7*(1+$D7*'Sales Forecast'!O8) -> 115421 | S7: =SUM(F7:H7) -> 11033.75 | T7: =SUM(I7:K7) -> 16918.207 | U7: =SUM(L7:N7) -> 50962.632 | V7: =SUM(O7:Q7) -> 223253.77 | X7: =SUM(S7:V7) -> 302168.36
C8: AWS Commercial Cloud | D8: 0 | E8: Per Month | F8: 0 | G8: 0 | H8: =G8*(1+$D8) -> 0 | I8: =H8*(1+$D8) -> 0 | J8: =I8*(1+$D8) -> 0 | K8: =J8*(1+$D8) -> 0 | L8: =K8*(1+$D8) -> 0 | M8: =L8*(1+$D8) -> 0 | N8: =M8*(1+$D8) -> 0 | O8: =N8*(1+$D8) -> 0 | ... Q8: =P8*(1+$D8) -> 0 | S8: =SUM(F8:H8) -> 0 | T8: =SUM(I8:K8) -> 0 | U8: =SUM(L8:N8) -> 0 | V8: =SUM(O8:Q8) -> 0 | X8: =SUM(S8:V8) -> 0
C9: Total Cost of Goods Sold - Hosting & Internet Fees | F9: =SUM(F7:F8) -> 3500 | G9: =SUM(G7:G8) -> 3675 | H9: =SUM(H7:H8) -> 3858.75 | I9: =SUM(I7:I8) -> 4437.5625 | J9: =SUM(J7:J8) -> 5546.9531 | K9: =SUM(K7:K8) -> 6933.6914 | L9: =SUM(L7:L8) -> 10400.537 | M9: =SUM(M7:M8) -> 15600.806 | ... Q9: =SUM(Q7:Q8) -> 115421 | S9: =SUM(S7:S8) -> 11033.75 | T9: =SUM(T7:T8) -> 16918.207 | U9: =SUM(U7:U8) -> 50962.632 | V9: =SUM(V7:V8) -> 223253.77 | X9: =SUM(X7:X8) -> 302168.36
C11: Allocation to Federal vs. Commercial | D11: Federal | E11: Commercial
C12: =C7 -> Azure Commercial Cloud | D12: 0.3 | E12: 0.7
C13: =C8 -> AWS Commercial Cloud | D13: 0 | E13: 0
C15: Split to Federal | F15: =SUMPRODUCT(F$7:F$8,$D$12:$D$13)/SUM(F$7:F$8) -> 0.3 | G15: =SUMPRODUCT(G$7:G$8,$D$12:$D$13)/SUM(G$7:G$8) -> 0.3 | H15: =SUMPRODUCT(H$7:H$8,$D$12:$D$13)/SUM(H$7:H$8) -> 0.3 | I15: =SUMPRODUCT(I$7:I$8,$D$12:$D$13)/SUM(I$7:I$8) -> 0.3 | J15: =SUMPRODUCT(J$7:J$8,$D$12:$D$13)/SUM(J$7:J$8) -> 0.3 | K15: =SUMPRODUCT(K$7:K$8,$D$12:$D$13)/SUM(K$7:K$8) -> 0.3 | L15: =SUMPRODUCT(L$7:L$8,$D$12:$D$13)/SUM(L$7:L$8) -> 0.3 | M15: =SUMPRODUCT(M$7:M$8,$D$12:$D$13)/SUM(M$7:M$8) -> 0.3 | ... Q15: =SUMPRODUCT(Q$7:Q$8,$D$12:$D$13)/SUM(Q$7:Q$8) -> 0.3 | S15: =AVERAGE(F15:H15) -> 0.3 | T15: =AVERAGE(I15:K15) -> 0.3 | U15: =AVERAGE(L15:N15) -> 0.3 | V15: =AVERAGE(O15:Q15) -> 0.3 | X15: =AVERAGE(S15:V15) -> 0.3
C16: Split to Commercial | F16: =SUMPRODUCT(F$7:F$8,$E$12:$E$13)/SUM(F$7:F$8) -> 0.7 | G16: =SUMPRODUCT(G$7:G$8,$E$12:$E$13)/SUM(G$7:G$8) -> 0.7 | H16: =SUMPRODUCT(H$7:H$8,$E$12:$E$13)/SUM(H$7:H$8) -> 0.7 | I16: =SUMPRODUCT(I$7:I$8,$E$12:$E$13)/SUM(I$7:I$8) -> 0.7 | J16: =SUMPRODUCT(J$7:J$8,$E$12:$E$13)/SUM(J$7:J$8) -> 0.7 | K16: =SUMPRODUCT(K$7:K$8,$E$12:$E$13)/SUM(K$7:K$8) -> 0.7 | L16: =SUMPRODUCT(L$7:L$8,$E$12:$E$13)/SUM(L$7:L$8) -> 0.7 | M16: =SUMPRODUCT(M$7:M$8,$E$12:$E$13)/SUM(M$7:M$8) -> 0.7 | ... Q16: =SUMPRODUCT(Q$7:Q$8,$E$12:$E$13)/SUM(Q$7:Q$8) -> 0.7 | S16: =AVERAGE(F16:H16) -> 0.7 | T16: =AVERAGE(I16:K16) -> 0.7 | U16: =AVERAGE(L16:N16) -> 0.7 | V16: =AVERAGE(O16:Q16) -> 0.7 | X16: =AVERAGE(S16:V16) -> 0.7
C18: Cost of Goods Sold - Hosting & Internet Fees
C19: Federal
C20: AI Monitoring 1 | D20: 0.65 | F20: =F$9*F$15*$D20 -> 682.5 | G20: =G$9*G$15*$D20 -> 716.625 | H20: =H$9*H$15*$D20 -> 752.45625 | I20: =I$9*I$15*$D20 -> 865.32469 | J20: =J$9*J$15*$D20 -> 1081.6559 | K20: =K$9*K$15*$D20 -> 1352.0698 | L20: =L$9*L$15*$D20 -> 2028.1047 | M20: =M$9*M$15*$D20 -> 3042.1571 | ... Q20: =Q$9*Q$15*$D20 -> 22507.095 | S20: =SUM(F20:H20) -> 2151.5813 | T20: =SUM(I20:K20) -> 3299.0504 | U20: =SUM(L20:N20) -> 9937.7132 | V20: =SUM(O20:Q20) -> 43534.485 | X20: =SUM(S20:V20) -> 58922.83
C21: AI Monitoring 2 | D21: 0.25 | F21: =F$9*F$15*$D21 -> 262.5 | G21: =G$9*G$15*$D21 -> 275.625 | H21: =H$9*H$15*$D21 -> 289.40625 | I21: =I$9*I$15*$D21 -> 332.81719 | J21: =J$9*J$15*$D21 -> 416.02148 | K21: =K$9*K$15*$D21 -> 520.02686 | L21: =L$9*L$15*$D21 -> 780.04028 | M21: =M$9*M$15*$D21 -> 1170.0604 | ... Q21: =Q$9*Q$15*$D21 -> 8656.575 | S21: =SUM(F21:H21) -> 827.53125 | T21: =SUM(I21:K21) -> 1268.8655 | U21: =SUM(L21:N21) -> 3822.1974 | V21: =SUM(O21:Q21) -> 16744.033 | X21: =SUM(S21:V21) -> 22662.627
C22: GRC | D22: 0.1 | F22: =F$9*F$15*$D22 -> 105 | G22: =G$9*G$15*$D22 -> 110.25 | H22: =H$9*H$15*$D22 -> 115.7625 | I22: =I$9*I$15*$D22 -> 133.12688 | J22: =J$9*J$15*$D22 -> 166.40859 | K22: =K$9*K$15*$D22 -> 208.01074 | L22: =L$9*L$15*$D22 -> 312.01611 | M22: =M$9*M$15*$D22 -> 468.02417 | ... Q22: =Q$9*Q$15*$D22 -> 3462.63 | S22: =SUM(F22:H22) -> 331.0125 | T22: =SUM(I22:K22) -> 507.54621 | U22: =SUM(L22:N22) -> 1528.879 | V22: =SUM(O22:Q22) -> 6697.6131 | X22: =SUM(S22:V22) -> 9065.0507
C23: Integration Fee | D23: 0 | F23: =F$9*F$15*$D23 -> 0 | G23: =G$9*G$15*$D23 -> 0 | H23: =H$9*H$15*$D23 -> 0 | I23: =I$9*I$15*$D23 -> 0 | J23: =J$9*J$15*$D23 -> 0 | K23: =K$9*K$15*$D23 -> 0 | L23: =L$9*L$15*$D23 -> 0 | M23: =M$9*M$15*$D23 -> 0 | ... Q23: =Q$9*Q$15*$D23 -> 0 | S23: =SUM(F23:H23) -> 0 | T23: =SUM(I23:K23) -> 0 | U23: =SUM(L23:N23) -> 0 | V23: =SUM(O23:Q23) -> 0 | X23: =SUM(S23:V23) -> 0
C24: Professional Services - Implementation | D24: 0 | F24: =F$9*F$15*$D24 -> 0 | G24: =G$9*G$15*$D24 -> 0 | H24: =H$9*H$15*$D24 -> 0 | I24: =I$9*I$15*$D24 -> 0 | J24: =J$9*J$15*$D24 -> 0 | K24: =K$9*K$15*$D24 -> 0 | L24: =L$9*L$15*$D24 -> 0 | M24: =M$9*M$15*$D24 -> 0 | ... Q24: =Q$9*Q$15*$D24 -> 0 | S24: =SUM(F24:H24) -> 0 | T24: =SUM(I24:K24) -> 0 | U24: =SUM(L24:N24) -> 0 | V24: =SUM(O24:Q24) -> 0 | X24: =SUM(S24:V24) -> 0
C25: Professional Services - Monthly | D25: 0 | F25: =F$9*F$15*$D25 -> 0 | G25: =G$9*G$15*$D25 -> 0 | H25: =H$9*H$15*$D25 -> 0 | I25: =I$9*I$15*$D25 -> 0 | J25: =J$9*J$15*$D25 -> 0 | K25: =K$9*K$15*$D25 -> 0 | L25: =L$9*L$15*$D25 -> 0 | M25: =M$9*M$15*$D25 -> 0 | ... Q25: =Q$9*Q$15*$D25 -> 0 | S25: =SUM(F25:H25) -> 0 | T25: =SUM(I25:K25) -> 0 | U25: =SUM(L25:N25) -> 0 | V25: =SUM(O25:Q25) -> 0 | X25: =SUM(S25:V25) -> 0
C26: Total Federal Cost of Goods Sold - Hosting & Internet Fees | F26: =SUM(F20:F25) -> 1050 | G26: =SUM(G20:G25) -> 1102.5 | H26: =SUM(H20:H25) -> 1157.625 | I26: =SUM(I20:I25) -> 1331.2687 | J26: =SUM(J20:J25) -> 1664.0859 | K26: =SUM(K20:K25) -> 2080.1074 | L26: =SUM(L20:L25) -> 3120.1611 | M26: =SUM(M20:M25) -> 4680.2417 | ... Q26: =SUM(Q20:Q25) -> 34626.3 | S26: =SUM(S20:S25) -> 3310.125 | T26: =SUM(T20:T25) -> 5075.4621 | U26: =SUM(U20:U25) -> 15288.79 | V26: =SUM(V20:V25) -> 66976.131 | X26: =SUM(X20:X25) -> 90650.507
C27: Commercial
C28: AI Monitoring 1 | D28: 0.65 | F28: =F$9*F$16*$D28 -> 1592.5 | G28: =G$9*G$16*$D28 -> 1672.125 | H28: =H$9*H$16*$D28 -> 1755.7313 | I28: =I$9*I$16*$D28 -> 2019.0909 | J28: =J$9*J$16*$D28 -> 2523.8637 | K28: =K$9*K$16*$D28 -> 3154.8296 | L28: =L$9*L$16*$D28 -> 4732.2444 | M28: =M$9*M$16*$D28 -> 7098.3666 | ... Q28: =Q$9*Q$16*$D28 -> 52516.555 | S28: =SUM(F28:H28) -> 5020.3562 | T28: =SUM(I28:K28) -> 7697.7842 | U28: =SUM(L28:N28) -> 23187.997 | V28: =SUM(O28:Q28) -> 101580.47 | X28: =SUM(S28:V28) -> 137486.6
C29: AI Monitoring 2 | D29: 0.25 | F29: =F$9*F$16*$D29 -> 612.5 | G29: =G$9*G$16*$D29 -> 643.125 | H29: =H$9*H$16*$D29 -> 675.28125 | I29: =I$9*I$16*$D29 -> 776.57344 | J29: =J$9*J$16*$D29 -> 970.7168 | K29: =K$9*K$16*$D29 -> 1213.396 | L29: =L$9*L$16*$D29 -> 1820.094 | M29: =M$9*M$16*$D29 -> 2730.141 | ... Q29: =Q$9*Q$16*$D29 -> 20198.675 | S29: =SUM(F29:H29) -> 1930.9062 | T29: =SUM(I29:K29) -> 2960.6862 | U29: =SUM(L29:N29) -> 8918.4606 | V29: =SUM(O29:Q29) -> 39069.41 | X29: =SUM(S29:V29) -> 52879.463
C30: GRC | D30: 0.1 | F30: =F$9*F$16*$D30 -> 245 | G30: =G$9*G$16*$D30 -> 257.25 | H30: =H$9*H$16*$D30 -> 270.1125 | I30: =I$9*I$16*$D30 -> 310.62937 | J30: =J$9*J$16*$D30 -> 388.28672 | K30: =K$9*K$16*$D30 -> 485.3584 | L30: =L$9*L$16*$D30 -> 728.0376 | M30: =M$9*M$16*$D30 -> 1092.0564 | ... Q30: =Q$9*Q$16*$D30 -> 8079.47 | S30: =SUM(F30:H30) -> 772.3625 | T30: =SUM(I30:K30) -> 1184.2745 | U30: =SUM(L30:N30) -> 3567.3842 | V30: =SUM(O30:Q30) -> 15627.764 | X30: =SUM(S30:V30) -> 21151.785
C31: Integration Fee | D31: 0 | F31: =F$9*F$16*$D31 -> 0 | G31: =G$9*G$16*$D31 -> 0 | H31: =H$9*H$16*$D31 -> 0 | I31: =I$9*I$16*$D31 -> 0 | J31: =J$9*J$16*$D31 -> 0 | K31: =K$9*K$16*$D31 -> 0 | L31: =L$9*L$16*$D31 -> 0 | M31: =M$9*M$16*$D31 -> 0 | ... Q31: =Q$9*Q$16*$D31 -> 0 | S31: =SUM(F31:H31) -> 0 | T31: =SUM(I31:K31) -> 0 | U31: =SUM(L31:N31) -> 0 | V31: =SUM(O31:Q31) -> 0 | X31: =SUM(S31:V31) -> 0
C32: Professional Services - Implementation | D32: 0 | F32: =F$9*F$16*$D32 -> 0 | G32: =G$9*G$16*$D32 -> 0 | H32: =H$9*H$16*$D32 -> 0 | I32: =I$9*I$16*$D32 -> 0 | J32: =J$9*J$16*$D32 -> 0 | K32: =K$9*K$16*$D32 -> 0 | L32: =L$9*L$16*$D32 -> 0 | M32: =M$9*M$16*$D32 -> 0 | ... Q32: =Q$9*Q$16*$D32 -> 0 | S32: =SUM(F32:H32) -> 0 | T32: =SUM(I32:K32) -> 0 | U32: =SUM(L32:N32) -> 0 | V32: =SUM(O32:Q32) -> 0 | X32: =SUM(S32:V32) -> 0
C33: Professional Services - Monthly | D33: 0 | F33: =F$9*F$16*$D33 -> 0 | G33: =G$9*G$16*$D33 -> 0 | H33: =H$9*H$16*$D33 -> 0 | I33: =I$9*I$16*$D33 -> 0 | J33: =J$9*J$16*$D33 -> 0 | K33: =K$9*K$16*$D33 -> 0 | L33: =L$9*L$16*$D33 -> 0 | M33: =M$9*M$16*$D33 -> 0 | ... Q33: =Q$9*Q$16*$D33 -> 0 | S33: =SUM(F33:H33) -> 0 | T33: =SUM(I33:K33) -> 0 | U33: =SUM(L33:N33) -> 0 | V33: =SUM(O33:Q33) -> 0 | X33: =SUM(S33:V33) -> 0
C34: Total Commercial Cost of Goods Sold - Hosting & Internet Fees | F34: =SUM(F28:F33) -> 2450 | G34: =SUM(G28:G33) -> 2572.5 | H34: =SUM(H28:H33) -> 2701.125 | I34: =SUM(I28:I33) -> 3106.2937 | J34: =SUM(J28:J33) -> 3882.8672 | K34: =SUM(K28:K33) -> 4853.584 | L34: =SUM(L28:L33) -> 7280.376 | M34: =SUM(M28:M33) -> 10920.564 | ... Q34: =SUM(Q28:Q33) -> 80794.7 | S34: =SUM(S28:S33) -> 7723.625 | T34: =SUM(T28:T33) -> 11842.745 | U34: =SUM(U28:U33) -> 35673.842 | V34: =SUM(V28:V33) -> 156277.64 | X34: =SUM(X28:X33) -> 211517.85
C36: Total Cost of Goods Sold - Hosting & Internet Fees | F36: =F26+F34 -> 3500 | G36: =G26+G34 -> 3675 | H36: =H26+H34 -> 3858.75 | I36: =I26+I34 -> 4437.5625 | J36: =J26+J34 -> 5546.9531 | K36: =K26+K34 -> 6933.6914 | L36: =L26+L34 -> 10400.537 | M36: =M26+M34 -> 15600.806 | ... Q36: =Q26+Q34 -> 115421 | S36: =S26+S34 -> 11033.75 | T36: =T26+T34 -> 16918.207 | U36: =U26+U34 -> 50962.632 | V36: =V26+V34 -> 223253.77 | X36: =X26+X34 -> 302168.36

Sheet Other
C2: 2026 Forecast
C3: Cost of Goods Sold - Other
C5: Vendor Name | D5: Metric | E5: 46023 | F5: =EOMONTH(E5,0)+1 -> 46054 | G5: =EOMONTH(F5,0)+1 -> 46082 | H5: =EOMONTH(G5,0)+1 -> 46113 | I5: =EOMONTH(H5,0)+1 -> 46143 | J5: =EOMONTH(I5,0)+1 -> 46174 | K5: =EOMONTH(J5,0)+1 -> 46204 | L5: =EOMONTH(K5,0)+1 -> 46235 | M5: =EOMONTH(L5,0)+1 -> 46266 | ... P5: =EOMONTH(O5,0)+1 -> 46357 | R5: Q1 '26 | S5: Q2 '26 | T5: Q3 '26 | U5: Q4 '26 | W5: 2026E
C7: PH Additional Services | D7: =IF($D$28="Moderate",#REF!,D31) -> 1400 | E7: =IF('Sales Forecast'!D9>1,'Sales Forecast'!D9-1,0)*Other!$D7 -> 0 | F7: =IF('Sales Forecast'!E9>1,'Sales Forecast'!E9-1,0)*Other!$D7 -> 0 | G7: =IF('Sales Forecast'!F9>1,'Sales Forecast'!F9-1,0)*Other!$D7 -> 0 | H7: =IF('Sales Forecast'!G9>1,'Sales Forecast'!G9-1,0)*Other!$D7 -> 0 | I7: =IF('Sales Forecast'!H9>1,'Sales Forecast'!H9-1,0)*Other!$D7 -> 0 | J7: =IF('Sales Forecast'!I9>1,'Sales Forecast'!I9-1,0)*Other!$D7 -> 0 | K7: =IF('Sales Forecast'!J9>1,'Sales Forecast'!J9-1,0)*Other!$D7 -> 0 | L7: =IF('Sales Forecast'!K9>1,'Sales Forecast'!K9-1,0)*Other!$D7 -> 1400 | ... P7: =IF('Sales Forecast'!O9>1,'Sales Forecast'!O9-1,0)*Other!$D7 -> 4200 | R7: =SUM(E7:G7) -> 0 | S7: =SUM(H7:J7) -> 0 | T7: =SUM(K7:M7) -> 2800 | U7: =SUM(N7:P7) -> 9800 | W7: =SUM(R7:U7) -> 12600
C8: AI Procurement Lab Commission - Federal | D8: 0.0125 | E8: =SUM('Sales Forecast'!D37:D37)*Other!$D8 -> 0 | F8: =SUM('Sales Forecast'!E37:E37)*Other!$D8 -> 0 | G8: =SUM('Sales Forecast'!F37:F37)*Other!$D8 -> 0 | H8: =SUM('Sales Forecast'!G37:G37)*Other!$D8 -> 0 | I8: =SUM('Sales Forecast'!H37:H37)*Other!$D8 -> 0 | J8: =SUM('Sales Forecast'!I37:I37)*Other!$D8 -> 0 | K8: =SUM('Sales Forecast'!J37:J37)*Other!$D8 -> 0 | L8: =SUM('Sales Forecast'!K37:K37)*Other!$D8 -> 0 | ... P8: =SUM('Sales Forecast'!O37:O37)*Other!$D8 -> 187.5 | R8: =SUM(E8:G8) -> 0 | S8: =SUM(H8:J8) -> 0 | T8: =SUM(K8:M8) -> 93.75 | U8: =SUM(N8:P8) -> 468.75 | W8: =SUM(R8:U8) -> 562.5
C9: AI Procurement Lab Commission - Commercial | D9: 0.0125 | E9: =SUM('Sales Forecast'!D43:D43)*Other!$D9 -> 0 | F9: =SUM('Sales Forecast'!E43:E43)*Other!$D9 -> 0 | G9: =SUM('Sales Forecast'!F43:F43)*Other!$D9 -> 0 | H9: =SUM('Sales Forecast'!G43:G43)*Other!$D9 -> 93.75 | I9: =SUM('Sales Forecast'!H43:H43)*Other!$D9 -> 187.5 | J9: =SUM('Sales Forecast'!I43:I43)*Other!$D9 -> 281.25 | K9: =SUM('Sales Forecast'!J43:J43)*Other!$D9 -> 562.5 | L9: =SUM('Sales Forecast'!K43:K43)*Other!$D9 -> 1031.25 | ... P9: =SUM('Sales Forecast'!O43:O43)*Other!$D9 -> 4500 | R9: =SUM(E9:G9) -> 0 | S9: =SUM(H9:J9) -> 562.5 | T9: =SUM(K9:M9) -> 3093.75 | U9: =SUM(N9:P9) -> 10312.5 | W9: =SUM(R9:U9) -> 13968.75
C10: Total Cost of Goods Sold - Other | E10: =SUM(E7:E9) -> 0 | F10: =SUM(F7:F9) -> 0 | G10: =SUM(G7:G9) -> 0 | H10: =SUM(H7:H9) -> 93.75 | I10: =SUM(I7:I9) -> 187.5 | J10: =SUM(J7:J9) -> 281.25 | K10: =SUM(K7:K9) -> 562.5 | L10: =SUM(L7:L9) -> 2431.25 | ... P10: =SUM(P7:P9) -> 8887.5 | R10: =SUM(R7:R9) -> 0 | S10: =SUM(S7:S9) -> 562.5 | T10: =SUM(T7:T9) -> 5987.5 | U10: =SUM(U7:U9) -> 20581.25 | W10: =SUM(W7:W9) -> 27131.25
C12: Cost of Goods Sold - Other
C13: Federal
C14: AI Monitoring | D14: ='Sales Forecast'!V37/SUM('Sales Forecast'!$V$37:$V$37) -> 1 | E14: =SUM(E$7:E$7)*$D14+'Sales Forecast'!D37*Other!$D$8 -> 0 | F14: =SUM(F$7:F$7)*$D14+'Sales Forecast'!E37*Other!$D$8 -> 0 | G14: =SUM(G$7:G$7)*$D14+'Sales Forecast'!F37*Other!$D$8 -> 0 | H14: =SUM(H$7:H$7)*$D14+'Sales Forecast'!G37*Other!$D$8 -> 0 | I14: =SUM(I$7:I$7)*$D14+'Sales Forecast'!H37*Other!$D$8 -> 0 | J14: =SUM(J$7:J$7)*$D14+'Sales Forecast'!I37*Other!$D$8 -> 0 | K14: =SUM(K$7:K$7)*$D14+'Sales Forecast'!J37*Other!$D$8 -> 0 | L14: =SUM(L$7:L$7)*$D14+'Sales Forecast'!K37*Other!$D$8 -> 1400 | ... P14: =SUM(P$7:P$7)*$D14+'Sales Forecast'!O37*Other!$D$8 -> 4387.5 | R14: =SUM(E14:G14) -> 0 | S14: =SUM(H14:J14) -> 0 | T14: =SUM(K14:M14) -> 2893.75 | U14: =SUM(N14:P14) -> 10268.75 | W14: =SUM(R14:U14) -> 13162.5
C15: Integration Fee | E15: 0 | F15: 0 | G15: 0 | H15: 0 | I15: 0 | J15: 0 | K15: 0 | L15: 0 | M15: 0 | N15: 0 | O15: 0 | P15: 0 | R15: =SUM(E15:G15) -> 0 | S15: =SUM(H15:J15) -> 0 | T15: =SUM(K15:M15) -> 0 | U15: =SUM(N15:P15) -> 0 | W15: =SUM(R15:U15) -> 0
C16: Professional Services - Implementation | E16: 0 | F16: 0 | G16: 0 | H16: 0 | I16: 0 | J16: 0 | K16: 0 | L16: 0 | M16: 0 | N16: 0 | O16: 0 | P16: 0 | R16: =SUM(E16:G16) -> 0 | S16: =SUM(H16:J16) -> 0 | T16: =SUM(K16:M16) -> 0 | U16: =SUM(N16:P16) -> 0 | W16: =SUM(R16:U16) -> 0
C17: Professional Services - Monthly | E17: 0 | F17: 0 | G17: 0 | H17: 0 | I17: 0 | J17: 0 | K17: 0 | L17: 0 | M17: 0 | N17: 0 | O17: 0 | P17: 0 | R17: =SUM(E17:G17) -> 0 | S17: =SUM(H17:J17) -> 0 | T17: =SUM(K17:M17) -> 0 | U17: =SUM(N17:P17) -> 0 | W17: =SUM(R17:U17) -> 0
C18: Total Federal Cost of Goods Sold - Other | E18: =SUM(E14:E17) -> 0 | F18: =SUM(F14:F17) -> 0 | G18: =SUM(G14:G17) -> 0 | H18: =SUM(H14:H17) -> 0 | I18: =SUM(I14:I17) -> 0 | J18: =SUM(J14:J17) -> 0 | K18: =SUM(K14:K17) -> 0 | L18: =SUM(L14:L17) -> 1400 | ... P18: =SUM(P14:P17) -> 4387.5 | R18: =SUM(R14:R17) -> 0 | S18: =SUM(S14:S17) -> 0 | T18: =SUM(T14:T17) -> 2893.75 | U18: =SUM(U14:U17) -> 10268.75 | W18: =SUM(R18:U18) -> 13162.5
C19: Commercial
C20: AI Monitoring | E20: ='Sales Forecast'!D43*Other!$D$9 -> 0 | F20: ='Sales Forecast'!E43*Other!$D$9 -> 0 | G20: ='Sales Forecast'!F43*Other!$D$9 -> 0 | H20: ='Sales Forecast'!G43*Other!$D$9 -> 93.75 | I20: ='Sales Forecast'!H43*Other!$D$9 -> 187.5 | J20: ='Sales Forecast'!I43*Other!$D$9 -> 281.25 | K20: ='Sales Forecast'!J43*Other!$D$9 -> 562.5 | L20: ='Sales Forecast'!K43*Other!$D$9 -> 1031.25 | ... P20: ='Sales Forecast'!O43*Other!$D$9 -> 4500 | R20: =SUM(E20:G20) -> 0 | S20: =SUM(H20:J20) -> 562.5 | T20: =SUM(K20:M20) -> 3093.75 | U20: =SUM(N20:P20) -> 10312.5 | W20: =SUM(R20:U20) -> 13968.75
C21: Integration Fee | E21: 0 | F21: 0 | G21: 0 | H21: 0 | I21: 0 | J21: 0 | K21: 0 | L21: 0 | M21: 0 | N21: 0 | O21: 0 | P21: 0 | R21: =SUM(E21:G21) -> 0 | S21: =SUM(H21:J21) -> 0 | T21: =SUM(K21:M21) -> 0 | U21: =SUM(N21:P21) -> 0 | W21: =SUM(R21:U21) -> 0
C22: Professional Services - Implementation | E22: 0 | F22: 0 | G22: 0 | H22: 0 | I22: 0 | J22: 0 | K22: 0 | L22: 0 | M22: 0 | N22: 0 | O22: 0 | P22: 0 | R22: =SUM(E22:G22) -> 0 | S22: =SUM(H22:J22) -> 0 | T22: =SUM(K22:M22) -> 0 | U22: =SUM(N22:P22) -> 0 | W22: =SUM(R22:U22) -> 0
C23: Professional Services - Monthly | E23: 0 | F23: 0 | G23: 0 | H23: 0 | I23: 0 | J23: 0 | K23: 0 | L23: 0 | M23: 0 | N23: 0 | O23: 0 | P23: 0 | R23: =SUM(E23:G23) -> 0 | S23: =SUM(H23:J23) -> 0 | T23: =SUM(K23:M23) -> 0 | U23: =SUM(N23:P23) -> 0 | W23: =SUM(R23:U23) -> 0
C24: Total Commercial Cost of Goods Sold - Other | E24: =SUM(E20:E23) -> 0 | F24: =SUM(F20:F23) -> 0 | G24: =SUM(G20:G23) -> 0 | H24: =SUM(H20:H23) -> 93.75 | I24: =SUM(I20:I23) -> 187.5 | J24: =SUM(J20:J23) -> 281.25 | K24: =SUM(K20:K23) -> 562.5 | L24: =SUM(L20:L23) -> 1031.25 | ... P24: =SUM(P20:P23) -> 4500 | R24: =SUM(R20:R23) -> 0 | S24: =SUM(S20:S23) -> 562.5 | T24: =SUM(T20:T23) -> 3093.75 | U24: =SUM(U20:U23) -> 10312.5 | W24: =SUM(R24:U24) -> 13968.75
C26: Total Cost of Goods Sold - Other | E26: =E18+E24 -> 0 | F26: =F18+F24 -> 0 | G26: =G18+G24 -> 0 | H26: =H18+H24 -> 93.75 | I26: =I18+I24 -> 187.5 | J26: =J18+J24 -> 281.25 | K26: =K18+K24 -> 562.5 | L26: =L18+L24 -> 2431.25 | ... P26: =P18+P24 -> 8887.5 | R26: =R18+R24 -> 0 | S26: =S18+S24 -> 562.5 | T26: =T18+T24 -> 5987.5 | U26: =U18+U24 -> 20581.25 | W26: =W18+W24 -> 27131.25
C28: FedRAMP Path | D28: ='Product & Pricing List'!$D$10 -> High
C29: Monthly GSS One PaaS Fee - PH Testing - High | D29: 6000
C30: Monthly GSS One PaaS Fee - Production - High | D30: 7000
C31: PH Additional Services - High | D31: 1400

Sheet OpEx >>>

Sheet Salaries, Wages, & Benefits
C2: 2026 Forecast
C3: Salaries, Wages, & Benefits
C5: Job Title | D5: Department | E5: Annual Salary | F5: 46023 | G5: =EOMONTH(F5,0)+1 -> 46054 | H5: =EOMONTH(G5,0)+1 -> 46082 | I5: =EOMONTH(H5,0)+1 -> 46113 | J5: =EOMONTH(I5,0)+1 -> 46143 | K5: =EOMONTH(J5,0)+1 -> 46174 | L5: =EOMONTH(K5,0)+1 -> 46204 | M5: =EOMONTH(L5,0)+1 -> 46235 | N5: =EOMONTH(M5,0)+1 -> 46266 | ... Q5: =EOMONTH(P5,0)+1 -> 46357 | S5: Q1 '26 | T5: Q2 '26 | U5: Q3 '26 | V5: Q4 '26 | X5: 2026E
C7: Chief Executive Officer | D7: Executive & Administrative | E7: 32000 | F7: =$E7/12 -> 2666.6667 | G7: =$E7/12 -> 2666.6667 | H7: =$E7/12 -> 2666.6667 | I7: =$E7/12 -> 2666.6667 | J7: =$E7/12 -> 2666.6667 | K7: =$E7/12 -> 2666.6667 | L7: =$E7/12 -> 2666.6667 | M7: =$E7/12 -> 2666.6667 | ... Q7: =$E7/12 -> 2666.6667 | S7: =SUM(F7:H7) -> 8000 | T7: =SUM(I7:K7) -> 8000 | U7: =SUM(L7:N7) -> 8000 | V7: =SUM(O7:Q7) -> 8000 | X7: =SUM(S7:V7) -> 32000
C8: SVP Special Projects | D8: Executive & Administrative | E8: 60000 | F8: =$E8/12 -> 5000 | G8: =$E8/12 -> 5000 | H8: =$E8/12 -> 5000 | I8: =$E8/12 -> 5000 | J8: =$E8/12 -> 5000 | K8: =$E8/12 -> 5000 | L8: =$E8/12 -> 5000 | M8: =$E8/12 -> 5000 | ... Q8: =$E8/12 -> 5000 | S8: =SUM(F8:H8) -> 15000 | T8: =SUM(I8:K8) -> 15000 | U8: =SUM(L8:N8) -> 15000 | V8: =SUM(O8:Q8) -> 15000 | X8: =SUM(S8:V8) -> 60000
C9: Chief Technology Officer | D9: Executive & Administrative | E9: 180000 | F9: 16666.667 | G9: =$E9/12 -> 15000 | H9: =$E9/12 -> 15000 | I9: =$E9/12 -> 15000 | J9: =$E9/12 -> 15000 | K9: =$E9/12 -> 15000 | L9: =$E9/12 -> 15000 | M9: =$E9/12 -> 15000 | N9: =$E9/12 -> 15000 | ... Q9: =$E9/12 -> 15000 | S9: =SUM(F9:H9) -> 46666.667 | T9: =SUM(I9:K9) -> 45000 | U9: =SUM(L9:N9) -> 45000 | V9: =SUM(O9:Q9) -> 45000 | X9: =SUM(S9:V9) -> 181666.67
C10: COO | D10: Executive & Administrative | E10: 175000 | F10: =$E10/12 -> 14583.333 | G10: =$E10/12 -> 14583.333 | H10: =$E10/12 -> 14583.333 | I10: =$E10/12 -> 14583.333 | J10: =$E10/12 -> 14583.333 | K10: =$E10/12 -> 14583.333 | L10: =$E10/12 -> 14583.333 | M10: =$E10/12 -> 14583.333 | ... Q10: =$E10/12 -> 14583.333 | S10: =SUM(F10:H10) -> 43750 | T10: =SUM(I10:K10) -> 43750 | U10: =SUM(L10:N10) -> 43750 | V10: =SUM(O10:Q10) -> 43750 | X10: =SUM(S10:V10) -> 175000
C11: Controller | D11: Executive & Administrative | E11: 60000 | F11: =$E11/12 -> 5000 | G11: =$E11/12 -> 5000 | H11: =$E11/12 -> 5000 | I11: =$E11/12 -> 5000 | J11: =$E11/12 -> 5000 | K11: =$E11/12 -> 5000 | L11: =$E11/12 -> 5000 | M11: =$E11/12 -> 5000 | ... Q11: =$E11/12 -> 5000 | S11: =SUM(F11:H11) -> 15000 | T11: =SUM(I11:K11) -> 15000 | U11: =SUM(L11:N11) -> 15000 | V11: =SUM(O11:Q11) -> 15000 | X11: =SUM(S11:V11) -> 60000
C12: SVP of Federal | D12: Sales & Marketing | E12: 180000 | F12: =$E12/12 -> 15000 | G12: =$E12/12 -> 15000 | H12: =$E12/12 -> 15000 | I12: =$E12/12 -> 15000 | J12: =$E12/12 -> 15000 | K12: =$E12/12 -> 15000 | L12: =$E12/12 -> 15000 | M12: =$E12/12 -> 15000 | ... Q12: =$E12/12 -> 15000 | S12: =SUM(F12:H12) -> 45000 | T12: =SUM(I12:K12) -> 45000 | U12: =SUM(L12:N12) -> 45000 | V12: =SUM(O12:Q12) -> 45000 | X12: =SUM(S12:V12) -> 180000
C13: Director of Product Research | D13: Product Management | E13: 180000 | F13: =$E13/12 -> 15000 | G13: =$E13/12 -> 15000 | H13: =$E13/12 -> 15000 | I13: =$E13/12 -> 15000 | J13: =$E13/12 -> 15000 | K13: =$E13/12 -> 15000 | L13: =$E13/12 -> 15000 | M13: =$E13/12 -> 15000 | ... Q13: =$E13/12 -> 15000 | S13: =SUM(F13:H13) -> 45000 | T13: =SUM(I13:K13) -> 45000 | U13: =SUM(L13:N13) -> 45000 | V13: =SUM(O13:Q13) -> 45000 | X13: =SUM(S13:V13) -> 180000
C14: Director of Sales | D14: Sales & Marketing | E14: 90000 | F14: =$E14/12 -> 7500 | G14: =$E14/12 -> 7500 | H14: =$E14/12 -> 7500 | I14: =$E14/12 -> 7500 | J14: =$E14/12 -> 7500 | K14: =$E14/12 -> 7500 | L14: =$E14/12 -> 7500 | M14: =$E14/12 -> 7500 | ... Q14: =$E14/12 -> 7500 | S14: =SUM(F14:H14) -> 22500 | T14: =SUM(I14:K14) -> 22500 | U14: =SUM(L14:N14) -> 22500 | V14: =SUM(O14:Q14) -> 22500 | X14: =SUM(S14:V14) -> 90000
C15: Director of Channel Sales | D15: Sales & Marketing | E15: 90000 | F15: =$E15/12 -> 7500 | G15: =$E15/12 -> 7500 | H15: =$E15/12 -> 7500 | I15: =$E15/12 -> 7500 | J15: =$E15/12 -> 7500 | K15: =$E15/12 -> 7500 | L15: =$E15/12 -> 7500 | M15: =$E15/12 -> 7500 | ... Q15: =$E15/12 -> 7500 | S15: =SUM(F15:H15) -> 22500 | T15: =SUM(I15:K15) -> 22500 | U15: =SUM(L15:N15) -> 22500 | V15: =SUM(O15:Q15) -> 22500 | X15: =SUM(S15:V15) -> 90000
C16: Customer Success Manager | D16: Customer Success | E16: 65000 | F16: =$E16/12 -> 5416.6667 | G16: =$E16/12 -> 5416.6667 | H16: =$E16/12 -> 5416.6667 | I16: =$E16/12 -> 5416.6667 | J16: =$E16/12 -> 5416.6667 | K16: =$E16/12 -> 5416.6667 | L16: =$E16/12 -> 5416.6667 | M16: =$E16/12 -> 5416.6667 | ... Q16: =$E16/12 -> 5416.6667 | S16: =SUM(F16:H16) -> 16250 | T16: =SUM(I16:K16) -> 16250 | U16: =SUM(L16:N16) -> 16250 | V16: =SUM(O16:Q16) -> 16250 | X16: =SUM(S16:V16) -> 65000
C17: Total Salaries & Wages | F17: =SUM(F7:F16) -> 94333.333 | G17: =SUM(G7:G16) -> 92666.667 | H17: =SUM(H7:H16) -> 92666.667 | I17: =SUM(I7:I16) -> 92666.667 | J17: =SUM(J7:J16) -> 92666.667 | K17: =SUM(K7:K16) -> 92666.667 | L17: =SUM(L7:L16) -> 92666.667 | M17: =SUM(M7:M16) -> 92666.667 | ... Q17: =SUM(Q7:Q16) -> 92666.667 | S17: =SUM(S7:S16) -> 279666.67 | T17: =SUM(T7:T16) -> 278000 | U17: =SUM(U7:U16) -> 278000 | V17: =SUM(V7:V16) -> 278000 | X17: =SUM(X7:X16) -> 1113666.7
C19: Employer Payroll Taxes | F19: =F17*F20 -> 11428.978 | G19: =G17*G20 -> 11227.043 | H19: =H17*H20 -> 7849.4598 | I19: =I17*I20 -> 7849.4537 | J19: =J17*J20 -> 7849.4591 | K19: =K17*K20 -> 7225.2095 | L19: =L17*L20 -> 7181.4271 | M19: =M17*M20 -> 7181.4271 | ... Q19: =Q17*Q20 -> 7181.4271 | S19: =SUM(F19:H19) -> 30505.481 | T19: =SUM(I19:K19) -> 22924.122 | U19: =SUM(L19:N19) -> 21544.281 | V19: =SUM(O19:Q19) -> 21544.281 | X19: =SUM(S19:V19) -> 96518.166
C20: % of Total Salaries & Wages | F20: 0.12115524 | G20: 0.12115514 | H20: 0.084706401 | I20: 0.084706335 | J20: 0.084706393 | K20: 0.077969886 | L20: 0.077497415 | M20: 0.077497415 | N20: 0.077497415 | O20: 0.077497415 | P20: 0.077497415 | Q20: 0.077497415
C22: Payroll Processing Fees | F22: =F17*F23 -> 773.53333 | G22: =G17*G23 -> 759.86667 | H22: =H17*H23 -> 759.86667 | I22: =I17*I23 -> 759.86667 | J22: =J17*J23 -> 759.86667 | K22: =K17*K23 -> 759.86667 | L22: =L17*L23 -> 759.86667 | M22: =M17*M23 -> 759.86667 | ... Q22: =Q17*Q23 -> 759.86667 | S22: =SUM(F22:H22) -> 2293.2667 | T22: =SUM(I22:K22) -> 2279.6 | U22: =SUM(L22:N22) -> 2279.6 | V22: =SUM(O22:Q22) -> 2279.6 | X22: =SUM(S22:V22) -> 9132.0667
C23: % of Total Salaries & Wages | F23: 0.0082 | G23: 0.0082 | H23: 0.0082 | I23: 0.0082 | J23: 0.0082 | K23: 0.0082 | L23: 0.0082 | M23: 0.0082 | N23: 0.0082 | O23: 0.0082 | P23: 0.0082 | Q23: 0.0082
C25: Medical Benefits | E25: 350 | F25: 0 | G25: 0 | H25: 0 | I25: =$E25*COUNTIFS(I$7:I$16,">"&0) -> 3500 | J25: =$E25*COUNTIFS(J$7:J$16,">"&0) -> 3500 | K25: =$E25*COUNTIFS(K$7:K$16,">"&0) -> 3500 | L25: =$E25*COUNTIFS(L$7:L$16,">"&0) -> 3500 | M25: =$E25*COUNTIFS(M$7:M$16,">"&0) -> 3500 | N25: =$E25*COUNTIFS(N$7:N$16,">"&0) -> 3500 | O25: =$E25*COUNTIFS(O$7:O$16,">"&0) -> 3500 | P25: =$E25*COUNTIFS(P$7:P$16,">"&0) -> 3500 | Q25: =$E25*COUNTIFS(Q$7:Q$16,">"&0) -> 3500 | S25: =SUM(F25:H25) -> 0 | T25: =SUM(I25:K25) -> 10500 | U25: =SUM(L25:N25) -> 10500 | V25: =SUM(O25:Q25) -> 10500 | X25: =SUM(S25:V25) -> 31500
C27: Accrued Bonuses | E27: 0 | F27: =F17*$E27 -> 0 | G27: =G17*$E27 -> 0 | H27: =H17*$E27 -> 0 | I27: =I17*$E27 -> 0 | J27: =J17*$E27 -> 0 | K27: =K17*$E27 -> 0 | L27: =L17*$E27 -> 0 | M27: =M17*$E27 -> 0 | ... Q27: =Q17*$E27 -> 0 | S27: =SUM(F27:H27) -> 0 | T27: =SUM(I27:K27) -> 0 | U27: =SUM(L27:N27) -> 0 | V27: =SUM(O27:Q27) -> 0 | X27: =SUM(S27:V27) -> 0
C29: Total Salaries, Wages, & Benefits | F29: =F17+F19+F22+F25+F27 -> 106535.84 | G29: =G17+G19+G22+G25+G27 -> 104653.58 | H29: =H17+H19+H22+H25+H27 -> 101275.99 | I29: =I17+I19+I22+I25+I27 -> 104775.99 | J29: =J17+J19+J22+J25+J27 -> 104775.99 | K29: =K17+K19+K22+K25+K27 -> 104151.74 | L29: =L17+L19+L22+L25+L27 -> 104107.96 | M29: =M17+M19+M22+M25+M27 -> 104107.96 | ... Q29: =Q17+Q19+Q22+Q25+Q27 -> 104107.96 | S29: =S17+S19+S22+S25+S27 -> 312465.41 | T29: =T17+T19+T22+T25+T27 -> 313703.72 | U29: =U17+U19+U22+U25+U27 -> 312323.88 | V29: =V17+V19+V22+V25+V27 -> 312323.88 | X29: =X17+X19+X22+X25+X27 -> 1250816.9
C31: Hours Allocated to Cost of Goods Sold - Labor
C32: Chief Strategy Officer | F32: =Labor!F$36*INDEX(Labor!$E$7:$E$15,MATCH('Salaries, Wages, & Benefits'!$C32,Labor!$C$7:$C$15,0),1) -> 0 | G32: =Labor!G$36*INDEX(Labor!$E$7:$E$15,MATCH('Salaries, Wages, & Benefits'!$C32,Labor!$C$7:$C$15,0),1) -> 0.15 | H32: =Labor!H$36*INDEX(Labor!$E$7:$E$15,MATCH('Salaries, Wages, & Benefits'!$C32,Labor!$C$7:$C$15,0),1) -> 0.15 | I32: =Labor!I$36*INDEX(Labor!$E$7:$E$15,MATCH('Salaries, Wages, & Benefits'!$C32,Labor!$C$7:$C$15,0),1) -> 10.6 | J32: =Labor!J$36*INDEX(Labor!$E$7:$E$15,MATCH('Salaries, Wages, & Benefits'!$C32,Labor!$C$7:$C$15,0),1) -> 21.05 | K32: =Labor!K$36*INDEX(Labor!$E$7:$E$15,MATCH('Salaries, Wages, & Benefits'!$C32,Labor!$C$7:$C$15,0),1) -> 31.35 | L32: =Labor!L$36*INDEX(Labor!$E$7:$E$15,MATCH('Salaries, Wages, & Benefits'!$C32,Labor!$C$7:$C$15,0),1) -> 62.4 | M32: =Labor!M$36*INDEX(Labor!$E$7:$E$15,MATCH('Salaries, Wages, & Benefits'!$C32,Labor!$C$7:$C$15,0),1) -> 113.3 | ... Q32: =Labor!Q$36*INDEX(Labor!$E$7:$E$15,MATCH('Salaries, Wages, & Benefits'!$C32,Labor!$C$7:$C$15,0),1) -> 509.75 | S32: =SUM(F32:H32) -> 0.3 | T32: =SUM(I32:K32) -> 63 | U32: =SUM(L32:N32) -> 350.05 | V32: =SUM(O32:Q32) -> 1173.55 | X32: =SUM(S32:V32) -> 1586.9
C33: Chief Technology Officer | F33: =Labor!F$36*INDEX(Labor!$E$7:$E$15,MATCH('Salaries, Wages, & Benefits'!$C33,Labor!$C$7:$C$15,0),1) -> 0 | G33: =Labor!G$36*INDEX(Labor!$E$7:$E$15,MATCH('Salaries, Wages, & Benefits'!$C33,Labor!$C$7:$C$15,0),1) -> 0.15 | H33: =Labor!H$36*INDEX(Labor!$E$7:$E$15,MATCH('Salaries, Wages, & Benefits'!$C33,Labor!$C$7:$C$15,0),1) -> 0.15 | I33: =Labor!I$36*INDEX(Labor!$E$7:$E$15,MATCH('Salaries, Wages, & Benefits'!$C33,Labor!$C$7:$C$15,0),1) -> 10.6 | J33: =Labor!J$36*INDEX(Labor!$E$7:$E$15,MATCH('Salaries, Wages, & Benefits'!$C33,Labor!$C$7:$C$15,0),1) -> 21.05 | K33: =Labor!K$36*INDEX(Labor!$E$7:$E$15,MATCH('Salaries, Wages, & Benefits'!$C33,Labor!$C$7:$C$15,0),1) -> 31.35 | L33: =Labor!L$36*INDEX(Labor!$E$7:$E$15,MATCH('Salaries, Wages, & Benefits'!$C33,Labor!$C$7:$C$15,0),1) -> 62.4 | M33: =Labor!M$36*INDEX(Labor!$E$7:$E$15,MATCH('Salaries, Wages, & Benefits'!$C33,Labor!$C$7:$C$15,0),1) -> 113.3 | ... Q33: =Labor!Q$36*INDEX(Labor!$E$7:$E$15,MATCH('Salaries, Wages, & Benefits'!$C33,Labor!$C$7:$C$15,0),1) -> 509.75 | S33: =SUM(F33:H33) -> 0.3 | T33: =SUM(I33:K33) -> 63 | U33: =SUM(L33:N33) -> 350.05 | V33: =SUM(O33:Q33) -> 1173.55 | X33: =SUM(S33:V33) -> 1586.9
C34: VP of AI Governance & Product Manager | F34: =Labor!F$36*INDEX(Labor!$E$7:$E$15,MATCH('Salaries, Wages, & Benefits'!$C34,Labor!$C$7:$C$15,0),1) -> 0 | G34: =Labor!G$36*INDEX(Labor!$E$7:$E$15,MATCH('Salaries, Wages, & Benefits'!$C34,Labor!$C$7:$C$15,0),1) -> 0.15 | H34: =Labor!H$36*INDEX(Labor!$E$7:$E$15,MATCH('Salaries, Wages, & Benefits'!$C34,Labor!$C$7:$C$15,0),1) -> 0.15 | I34: =Labor!I$36*INDEX(Labor!$E$7:$E$15,MATCH('Salaries, Wages, & Benefits'!$C34,Labor!$C$7:$C$15,0),1) -> 10.6 | J34: =Labor!J$36*INDEX(Labor!$E$7:$E$15,MATCH('Salaries, Wages, & Benefits'!$C34,Labor!$C$7:$C$15,0),1) -> 21.05 | K34: =Labor!K$36*INDEX(Labor!$E$7:$E$15,MATCH('Salaries, Wages, & Benefits'!$C34,Labor!$C$7:$C$15,0),1) -> 31.35 | L34: =Labor!L$36*INDEX(Labor!$E$7:$E$15,MATCH('Salaries, Wages, & Benefits'!$C34,Labor!$C$7:$C$15,0),1) -> 62.4 | M34: =Labor!M$36*INDEX(Labor!$E$7:$E$15,MATCH('Salaries, Wages, & Benefits'!$C34,Labor!$C$7:$C$15,0),1) -> 113.3 | ... Q34: =Labor!Q$36*INDEX(Labor!$E$7:$E$15,MATCH('Salaries, Wages, & Benefits'!$C34,Labor!$C$7:$C$15,0),1) -> 509.75 | S34: =SUM(F34:H34) -> 0.3 | T34: =SUM(I34:K34) -> 63 | U34: =SUM(L34:N34) -> 350.05 | V34: =SUM(O34:Q34) -> 1173.55 | X34: =SUM(S34:V34) -> 1586.9
C35: Director of AI Governance & Product Research | F35: =Labor!F$36*INDEX(Labor!$E$7:$E$15,MATCH('Salaries, Wages, & Benefits'!$C35,Labor!$C$7:$C$15,0),1) -> 0 | G35: =Labor!G$36*INDEX(Labor!$E$7:$E$15,MATCH('Salaries, Wages, & Benefits'!$C35,Labor!$C$7:$C$15,0),1) -> 0.3 | H35: =Labor!H$36*INDEX(Labor!$E$7:$E$15,MATCH('Salaries, Wages, & Benefits'!$C35,Labor!$C$7:$C$15,0),1) -> 0.3 | I35: =Labor!I$36*INDEX(Labor!$E$7:$E$15,MATCH('Salaries, Wages, & Benefits'!$C35,Labor!$C$7:$C$15,0),1) -> 21.2 | J35: =Labor!J$36*INDEX(Labor!$E$7:$E$15,MATCH('Salaries, Wages, & Benefits'!$C35,Labor!$C$7:$C$15,0),1) -> 42.1 | K35: =Labor!K$36*INDEX(Labor!$E$7:$E$15,MATCH('Salaries, Wages, & Benefits'!$C35,Labor!$C$7:$C$15,0),1) -> 62.7 | L35: =Labor!L$36*INDEX(Labor!$E$7:$E$15,MATCH('Salaries, Wages, & Benefits'!$C35,Labor!$C$7:$C$15,0),1) -> 124.8 | M35: =Labor!M$36*INDEX(Labor!$E$7:$E$15,MATCH('Salaries, Wages, & Benefits'!$C35,Labor!$C$7:$C$15,0),1) -> 226.6 | ... Q35: =Labor!Q$36*INDEX(Labor!$E$7:$E$15,MATCH('Salaries, Wages, & Benefits'!$C35,Labor!$C$7:$C$15,0),1) -> 1019.5 | S35: =SUM(F35:H35) -> 0.6 | T35: =SUM(I35:K35) -> 126 | U35: =SUM(L35:N35) -> 700.1 | V35: =SUM(O35:Q35) -> 2347.1 | X35: =SUM(S35:V35) -> 3173.8
C36: Director of Sales | F36: =Labor!F$36*INDEX(Labor!$E$7:$E$15,MATCH('Salaries, Wages, & Benefits'!$C36,Labor!$C$7:$C$15,0),1) -> 0 | G36: =Labor!G$36*INDEX(Labor!$E$7:$E$15,MATCH('Salaries, Wages, & Benefits'!$C36,Labor!$C$7:$C$15,0),1) -> 0.15 | H36: =Labor!H$36*INDEX(Labor!$E$7:$E$15,MATCH('Salaries, Wages, & Benefits'!$C36,Labor!$C$7:$C$15,0),1) -> 0.15 | I36: =Labor!I$36*INDEX(Labor!$E$7:$E$15,MATCH('Salaries, Wages, & Benefits'!$C36,Labor!$C$7:$C$15,0),1) -> 10.6 | J36: =Labor!J$36*INDEX(Labor!$E$7:$E$15,MATCH('Salaries, Wages, & Benefits'!$C36,Labor!$C$7:$C$15,0),1) -> 21.05 | K36: =Labor!K$36*INDEX(Labor!$E$7:$E$15,MATCH('Salaries, Wages, & Benefits'!$C36,Labor!$C$7:$C$15,0),1) -> 31.35 | L36: =Labor!L$36*INDEX(Labor!$E$7:$E$15,MATCH('Salaries, Wages, & Benefits'!$C36,Labor!$C$7:$C$15,0),1) -> 62.4 | M36: =Labor!M$36*INDEX(Labor!$E$7:$E$15,MATCH('Salaries, Wages, & Benefits'!$C36,Labor!$C$7:$C$15,0),1) -> 113.3 | ... Q36: =Labor!Q$36*INDEX(Labor!$E$7:$E$15,MATCH('Salaries, Wages, & Benefits'!$C36,Labor!$C$7:$C$15,0),1) -> 509.75 | S36: =SUM(F36:H36) -> 0.3 | T36: =SUM(I36:K36) -> 63 | U36: =SUM(L36:N36) -> 350.05 | V36: =SUM(O36:Q36) -> 1173.55 | X36: =SUM(S36:V36) -> 1586.9
C37: Director of Channel Sales | F37: =Labor!F$36*INDEX(Labor!$E$7:$E$15,MATCH('Salaries, Wages, & Benefits'!$C37,Labor!$C$7:$C$15,0),1) -> 0 | G37: =Labor!G$36*INDEX(Labor!$E$7:$E$15,MATCH('Salaries, Wages, & Benefits'!$C37,Labor!$C$7:$C$15,0),1) -> 0.15 | H37: =Labor!H$36*INDEX(Labor!$E$7:$E$15,MATCH('Salaries, Wages, & Benefits'!$C37,Labor!$C$7:$C$15,0),1) -> 0.15 | I37: =Labor!I$36*INDEX(Labor!$E$7:$E$15,MATCH('Salaries, Wages, & Benefits'!$C37,Labor!$C$7:$C$15,0),1) -> 10.6 | J37: =Labor!J$36*INDEX(Labor!$E$7:$E$15,MATCH('Salaries, Wages, & Benefits'!$C37,Labor!$C$7:$C$15,0),1) -> 21.05 | K37: =Labor!K$36*INDEX(Labor!$E$7:$E$15,MATCH('Salaries, Wages, & Benefits'!$C37,Labor!$C$7:$C$15,0),1) -> 31.35 | L37: =Labor!L$36*INDEX(Labor!$E$7:$E$15,MATCH('Salaries, Wages, & Benefits'!$C37,Labor!$C$7:$C$15,0),1) -> 62.4 | M37: =Labor!M$36*INDEX(Labor!$E$7:$E$15,MATCH('Salaries, Wages, & Benefits'!$C37,Labor!$C$7:$C$15,0),1) -> 113.3 | ... Q37: =Labor!Q$36*INDEX(Labor!$E$7:$E$15,MATCH('Salaries, Wages, & Benefits'!$C37,Labor!$C$7:$C$15,0),1) -> 509.75 | S37: =SUM(F37:H37) -> 0.3 | T37: =SUM(I37:K37) -> 63 | U37: =SUM(L37:N37) -> 350.05 | V37: =SUM(O37:Q37) -> 1173.55 | X37: =SUM(S37:V37) -> 1586.9
C38: Customer Success Manager | F38: =Labor!F$36*INDEX(Labor!$E$7:$E$15,MATCH('Salaries, Wages, & Benefits'!$C38,Labor!$C$7:$C$15,0),1) -> 0 | G38: =Labor!G$36*INDEX(Labor!$E$7:$E$15,MATCH('Salaries, Wages, & Benefits'!$C38,Labor!$C$7:$C$15,0),1) -> 0.15 | H38: =Labor!H$36*INDEX(Labor!$E$7:$E$15,MATCH('Salaries, Wages, & Benefits'!$C38,Labor!$C$7:$C$15,0),1) -> 0.15 | I38: =Labor!I$36*INDEX(Labor!$E$7:$E$15,MATCH('Salaries, Wages, & Benefits'!$C38,Labor!$C$7:$C$15,0),1) -> 10.6 | J38: =Labor!J$36*INDEX(Labor!$E$7:$E$15,MATCH('Salaries, Wages, & Benefits'!$C38,Labor!$C$7:$C$15,0),1) -> 21.05 | K38: =Labor!K$36*INDEX(Labor!$E$7:$E$15,MATCH('Salaries, Wages, & Benefits'!$C38,Labor!$C$7:$C$15,0),1) -> 31.35 | L38: =Labor!L$36*INDEX(Labor!$E$7:$E$15,MATCH('Salaries, Wages, & Benefits'!$C38,Labor!$C$7:$C$15,0),1) -> 62.4 | M38: =Labor!M$36*INDEX(Labor!$E$7:$E$15,MATCH('Salaries, Wages, & Benefits'!$C38,Labor!$C$7:$C$15,0),1) -> 113.3 | ... Q38: =Labor!Q$36*INDEX(Labor!$E$7:$E$15,MATCH('Salaries, Wages, & Benefits'!$C38,Labor!$C$7:$C$15,0),1) -> 509.75 | S38: =SUM(F38:H38) -> 0.3 | T38: =SUM(I38:K38) -> 63 | U38: =SUM(L38:N38) -> 350.05 | V38: =SUM(O38:Q38) -> 1173.55 | X38: =SUM(S38:V38) -> 1586.9
C39: Total Hours Allocated to Cost of Goods Sold - Labor | F39: =SUM(F32:F38) -> 0 | G39: =SUM(G32:G38) -> 1.2 | H39: =SUM(H32:H38) -> 1.2 | I39: =SUM(I32:I38) -> 84.8 | J39: =SUM(J32:J38) -> 168.4 | K39: =SUM(K32:K38) -> 250.8 | L39: =SUM(L32:L38) -> 499.2 | M39: =SUM(M32:M38) -> 906.4 | ... Q39: =SUM(Q32:Q38) -> 4078 | S39: =SUM(S32:S38) -> 2.4 | T39: =SUM(T32:T38) -> 504 | U39: =SUM(U32:U38) -> 2800.4 | V39: =SUM(V32:V38) -> 9388.4 | X39: =SUM(X32:X38) -> 12695.2
C40: % of Total Labor Hours | F40: =IFERROR(F39/Labor!F36,"nm") -> nm | G40: =IFERROR(G39/Labor!G36,"nm") -> 0.4 | H40: =IFERROR(H39/Labor!H36,"nm") -> 0.4 | I40: =IFERROR(I39/Labor!I36,"nm") -> 0.4 | J40: =IFERROR(J39/Labor!J36,"nm") -> 0.4 | K40: =IFERROR(K39/Labor!K36,"nm") -> 0.4 | L40: =IFERROR(L39/Labor!L36,"nm") -> 0.4 | M40: =IFERROR(M39/Labor!M36,"nm") -> 0.4 | ... Q40: =IFERROR(Q39/Labor!Q36,"nm") -> 0.4 | S40: =IFERROR(S39/Labor!S36,"nm") -> 0.4 | T40: =IFERROR(T39/Labor!T36,"nm") -> 0.4 | U40: =IFERROR(U39/Labor!U36,"nm") -> 0.4 | V40: =IFERROR(V39/Labor!V36,"nm") -> 0.4 | X40: =IFERROR(X39/Labor!X36,"nm") -> 0.4
C42: Allocation to Cost of Goods Sold - Labor
C43: Chief Strategy Officer | F43: =F32*INDEX(Labor!$D$7:$D$15,MATCH('Salaries, Wages, & Benefits'!$C43,Labor!$C$7:$C$15,0),1) -> 0 | G43: =G32*INDEX(Labor!$D$7:$D$15,MATCH('Salaries, Wages, & Benefits'!$C43,Labor!$C$7:$C$15,0),1) -> 14.423077 | H43: =H32*INDEX(Labor!$D$7:$D$15,MATCH('Salaries, Wages, & Benefits'!$C43,Labor!$C$7:$C$15,0),1) -> 14.423077 | I43: =I32*INDEX(Labor!$D$7:$D$15,MATCH('Salaries, Wages, & Benefits'!$C43,Labor!$C$7:$C$15,0),1) -> 1019.2308 | J43: =J32*INDEX(Labor!$D$7:$D$15,MATCH('Salaries, Wages, & Benefits'!$C43,Labor!$C$7:$C$15,0),1) -> 2024.0385 | K43: =K32*INDEX(Labor!$D$7:$D$15,MATCH('Salaries, Wages, & Benefits'!$C43,Labor!$C$7:$C$15,0),1) -> 3014.4231 | L43: =L32*INDEX(Labor!$D$7:$D$15,MATCH('Salaries, Wages, & Benefits'!$C43,Labor!$C$7:$C$15,0),1) -> 6000 | M43: =M32*INDEX(Labor!$D$7:$D$15,MATCH('Salaries, Wages, & Benefits'!$C43,Labor!$C$7:$C$15,0),1) -> 10894.231 | ... Q43: =Q32*INDEX(Labor!$D$7:$D$15,MATCH('Salaries, Wages, & Benefits'!$C43,Labor!$C$7:$C$15,0),1) -> 49014.423 | S43: =SUM(F43:H43) -> 28.846154 | T43: =SUM(I43:K43) -> 6057.6923 | U43: =SUM(L43:N43) -> 33658.654 | V43: =SUM(O43:Q43) -> 112841.35 | X43: =SUM(S43:V43) -> 152586.54
C44: Chief Technology Officer | F44: =F33*INDEX(Labor!$D$7:$D$15,MATCH('Salaries, Wages, & Benefits'!$C44,Labor!$C$7:$C$15,0),1) -> 0 | G44: =G33*INDEX(Labor!$D$7:$D$15,MATCH('Salaries, Wages, & Benefits'!$C44,Labor!$C$7:$C$15,0),1) -> 14.423077 | H44: =H33*INDEX(Labor!$D$7:$D$15,MATCH('Salaries, Wages, & Benefits'!$C44,Labor!$C$7:$C$15,0),1) -> 14.423077 | I44: =I33*INDEX(Labor!$D$7:$D$15,MATCH('Salaries, Wages, & Benefits'!$C44,Labor!$C$7:$C$15,0),1) -> 1019.2308 | J44: =J33*INDEX(Labor!$D$7:$D$15,MATCH('Salaries, Wages, & Benefits'!$C44,Labor!$C$7:$C$15,0),1) -> 2024.0385 | K44: =K33*INDEX(Labor!$D$7:$D$15,MATCH('Salaries, Wages, & Benefits'!$C44,Labor!$C$7:$C$15,0),1) -> 3014.4231 | L44: =L33*INDEX(Labor!$D$7:$D$15,MATCH('Salaries, Wages, & Benefits'!$C44,Labor!$C$7:$C$15,0),1) -> 6000 | M44: =M33*INDEX(Labor!$D$7:$D$15,MATCH('Salaries, Wages, & Benefits'!$C44,Labor!$C$7:$C$15,0),1) -> 10894.231 | ... Q44: =Q33*INDEX(Labor!$D$7:$D$15,MATCH('Salaries, Wages, & Benefits'!$C44,Labor!$C$7:$C$15,0),1) -> 49014.423 | S44: =SUM(F44:H44) -> 28.846154 | T44: =SUM(I44:K44) -> 6057.6923 | U44: =SUM(L44:N44) -> 33658.654 | V44: =SUM(O44:Q44) -> 112841.35 | X44: =SUM(S44:V44) -> 152586.54
C45: VP of AI Governance & Product Manager | F45: =F34*INDEX(Labor!$D$7:$D$15,MATCH('Salaries, Wages, & Benefits'!$C45,Labor!$C$7:$C$15,0),1) -> 0 | G45: =G34*INDEX(Labor!$D$7:$D$15,MATCH('Salaries, Wages, & Benefits'!$C45,Labor!$C$7:$C$15,0),1) -> 12.980769 | H45: =H34*INDEX(Labor!$D$7:$D$15,MATCH('Salaries, Wages, & Benefits'!$C45,Labor!$C$7:$C$15,0),1) -> 12.980769 | I45: =I34*INDEX(Labor!$D$7:$D$15,MATCH('Salaries, Wages, & Benefits'!$C45,Labor!$C$7:$C$15,0),1) -> 917.30769 | J45: =J34*INDEX(Labor!$D$7:$D$15,MATCH('Salaries, Wages, & Benefits'!$C45,Labor!$C$7:$C$15,0),1) -> 1821.6346 | K45: =K34*INDEX(Labor!$D$7:$D$15,MATCH('Salaries, Wages, & Benefits'!$C45,Labor!$C$7:$C$15,0),1) -> 2712.9808 | L45: =L34*INDEX(Labor!$D$7:$D$15,MATCH('Salaries, Wages, & Benefits'!$C45,Labor!$C$7:$C$15,0),1) -> 5400 | M45: =M34*INDEX(Labor!$D$7:$D$15,MATCH('Salaries, Wages, & Benefits'!$C45,Labor!$C$7:$C$15,0),1) -> 9804.8077 | ... Q45: =Q34*INDEX(Labor!$D$7:$D$15,MATCH('Salaries, Wages, & Benefits'!$C45,Labor!$C$7:$C$15,0),1) -> 44112.981 | S45: =SUM(F45:H45) -> 25.961538 | T45: =SUM(I45:K45) -> 5451.9231 | U45: =SUM(L45:N45) -> 30292.788 | V45: =SUM(O45:Q45) -> 101557.21 | X45: =SUM(S45:V45) -> 137327.88
C46: Director of AI Governance & Product Research | F46: =F35*INDEX(Labor!$D$7:$D$15,MATCH('Salaries, Wages, & Benefits'!$C46,Labor!$C$7:$C$15,0),1) -> 0 | G46: =G35*INDEX(Labor!$D$7:$D$15,MATCH('Salaries, Wages, & Benefits'!$C46,Labor!$C$7:$C$15,0),1) -> 23.798077 | H46: =H35*INDEX(Labor!$D$7:$D$15,MATCH('Salaries, Wages, & Benefits'!$C46,Labor!$C$7:$C$15,0),1) -> 23.798077 | I46: =I35*INDEX(Labor!$D$7:$D$15,MATCH('Salaries, Wages, & Benefits'!$C46,Labor!$C$7:$C$15,0),1) -> 1681.7308 | J46: =J35*INDEX(Labor!$D$7:$D$15,MATCH('Salaries, Wages, & Benefits'!$C46,Labor!$C$7:$C$15,0),1) -> 3339.6635 | K46: =K35*INDEX(Labor!$D$7:$D$15,MATCH('Salaries, Wages, & Benefits'!$C46,Labor!$C$7:$C$15,0),1) -> 4973.7981 | L46: =L35*INDEX(Labor!$D$7:$D$15,MATCH('Salaries, Wages, & Benefits'!$C46,Labor!$C$7:$C$15,0),1) -> 9900 | M46: =M35*INDEX(Labor!$D$7:$D$15,MATCH('Salaries, Wages, & Benefits'!$C46,Labor!$C$7:$C$15,0),1) -> 17975.481 | ... Q46: =Q35*INDEX(Labor!$D$7:$D$15,MATCH('Salaries, Wages, & Benefits'!$C46,Labor!$C$7:$C$15,0),1) -> 80873.798 | S46: =SUM(F46:H46) -> 47.596154 | T46: =SUM(I46:K46) -> 9995.1923 | U46: =SUM(L46:N46) -> 55536.779 | V46: =SUM(O46:Q46) -> 186188.22 | X46: =SUM(S46:V46) -> 251767.79
C47: Director of Sales | F47: =F36*INDEX(Labor!$D$7:$D$15,MATCH('Salaries, Wages, & Benefits'!$C47,Labor!$C$7:$C$15,0),1) -> 0 | G47: =G36*INDEX(Labor!$D$7:$D$15,MATCH('Salaries, Wages, & Benefits'!$C47,Labor!$C$7:$C$15,0),1) -> 6.4903846 | H47: =H36*INDEX(Labor!$D$7:$D$15,MATCH('Salaries, Wages, & Benefits'!$C47,Labor!$C$7:$C$15,0),1) -> 6.4903846 | I47: =I36*INDEX(Labor!$D$7:$D$15,MATCH('Salaries, Wages, & Benefits'!$C47,Labor!$C$7:$C$15,0),1) -> 458.65385 | J47: =J36*INDEX(Labor!$D$7:$D$15,MATCH('Salaries, Wages, & Benefits'!$C47,Labor!$C$7:$C$15,0),1) -> 910.81731 | K47: =K36*INDEX(Labor!$D$7:$D$15,MATCH('Salaries, Wages, & Benefits'!$C47,Labor!$C$7:$C$15,0),1) -> 1356.4904 | L47: =L36*INDEX(Labor!$D$7:$D$15,MATCH('Salaries, Wages, & Benefits'!$C47,Labor!$C$7:$C$15,0),1) -> 2700 | M47: =M36*INDEX(Labor!$D$7:$D$15,MATCH('Salaries, Wages, & Benefits'!$C47,Labor!$C$7:$C$15,0),1) -> 4902.4038 | ... Q47: =Q36*INDEX(Labor!$D$7:$D$15,MATCH('Salaries, Wages, & Benefits'!$C47,Labor!$C$7:$C$15,0),1) -> 22056.49 | S47: =SUM(F47:H47) -> 12.980769 | T47: =SUM(I47:K47) -> 2725.9615 | U47: =SUM(L47:N47) -> 15146.394 | V47: =SUM(O47:Q47) -> 50778.606 | X47: =SUM(S47:V47) -> 68663.942
C48: Director of Channel Sales | F48: =F37*INDEX(Labor!$D$7:$D$15,MATCH('Salaries, Wages, & Benefits'!$C48,Labor!$C$7:$C$15,0),1) -> 0 | G48: =G37*INDEX(Labor!$D$7:$D$15,MATCH('Salaries, Wages, & Benefits'!$C48,Labor!$C$7:$C$15,0),1) -> 6.4903846 | H48: =H37*INDEX(Labor!$D$7:$D$15,MATCH('Salaries, Wages, & Benefits'!$C48,Labor!$C$7:$C$15,0),1) -> 6.4903846 | I48: =I37*INDEX(Labor!$D$7:$D$15,MATCH('Salaries, Wages, & Benefits'!$C48,Labor!$C$7:$C$15,0),1) -> 458.65385 | J48: =J37*INDEX(Labor!$D$7:$D$15,MATCH('Salaries, Wages, & Benefits'!$C48,Labor!$C$7:$C$15,0),1) -> 910.81731 | K48: =K37*INDEX(Labor!$D$7:$D$15,MATCH('Salaries, Wages, & Benefits'!$C48,Labor!$C$7:$C$15,0),1) -> 1356.4904 | L48: =L37*INDEX(Labor!$D$7:$D$15,MATCH('Salaries, Wages, & Benefits'!$C48,Labor!$C$7:$C$15,0),1) -> 2700 | M48: =M37*INDEX(Labor!$D$7:$D$15,MATCH('Salaries, Wages, & Benefits'!$C48,Labor!$C$7:$C$15,0),1) -> 4902.4038 | ... Q48: =Q37*INDEX(Labor!$D$7:$D$15,MATCH('Salaries, Wages, & Benefits'!$C48,Labor!$C$7:$C$15,0),1) -> 22056.49 | S48: =SUM(F48:H48) -> 12.980769 | T48: =SUM(I48:K48) -> 2725.9615 | U48: =SUM(L48:N48) -> 15146.394 | V48: =SUM(O48:Q48) -> 50778.606 | X48: =SUM(S48:V48) -> 68663.942
C49: Customer Success Manager | F49: =F38*INDEX(Labor!$D$7:$D$15,MATCH('Salaries, Wages, & Benefits'!$C49,Labor!$C$7:$C$15,0),1) -> 0 | G49: =G38*INDEX(Labor!$D$7:$D$15,MATCH('Salaries, Wages, & Benefits'!$C49,Labor!$C$7:$C$15,0),1) -> 4.6875 | H49: =H38*INDEX(Labor!$D$7:$D$15,MATCH('Salaries, Wages, & Benefits'!$C49,Labor!$C$7:$C$15,0),1) -> 4.6875 | I49: =I38*INDEX(Labor!$D$7:$D$15,MATCH('Salaries, Wages, & Benefits'!$C49,Labor!$C$7:$C$15,0),1) -> 331.25 | J49: =J38*INDEX(Labor!$D$7:$D$15,MATCH('Salaries, Wages, & Benefits'!$C49,Labor!$C$7:$C$15,0),1) -> 657.8125 | K49: =K38*INDEX(Labor!$D$7:$D$15,MATCH('Salaries, Wages, & Benefits'!$C49,Labor!$C$7:$C$15,0),1) -> 979.6875 | L49: =L38*INDEX(Labor!$D$7:$D$15,MATCH('Salaries, Wages, & Benefits'!$C49,Labor!$C$7:$C$15,0),1) -> 1950 | M49: =M38*INDEX(Labor!$D$7:$D$15,MATCH('Salaries, Wages, & Benefits'!$C49,Labor!$C$7:$C$15,0),1) -> 3540.625 | ... Q49: =Q38*INDEX(Labor!$D$7:$D$15,MATCH('Salaries, Wages, & Benefits'!$C49,Labor!$C$7:$C$15,0),1) -> 15929.688 | S49: =SUM(F49:H49) -> 9.375 | T49: =SUM(I49:K49) -> 1968.75 | U49: =SUM(L49:N49) -> 10939.063 | V49: =SUM(O49:Q49) -> 36673.438 | X49: =SUM(S49:V49) -> 49590.625
C50: Total Allocation to Cost of Goods Sold - Labor | F50: =SUM(F43:F49) -> 0 | G50: =SUM(G43:G49) -> 83.293269 | H50: =SUM(H43:H49) -> 83.293269 | I50: =SUM(I43:I49) -> 5886.0577 | J50: =SUM(J43:J49) -> 11688.822 | K50: =SUM(K43:K49) -> 17408.293 | L50: =SUM(L43:L49) -> 34650 | M50: =SUM(M43:M49) -> 62914.183 | ... Q50: =SUM(Q43:Q49) -> 283058.29 | S50: =SUM(S43:S49) -> 166.58654 | T50: =SUM(T43:T49) -> 34983.173 | U50: =SUM(U43:U49) -> 194378.73 | V50: =SUM(V43:V49) -> 651658.77 | X50: =SUM(X43:X49) -> 881187.26
C52: Total Net Salaries, Wages, & Benefits | F52: =F29-F50 -> 106535.84 | G52: =G29-G50 -> 104570.28 | H52: =H29-H50 -> 101192.7 | I52: =I29-I50 -> 98889.929 | J52: =J29-J50 -> 93087.17 | K52: =K29-K50 -> 86743.45 | L52: =L29-L50 -> 69457.96 | M52: =M29-M50 -> 41193.778 | ... Q52: =Q29-Q50 -> -178950.33 | S52: =S29-S50 -> 312298.83 | T52: =T29-T50 -> 278720.55 | U52: =U29-U50 -> 117945.16 | V52: =V29-V50 -> -339334.89 | X52: =X29-X50 -> 369629.64

Sheet Contract Labor
C2: 2026 Forecast
C3: Contract Labor
C5: Last Name | D5: First Name | E5: Title | F5: Pay Rate | G5: Hrs / Month | H5: End Date | I5: 46023 | J5: =EOMONTH(I5,0)+1 -> 46054 | K5: =EOMONTH(J5,0)+1 -> 46082 | L5: =EOMONTH(K5,0)+1 -> 46113 | M5: =EOMONTH(L5,0)+1 -> 46143 | N5: =EOMONTH(M5,0)+1 -> 46174 | O5: =EOMONTH(N5,0)+1 -> 46204 | P5: =EOMONTH(O5,0)+1 -> 46235 | Q5: =EOMONTH(P5,0)+1 -> 46266 | ... T5: =EOMONTH(S5,0)+1 -> 46357 | V5: Q1 '26 | W5: Q2 '26 | X5: Q3 '26 | Y5: Q4 '26 | AA5: 2026E
E7: Azure Architect | F7: 100 | G7: 160 | H7: 46382 | I7: =IF(I$5>$H7,0,$F7*$G7) -> 16000 | J7: =IF(J$5>$H7,0,$F7*$G7) -> 16000 | K7: =IF(K$5>$H7,0,$F7*$G7) -> 16000 | L7: =IF(L$5>$H7,0,$F7*$G7) -> 16000 | M7: =IF(M$5>$H7,0,$F7*$G7) -> 16000 | N7: =IF(N$5>$H7,0,$F7*$G7) -> 16000 | O7: =IF(O$5>$H7,0,$F7*$G7) -> 16000 | P7: =IF(P$5>$H7,0,$F7*$G7) -> 16000 | ... T7: =IF(T$5>$H7,0,$F7*$G7) -> 16000 | V7: =SUM(I7:K7) -> 48000 | W7: =SUM(L7:N7) -> 48000 | X7: =SUM(O7:Q7) -> 48000 | Y7: =SUM(R7:T7) -> 48000 | AA7: =SUM(V7:Y7) -> 192000
E8: Quality Assurance | F8: 17 | G8: 160 | H8: 46382 | I8: =IF(I$5>$H8,0,$F8*$G8) -> 2720 | J8: =IF(J$5>$H8,0,$F8*$G8) -> 2720 | K8: =IF(K$5>$H8,0,$F8*$G8) -> 2720 | L8: =IF(L$5>$H8,0,$F8*$G8) -> 2720 | M8: =IF(M$5>$H8,0,$F8*$G8) -> 2720 | N8: =IF(N$5>$H8,0,$F8*$G8) -> 2720 | O8: =IF(O$5>$H8,0,$F8*$G8) -> 2720 | P8: =IF(P$5>$H8,0,$F8*$G8) -> 2720 | ... T8: =IF(T$5>$H8,0,$F8*$G8) -> 2720 | V8: =SUM(I8:K8) -> 8160 | W8: =SUM(L8:N8) -> 8160 | X8: =SUM(O8:Q8) -> 8160 | Y8: =SUM(R8:T8) -> 8160 | AA8: =SUM(V8:Y8) -> 32640
E9: Front-End Developer | F9: 50 | G9: 160 | H9: 46382 | I9: =IF(I$5>$H9,0,$F9*$G9) -> 8000 | J9: =IF(J$5>$H9,0,$F9*$G9) -> 8000 | K9: =IF(K$5>$H9,0,$F9*$G9) -> 8000 | L9: =IF(L$5>$H9,0,$F9*$G9) -> 8000 | M9: =IF(M$5>$H9,0,$F9*$G9) -> 8000 | N9: =IF(N$5>$H9,0,$F9*$G9) -> 8000 | O9: =IF(O$5>$H9,0,$F9*$G9) -> 8000 | P9: =IF(P$5>$H9,0,$F9*$G9) -> 8000 | ... T9: =IF(T$5>$H9,0,$F9*$G9) -> 8000 | V9: =SUM(I9:K9) -> 24000 | W9: =SUM(L9:N9) -> 24000 | X9: =SUM(O9:Q9) -> 24000 | Y9: =SUM(R9:T9) -> 24000 | AA9: =SUM(V9:Y9) -> 96000
E10: Azure CSO & Admin | F10: 150 | G10: 10 | H10: 46382 | I10: =IF(I$5>$H10,0,$F10*$G10) -> 1500 | J10: =IF(J$5>$H10,0,$F10*$G10) -> 1500 | K10: =IF(K$5>$H10,0,$F10*$G10) -> 1500 | L10: =IF(L$5>$H10,0,$F10*$G10) -> 1500 | M10: =IF(M$5>$H10,0,$F10*$G10) -> 1500 | N10: =IF(N$5>$H10,0,$F10*$G10) -> 1500 | O10: =IF(O$5>$H10,0,$F10*$G10) -> 1500 | P10: =IF(P$5>$H10,0,$F10*$G10) -> 1500 | ... T10: =IF(T$5>$H10,0,$F10*$G10) -> 1500 | V10: =SUM(I10:K10) -> 4500 | W10: =SUM(L10:N10) -> 4500 | X10: =SUM(O10:Q10) -> 4500 | Y10: =SUM(R10:T10) -> 4500 | AA10: =SUM(V10:Y10) -> 18000
E11: Front-End Developer | F11: 43 | G11: 160 | H11: 46382 | I11: =IF(I$5>$H11,0,$F11*$G11) -> 6880 | J11: =IF(J$5>$H11,0,$F11*$G11) -> 6880 | K11: =IF(K$5>$H11,0,$F11*$G11) -> 6880 | L11: =IF(L$5>$H11,0,$F11*$G11) -> 6880 | M11: =IF(M$5>$H11,0,$F11*$G11) -> 6880 | N11: =IF(N$5>$H11,0,$F11*$G11) -> 6880 | O11: =IF(O$5>$H11,0,$F11*$G11) -> 6880 | P11: =IF(P$5>$H11,0,$F11*$G11) -> 6880 | ... T11: =IF(T$5>$H11,0,$F11*$G11) -> 6880 | V11: =SUM(I11:K11) -> 20640 | W11: =SUM(L11:N11) -> 20640 | X11: =SUM(O11:Q11) -> 20640 | Y11: =SUM(R11:T11) -> 20640 | AA11: =SUM(V11:Y11) -> 82560
E12: Full Stack Developer | F12: 120 | G12: 160 | H12: 46382 | I12: =IF(I$5>$H12,0,$F12*$G12) -> 19200 | J12: =IF(J$5>$H12,0,$F12*$G12) -> 19200 | K12: =IF(K$5>$H12,0,$F12*$G12) -> 19200 | L12: =IF(L$5>$H12,0,$F12*$G12) -> 19200 | M12: =IF(M$5>$H12,0,$F12*$G12) -> 19200 | N12: =IF(N$5>$H12,0,$F12*$G12) -> 19200 | O12: =IF(O$5>$H12,0,$F12*$G12) -> 19200 | P12: =IF(P$5>$H12,0,$F12*$G12) -> 19200 | ... T12: =IF(T$5>$H12,0,$F12*$G12) -> 19200 | V12: =SUM(I12:K12) -> 57600 | W12: =SUM(L12:N12) -> 57600 | X12: =SUM(O12:Q12) -> 57600 | Y12: =SUM(R12:T12) -> 57600 | AA12: =SUM(V12:Y12) -> 230400
E13: Business Analyst | F13: 15 | G13: 20 | H13: 46382 | I13: =IF(I$5>$H13,0,$F13*$G13) -> 300 | J13: =IF(J$5>$H13,0,$F13*$G13) -> 300 | K13: =IF(K$5>$H13,0,$F13*$G13) -> 300 | L13: =IF(L$5>$H13,0,$F13*$G13) -> 300 | M13: =IF(M$5>$H13,0,$F13*$G13) -> 300 | N13: =IF(N$5>$H13,0,$F13*$G13) -> 300 | O13: =IF(O$5>$H13,0,$F13*$G13) -> 300 | P13: =IF(P$5>$H13,0,$F13*$G13) -> 300 | ... T13: =IF(T$5>$H13,0,$F13*$G13) -> 300 | V13: =SUM(I13:K13) -> 900 | W13: =SUM(L13:N13) -> 900 | X13: =SUM(O13:Q13) -> 900 | Y13: =SUM(R13:T13) -> 900 | AA13: =SUM(V13:Y13) -> 3600
E14: Back-End Developer | F14: 48 | G14: 140 | H14: 46382 | I14: =IF(I$5>$H14,0,$F14*$G14) -> 6720 | J14: =IF(J$5>$H14,0,$F14*$G14) -> 6720 | K14: =IF(K$5>$H14,0,$F14*$G14) -> 6720 | L14: =IF(L$5>$H14,0,$F14*$G14) -> 6720 | M14: =IF(M$5>$H14,0,$F14*$G14) -> 6720 | N14: =IF(N$5>$H14,0,$F14*$G14) -> 6720 | O14: =IF(O$5>$H14,0,$F14*$G14) -> 6720 | P14: =IF(P$5>$H14,0,$F14*$G14) -> 6720 | ... T14: =IF(T$5>$H14,0,$F14*$G14) -> 6720 | V14: =SUM(I14:K14) -> 20160 | W14: =SUM(L14:N14) -> 20160 | X14: =SUM(O14:Q14) -> 20160 | Y14: =SUM(R14:T14) -> 20160 | AA14: =SUM(V14:Y14) -> 80640
E15: Back-End Developer | F15: 48 | G15: 140 | H15: 46382 | I15: =IF(I$5>$H15,0,$F15*$G15) -> 6720 | J15: =IF(J$5>$H15,0,$F15*$G15) -> 6720 | K15: =IF(K$5>$H15,0,$F15*$G15) -> 6720 | L15: =IF(L$5>$H15,0,$F15*$G15) -> 6720 | M15: =IF(M$5>$H15,0,$F15*$G15) -> 6720 | N15: =IF(N$5>$H15,0,$F15*$G15) -> 6720 | O15: =IF(O$5>$H15,0,$F15*$G15) -> 6720 | P15: =IF(P$5>$H15,0,$F15*$G15) -> 6720 | ... T15: =IF(T$5>$H15,0,$F15*$G15) -> 6720 | V15: =SUM(I15:K15) -> 20160 | W15: =SUM(L15:N15) -> 20160 | X15: =SUM(O15:Q15) -> 20160 | Y15: =SUM(R15:T15) -> 20160 | AA15: =SUM(V15:Y15) -> 80640
E16: UI / UX Designer | F16: 50 | G16: 120 | H16: 46382 | I16: =IF(I$5>$H16,0,$F16*$G16) -> 6000 | J16: =IF(J$5>$H16,0,$F16*$G16) -> 6000 | K16: =IF(K$5>$H16,0,$F16*$G16) -> 6000 | L16: =IF(L$5>$H16,0,$F16*$G16) -> 6000 | M16: =IF(M$5>$H16,0,$F16*$G16) -> 6000 | N16: =IF(N$5>$H16,0,$F16*$G16) -> 6000 | O16: =IF(O$5>$H16,0,$F16*$G16) -> 6000 | P16: =IF(P$5>$H16,0,$F16*$G16) -> 6000 | ... T16: =IF(T$5>$H16,0,$F16*$G16) -> 6000 | V16: =SUM(I16:K16) -> 18000 | W16: =SUM(L16:N16) -> 18000 | X16: =SUM(O16:Q16) -> 18000 | Y16: =SUM(R16:T16) -> 18000 | AA16: =SUM(V16:Y16) -> 72000
E17: Front-End Developer | F17: 40 | G17: 120 | H17: 46382 | I17: =IF(I$5>$H17,0,$F17*$G17) -> 4800 | J17: =IF(J$5>$H17,0,$F17*$G17) -> 4800 | K17: =IF(K$5>$H17,0,$F17*$G17) -> 4800 | L17: =IF(L$5>$H17,0,$F17*$G17) -> 4800 | M17: =IF(M$5>$H17,0,$F17*$G17) -> 4800 | N17: =IF(N$5>$H17,0,$F17*$G17) -> 4800 | O17: =IF(O$5>$H17,0,$F17*$G17) -> 4800 | P17: =IF(P$5>$H17,0,$F17*$G17) -> 4800 | ... T17: =IF(T$5>$H17,0,$F17*$G17) -> 4800 | V17: =SUM(I17:K17) -> 14400 | W17: =SUM(L17:N17) -> 14400 | X17: =SUM(O17:Q17) -> 14400 | Y17: =SUM(R17:T17) -> 14400 | AA17: =SUM(V17:Y17) -> 57600
E18: UI / UX Designer | F18: 40 | G18: 160 | H18: 46382 | I18: =IF(I$5>$H18,0,$F18*$G18) -> 6400 | J18: =IF(J$5>$H18,0,$F18*$G18) -> 6400 | K18: =IF(K$5>$H18,0,$F18*$G18) -> 6400 | L18: =IF(L$5>$H18,0,$F18*$G18) -> 6400 | M18: =IF(M$5>$H18,0,$F18*$G18) -> 6400 | N18: =IF(N$5>$H18,0,$F18*$G18) -> 6400 | O18: =IF(O$5>$H18,0,$F18*$G18) -> 6400 | P18: =IF(P$5>$H18,0,$F18*$G18) -> 6400 | ... T18: =IF(T$5>$H18,0,$F18*$G18) -> 6400 | V18: =SUM(I18:K18) -> 19200 | W18: =SUM(L18:N18) -> 19200 | X18: =SUM(O18:Q18) -> 19200 | Y18: =SUM(R18:T18) -> 19200 | AA18: =SUM(V18:Y18) -> 76800
E19: Azure Architect & Full Stack Programmer | F19: 120 | G19: 160 | H19: 46382 | I19: =IF(I$5>$H19,0,$F19*$G19) -> 19200 | J19: =IF(J$5>$H19,0,$F19*$G19) -> 19200 | K19: =IF(K$5>$H19,0,$F19*$G19) -> 19200 | L19: =IF(L$5>$H19,0,$F19*$G19) -> 19200 | M19: =IF(M$5>$H19,0,$F19*$G19) -> 19200 | N19: =IF(N$5>$H19,0,$F19*$G19) -> 19200 | O19: =IF(O$5>$H19,0,$F19*$G19) -> 19200 | P19: =IF(P$5>$H19,0,$F19*$G19) -> 19200 | ... T19: =IF(T$5>$H19,0,$F19*$G19) -> 19200 | V19: =SUM(I19:K19) -> 57600 | W19: =SUM(L19:N19) -> 57600 | X19: =SUM(O19:Q19) -> 57600 | Y19: =SUM(R19:T19) -> 57600 | AA19: =SUM(V19:Y19) -> 230400
C20: Total Contract Labor | I20: =SUM(I7:I19) -> 104440 | J20: =SUM(J7:J19) -> 104440 | K20: =SUM(K7:K19) -> 104440 | L20: =SUM(L7:L19) -> 104440 | M20: =SUM(M7:M19) -> 104440 | N20: =SUM(N7:N19) -> 104440 | O20: =SUM(O7:O19) -> 104440 | P20: =SUM(P7:P19) -> 104440 | ... T20: =SUM(T7:T19) -> 104440 | V20: =SUM(V7:V19) -> 313320 | W20: =SUM(W7:W19) -> 313320 | X20: =SUM(X7:X19) -> 313320 | Y20: =SUM(Y7:Y19) -> 313320 | AA20: =SUM(AA7:AA19) -> 1253280
H22: Target: | K22: 40000 | L22: 40000 | M22: 40000 | N22: 40000 | O22: 40000 | P22: 40000 | Q22: 40000 | R22: 40000 | S22: 40000 | T22: 40000
H23: Target Reductions: | K23: =K20-K22 -> 64440 | L23: =L20-L22 -> 64440 | M23: =M20-M22 -> 64440 | N23: =N20-N22 -> 64440 | O23: =O20-O22 -> 64440 | P23: =P20-P22 -> 64440 | Q23: =Q20-Q22 -> 64440 | R23: =R20-R22 -> 64440 | ... T23: =T20-T22 -> 64440
C25: Adjusted Total Contract Labor | I25: =I20 -> 104440 | J25: =J20 -> 104440 | K25: =K20 -> 104440 | L25: =L20 -> 104440 | M25: =M20 -> 104440 | N25: =N20 -> 104440 | O25: =O20 -> 104440 | P25: =P20 -> 104440 | ... T25: =T20 -> 104440 | V25: =SUM(I25:K25) -> 313320 | W25: =SUM(L25:N25) -> 313320 | X25: =SUM(O25:Q25) -> 313320 | Y25: =SUM(R25:T25) -> 313320 | AA25: =SUM(V25:Y25) -> 1253280

Sheet Professional Fees
C2: 2026 Forecast
C3: Professional Fees
C5: Vendor Name | D5: Description | E5: 46023 | F5: =EOMONTH(E5,0)+1 -> 46054 | G5: =EOMONTH(F5,0)+1 -> 46082 | H5: =EOMONTH(G5,0)+1 -> 46113 | I5: =EOMONTH(H5,0)+1 -> 46143 | J5: =EOMONTH(I5,0)+1 -> 46174 | K5: =EOMONTH(J5,0)+1 -> 46204 | L5: =EOMONTH(K5,0)+1 -> 46235 | M5: =EOMONTH(L5,0)+1 -> 46266 | ... P5: =EOMONTH(O5,0)+1 -> 46357 | R5: Q1 '26 | S5: Q2 '26 | T5: Q3 '26 | U5: Q4 '26 | W5: 2026E
C7: Marcum | D7: Tax Preparation | E7: 0 | F7: 5000 | G7: 5000 | H7: 5000 | I7: 0 | J7: 0 | K7: 0 | L7: 0 | M7: 0 | N7: 0 | O7: 0 | P7: 0 | R7: =SUM(E7:G7) -> 10000 | S7: =SUM(H7:J7) -> 5000 | T7: =SUM(K7:M7) -> 0 | U7: =SUM(N7:P7) -> 0 | W7: =SUM(R7:U7) -> 15000
C8: ProjectHosts | D8: FedRAMP | E8: 2000 | F8: 2000 | G8: 2000 | H8: 2000 | I8: 2000 | J8: 2000 | K8: 2000 | L8: 2000 | M8: 2000 | N8: 2000 | O8: 2000 | P8: 2000 | R8: =SUM(E8:G8) -> 6000 | S8: =SUM(H8:J8) -> 6000 | T8: =SUM(K8:M8) -> 6000 | U8: =SUM(N8:P8) -> 6000 | W8: =SUM(R8:U8) -> 24000
C9: Legal Fee | D9: General Counsel | E9: 2500 | F9: 2500 | G9: 2500 | H9: 2500 | I9: 2500 | J9: 5000 | K9: 5000 | L9: 5000 | M9: 5000 | N9: 5000 | O9: 5000 | P9: 5000 | R9: =SUM(E9:G9) -> 7500 | S9: =SUM(H9:J9) -> 10000 | T9: =SUM(K9:M9) -> 15000 | U9: =SUM(N9:P9) -> 15000 | W9: =SUM(R9:U9) -> 47500
C10: Total Professional Fees | E10: =SUM(E7:E9) -> 4500 | F10: =SUM(F7:F9) -> 9500 | G10: =SUM(G7:G9) -> 9500 | H10: =SUM(H7:H9) -> 9500 | I10: =SUM(I7:I9) -> 4500 | J10: =SUM(J7:J9) -> 7000 | K10: =SUM(K7:K9) -> 7000 | L10: =SUM(L7:L9) -> 7000 | ... P10: =SUM(P7:P9) -> 7000 | R10: =SUM(R7:R9) -> 23500 | S10: =SUM(S7:S9) -> 21000 | T10: =SUM(T7:T9) -> 21000 | U10: =SUM(U7:U9) -> 21000 | W10: =SUM(W7:W9) -> 86500
C12: FedRAMP Path | D12: =Other!D28 -> High
C13: Test Environment Setup - Moderate | D13: 10000
C14: Production Environment Setup - Moderate | D14: 30000
C15: Test Environment Setup - High | D15: 10000
C16: Production Environment Setup - High | D16: 40000
C17: Audit Cost 1 - Moderate | D17: 125000
C18: Audit Cost 1 - High | D18: 175000
C19: Audit Cost 2 - Moderate | D19: 25000
C20: Audit Cost 2 - High | D20: 25000

Sheet Office Expenses
C2: 2026 Forecast
C3: Office Expenses
C5: Vendor Name | D5: Description | E5: 46023 | F5: =EOMONTH(E5,0)+1 -> 46054 | G5: =EOMONTH(F5,0)+1 -> 46082 | H5: =EOMONTH(G5,0)+1 -> 46113 | I5: =EOMONTH(H5,0)+1 -> 46143 | J5: =EOMONTH(I5,0)+1 -> 46174 | K5: =EOMONTH(J5,0)+1 -> 46204 | L5: =EOMONTH(K5,0)+1 -> 46235 | M5: =EOMONTH(L5,0)+1 -> 46266 | ... P5: =EOMONTH(O5,0)+1 -> 46357 | R5: Q1 '26 | S5: Q2 '26 | T5: Q3 '26 | U5: Q4 '26 | W5: 2026E
C7: DocuSign | D7: Computer - Software Licenses | E7: 0 | F7: 1773.11 | G7: 0 | H7: 0 | I7: 0 | J7: 0 | K7: 0 | L7: 0 | M7: 0 | N7: 0 | O7: 0 | P7: 0 | R7: =SUM(E7:G7) -> 1773.11 | S7: =SUM(H7:J7) -> 0 | T7: =SUM(K7:M7) -> 0 | U7: =SUM(N7:P7) -> 0 | W7: =SUM(R7:U7) -> 1773.11
C8: Lucid Software | D8: Computer - Software Licenses | E8: 876 | F8: 0 | G8: 0 | H8: 0 | I8: 0 | J8: 0 | K8: 0 | L8: 0 | M8: 0 | N8: 0 | O8: 0 | P8: 0 | R8: =SUM(E8:G8) -> 876 | S8: =SUM(H8:J8) -> 0 | T8: =SUM(K8:M8) -> 0 | U8: =SUM(N8:P8) -> 0 | W8: =SUM(R8:U8) -> 876
C9: NetSuite | D9: Computer - Software Licenses | E9: 200 | F9: 200 | G9: 200 | H9: 200 | I9: 200 | J9: 200 | K9: 200 | L9: 200 | M9: 200 | N9: 200 | O9: 200 | P9: 200 | R9: =SUM(E9:G9) -> 600 | S9: =SUM(H9:J9) -> 600 | T9: =SUM(K9:M9) -> 600 | U9: =SUM(N9:P9) -> 600 | W9: =SUM(R9:U9) -> 2400
C10: Microsoft | D10: Computer - Software Licenses | E10: 500 | F10: 500 | G10: 500 | H10: 500 | I10: 500 | J10: 500 | K10: 500 | L10: 500 | M10: 500 | N10: 500 | O10: 500 | P10: 500 | R10: =SUM(E10:G10) -> 1500 | S10: =SUM(H10:J10) -> 1500 | T10: =SUM(K10:M10) -> 1500 | U10: =SUM(N10:P10) -> 1500 | W10: =SUM(R10:U10) -> 6000
C11: Atlassian | D11: Computer - Software Licenses | E11: 650 | F11: 650 | G11: 650 | H11: 650 | I11: 650 | J11: 650 | K11: 650 | L11: 650 | M11: 650 | N11: 650 | O11: 650 | P11: 650 | R11: =SUM(E11:G11) -> 1950 | S11: =SUM(H11:J11) -> 1950 | T11: =SUM(K11:M11) -> 1950 | U11: =SUM(N11:P11) -> 1950 | W11: =SUM(R11:U11) -> 7800
C12: Hubspot | D12: Computer - Software Licenses | E12: 1200 | F12: 1200 | G12: 1200 | H12: 1200 | I12: 1200 | J12: 1200 | K12: 1200 | L12: 1200 | M12: 1200 | N12: 1200 | O12: 1200 | P12: 1200 | R12: =SUM(E12:G12) -> 3600 | S12: =SUM(H12:J12) -> 3600 | T12: =SUM(K12:M12) -> 3600 | U12: =SUM(N12:P12) -> 3600 | W12: =SUM(R12:U12) -> 14400
C13: OpenAI | D13: Computer - Software Licenses | E13: 200 | F13: 200 | G13: 200 | H13: 200 | I13: 200 | J13: 200 | K13: 200 | L13: 200 | M13: 200 | N13: 200 | O13: 200 | P13: 200 | R13: =SUM(E13:G13) -> 600 | S13: =SUM(H13:J13) -> 600 | T13: =SUM(K13:M13) -> 600 | U13: =SUM(N13:P13) -> 600 | W13: =SUM(R13:U13) -> 2400
C14: Zoho Expense | D14: Computer - Software Licenses | E14: 0 | F14: 0 | G14: 0 | H14: 300 | I14: 0 | J14: 0 | K14: 0 | L14: 0 | M14: 0 | N14: 0 | O14: 0 | P14: 0 | R14: =SUM(E14:G14) -> 0 | S14: =SUM(H14:J14) -> 300 | T14: =SUM(K14:M14) -> 0 | U14: =SUM(N14:P14) -> 0 | W14: =SUM(R14:U14) -> 300
C15: Monday | D15: Computer - Software Licenses | E15: 0 | F15: 0 | G15: 0 | H15: 2160 | I15: 0 | J15: 0 | K15: 0 | L15: 0 | M15: 0 | N15: 0 | O15: 0 | P15: 0 | R15: =SUM(E15:G15) -> 0 | S15: =SUM(H15:J15) -> 2160 | T15: =SUM(K15:M15) -> 0 | U15: =SUM(N15:P15) -> 0 | W15: =SUM(R15:U15) -> 2160
C16: Carta | D16: Computer - Software Licenses | E16: 0 | F16: 0 | G16: 0 | H16: 0 | I16: 3900 | J16: 0 | K16: 0 | L16: 0 | M16: 0 | N16: 0 | O16: 0 | P16: 0 | R16: =SUM(E16:G16) -> 0 | S16: =SUM(H16:J16) -> 3900 | T16: =SUM(K16:M16) -> 0 | U16: =SUM(N16:P16) -> 0 | W16: =SUM(R16:U16) -> 3900
C17: Figma | D17: Computer - Software Licenses | E17: 200 | F17: 200 | G17: 200 | H17: 200 | I17: 200 | J17: 200 | K17: 200 | L17: 200 | M17: 200 | N17: 200 | O17: 200 | P17: 200 | R17: =SUM(E17:G17) -> 600 | S17: =SUM(H17:J17) -> 600 | T17: =SUM(K17:M17) -> 600 | U17: =SUM(N17:P17) -> 600 | W17: =SUM(R17:U17) -> 2400
C18: 7pace | D18: Computer - Software Licenses | E18: 0 | F18: 0 | G18: 0 | H18: 0 | I18: 0 | J18: 840 | K18: 0 | L18: 0 | M18: 0 | N18: 0 | O18: 0 | P18: 0 | R18: =SUM(E18:G18) -> 0 | S18: =SUM(H18:J18) -> 840 | T18: =SUM(K18:M18) -> 0 | U18: =SUM(N18:P18) -> 0 | W18: =SUM(R18:U18) -> 840
... C30: Office Depot | D30: Printing & Photocopying | E30: 25 | F30: 25 | G30: 25 | H30: 25 | I30: 25 | J30: 25 | K30: 25 | L30: 25 | M30: 25 | N30: 25 | O30: 25 | P30: 25 | R30: =SUM(E30:G30) -> 75 | S30: =SUM(H30:J30) -> 75 | T30: =SUM(K30:M30) -> 75 | U30: =SUM(N30:P30) -> 75 | W30: =SUM(R30:U30) -> 300
C31: Total Office Expenses | E31: =SUM(E7:E30) -> 4401 | F31: =SUM(F7:F30) -> 5149.11 | G31: =SUM(G7:G30) -> 3376 | H31: =SUM(H7:H30) -> 5836 | I31: =SUM(I7:I30) -> 7418 | J31: =SUM(J7:J30) -> 4216 | K31: =SUM(K7:K30) -> 3376 | L31: =SUM(L7:L30) -> 3376 | ... P31: =SUM(P7:P30) -> 3376 | R31: =SUM(R7:R30) -> 12926.11 | S31: =SUM(S7:S30) -> 17470 | T31: =SUM(T7:T30) -> 13128 | U31: =SUM(U7:U30) -> 10128 | W31: =SUM(W7:W30) -> 53652.11

Sheet Advertising & Marketing
C2: 2026 Forecast
C3: Advertising & Marketing
C5: Vendor Name | D5: Description | E5: 46023 | F5: =EOMONTH(E5,0)+1 -> 46054 | G5: =EOMONTH(F5,0)+1 -> 46082 | H5: =EOMONTH(G5,0)+1 -> 46113 | I5: =EOMONTH(H5,0)+1 -> 46143 | J5: =EOMONTH(I5,0)+1 -> 46174 | K5: =EOMONTH(J5,0)+1 -> 46204 | L5: =EOMONTH(K5,0)+1 -> 46235 | M5: =EOMONTH(L5,0)+1 -> 46266 | ... P5: =EOMONTH(O5,0)+1 -> 46357 | R5: Q1 '26 | S5: Q2 '26 | T5: Q3 '26 | U5: Q4 '26 | W5: 2026E
C7: Conferences | D7: Conferences | E7: 0 | F7: 3000 | G7: 3000 | H7: 3000 | I7: 3000 | J7: 3000 | K7: 3000 | L7: 3000 | M7: 3000 | N7: 3000 | O7: 3000 | P7: 3000 | R7: =SUM(E7:G7) -> 6000 | S7: =SUM(H7:J7) -> 9000 | T7: =SUM(K7:M7) -> 9000 | U7: =SUM(N7:P7) -> 9000 | W7: =SUM(R7:U7) -> 33000
C8: ShutterStock | D8: Marketing Collateral | E8: 29 | F8: 29 | G8: 29 | H8: 29 | I8: 29 | J8: 29 | K8: 29 | L8: 29 | M8: 29 | N8: 29 | O8: 29 | P8: 29 | R8: =SUM(E8:G8) -> 87 | S8: =SUM(H8:J8) -> 87 | T8: =SUM(K8:M8) -> 87 | U8: =SUM(N8:P8) -> 87 | W8: =SUM(R8:U8) -> 348
C9: VistaPrint | D9: Marketing Collateral | E9: 50 | F9: 50 | G9: 50 | H9: 50 | I9: 50 | J9: 50 | K9: 50 | L9: 50 | M9: 50 | N9: 50 | O9: 50 | P9: 50 | R9: =SUM(E9:G9) -> 150 | S9: =SUM(H9:J9) -> 150 | T9: =SUM(K9:M9) -> 150 | U9: =SUM(N9:P9) -> 150 | W9: =SUM(R9:U9) -> 600
C10: Design | D10: Marketing Collateral | E10: 200 | F10: 200 | G10: 200 | H10: 200 | I10: 200 | J10: 200 | K10: 200 | L10: 200 | M10: 200 | N10: 200 | O10: 200 | P10: 200 | R10: =SUM(E10:G10) -> 600 | S10: =SUM(H10:J10) -> 600 | T10: =SUM(K10:M10) -> 600 | U10: =SUM(N10:P10) -> 600 | W10: =SUM(R10:U10) -> 2400
C11: Wedsite | D11: Website Development & Maintenance | E11: 1000 | F11: 1000 | G11: 1000 | H11: 1000 | I11: 1000 | J11: 1000 | K11: 1000 | L11: 1000 | M11: 1000 | N11: 1000 | O11: 1000 | P11: 1000 | R11: =SUM(E11:G11) -> 3000 | S11: =SUM(H11:J11) -> 3000 | T11: =SUM(K11:M11) -> 3000 | U11: =SUM(N11:P11) -> 3000 | W11: =SUM(R11:U11) -> 12000
C12: Total Advertising & Marketing | E12: =SUM(E7:E11) -> 1279 | F12: =SUM(F7:F11) -> 4279 | G12: =SUM(G7:G11) -> 4279 | H12: =SUM(H7:H11) -> 4279 | I12: =SUM(I7:I11) -> 4279 | J12: =SUM(J7:J11) -> 4279 | K12: =SUM(K7:K11) -> 4279 | L12: =SUM(L7:L11) -> 4279 | ... P12: =SUM(P7:P11) -> 4279 | R12: =SUM(R7:R11) -> 9837 | S12: =SUM(S7:S11) -> 12837 | T12: =SUM(T7:T11) -> 12837 | U12: =SUM(U7:U11) -> 12837 | W12: =SUM(W7:W11) -> 48348

Sheet Employee Travel
C2: 2026 Forecast
C3: Employee Travel
C5: Vendor Name | D5: 46023 | E5: =EOMONTH(D5,0)+1 -> 46054 | F5: =EOMONTH(E5,0)+1 -> 46082 | G5: =EOMONTH(F5,0)+1 -> 46113 | H5: =EOMONTH(G5,0)+1 -> 46143 | I5: =EOMONTH(H5,0)+1 -> 46174 | J5: =EOMONTH(I5,0)+1 -> 46204 | K5: =EOMONTH(J5,0)+1 -> 46235 | L5: =EOMONTH(K5,0)+1 -> 46266 | ... O5: =EOMONTH(N5,0)+1 -> 46357 | Q5: Q1 '26 | R5: Q2 '26 | S5: Q3 '26 | T5: Q4 '26 | V5: 2026E
C7: Airfare | D7: 5000 | E7: 5000 | F7: 5000 | G7: 5000 | H7: 5000 | I7: 5000 | J7: 5000 | K7: 5000 | L7: 5000 | M7: 5000 | N7: 5000 | O7: 5000 | Q7: =SUM(D7:F7) -> 15000 | R7: =SUM(G7:I7) -> 15000 | S7: =SUM(J7:L7) -> 15000 | T7: =SUM(M7:O7) -> 15000 | V7: =SUM(Q7:T7) -> 60000
C8: Employee Meals | D8: 2000 | E8: 2000 | F8: 2000 | G8: 2000 | H8: 2000 | I8: 2000 | J8: 2000 | K8: 2000 | L8: 2000 | M8: 2000 | N8: 2000 | O8: 2000 | Q8: =SUM(D8:F8) -> 6000 | R8: =SUM(G8:I8) -> 6000 | S8: =SUM(J8:L8) -> 6000 | T8: =SUM(M8:O8) -> 6000 | V8: =SUM(Q8:T8) -> 24000
C9: Hotels | D9: 4000 | E9: 4000 | F9: 4000 | G9: 4000 | H9: 4000 | I9: 4000 | J9: 4000 | K9: 4000 | L9: 4000 | M9: 4000 | N9: 4000 | O9: 4000 | Q9: =SUM(D9:F9) -> 12000 | R9: =SUM(G9:I9) -> 12000 | S9: =SUM(J9:L9) -> 12000 | T9: =SUM(M9:O9) -> 12000 | V9: =SUM(Q9:T9) -> 48000
C10: Mileage | D10: 200 | E10: 200 | F10: 200 | G10: 200 | H10: 200 | I10: 200 | J10: 200 | K10: 200 | L10: 200 | M10: 200 | N10: 200 | O10: 200 | Q10: =SUM(D10:F10) -> 600 | R10: =SUM(G10:I10) -> 600 | S10: =SUM(J10:L10) -> 600 | T10: =SUM(M10:O10) -> 600 | V10: =SUM(Q10:T10) -> 2400
C11: Other Employee Expenses | D11: 500 | E11: 500 | F11: 500 | G11: 500 | H11: 500 | I11: 500 | J11: 500 | K11: 500 | L11: 500 | M11: 500 | N11: 500 | O11: 500 | Q11: =SUM(D11:F11) -> 1500 | R11: =SUM(G11:I11) -> 1500 | S11: =SUM(J11:L11) -> 1500 | T11: =SUM(M11:O11) -> 1500 | V11: =SUM(Q11:T11) -> 6000
C12: Parking | D12: 200 | E12: 150 | F12: 100 | G12: 100 | H12: 100 | I12: 100 | J12: 100 | K12: 100 | L12: 100 | M12: 100 | N12: 100 | O12: 100 | Q12: =SUM(D12:F12) -> 450 | R12: =SUM(G12:I12) -> 300 | S12: =SUM(J12:L12) -> 300 | T12: =SUM(M12:O12) -> 300 | V12: =SUM(Q12:T12) -> 1350
C13: Taxis & Shared Rides | D13: 500 | E13: 400 | F13: 400 | G13: 400 | H13: 400 | I13: 400 | J13: 400 | K13: 400 | L13: 400 | M13: 400 | N13: 400 | O13: 400 | Q13: =SUM(D13:F13) -> 1300 | R13: =SUM(G13:I13) -> 1200 | S13: =SUM(J13:L13) -> 1200 | T13: =SUM(M13:O13) -> 1200 | V13: =SUM(Q13:T13) -> 4900
C14: Total Employee Travel | D14: =SUM(D7:D13) -> 12400 | E14: =SUM(E7:E13) -> 12250 | F14: =SUM(F7:F13) -> 12200 | G14: =SUM(G7:G13) -> 12200 | H14: =SUM(H7:H13) -> 12200 | I14: =SUM(I7:I13) -> 12200 | J14: =SUM(J7:J13) -> 12200 | K14: =SUM(K7:K13) -> 12200 | ... O14: =SUM(O7:O13) -> 12200 | Q14: =SUM(Q7:Q13) -> 36850 | R14: =SUM(R7:R13) -> 36600 | S14: =SUM(S7:S13) -> 36600 | T14: =SUM(T7:T13) -> 36600 | V14: =SUM(V7:V13) -> 146650

Sheet Other Operating Expenses
C2: 2025 Forecast
C3: Other Operating Expenses
C5: Vendor Name | D5: Description | E5: 46023 | F5: =EOMONTH(E5,0)+1 -> 46054 | G5: =EOMONTH(F5,0)+1 -> 46082 | H5: =EOMONTH(G5,0)+1 -> 46113 | I5: =EOMONTH(H5,0)+1 -> 46143 | J5: =EOMONTH(I5,0)+1 -> 46174 | K5: =EOMONTH(J5,0)+1 -> 46204 | L5: =EOMONTH(K5,0)+1 -> 46235 | M5: =EOMONTH(L5,0)+1 -> 46266 | ... P5: =EOMONTH(O5,0)+1 -> 46357 | R5: Q1 '26 | S5: Q2 '26 | T5: Q3 '26 | U5: Q4 '26 | W5: 2026E
C7: Bad Debt Expense | D7: Bad Debt Expense | E7: 0 | F7: 0 | G7: 0 | H7: 0 | I7: 0 | J7: 0 | K7: 0 | L7: 0 | M7: 0 | N7: 0 | O7: 0 | P7: 0 | R7: =SUM(E7:G7) -> 0 | S7: =SUM(H7:J7) -> 0 | T7: =SUM(K7:M7) -> 0 | U7: =SUM(N7:P7) -> 0 | W7: =SUM(R7:U7) -> 0
C8: Bank of America | D8: Bank Fees & Service Charges | E8: 20 | F8: 20 | G8: 20 | H8: 20 | I8: 20 | J8: 20 | K8: 20 | L8: 20 | M8: 20 | N8: 20 | O8: 20 | P8: 20 | R8: =SUM(E8:G8) -> 60 | S8: =SUM(H8:J8) -> 60 | T8: =SUM(K8:M8) -> 60 | U8: =SUM(N8:P8) -> 60 | W8: =SUM(R8:U8) -> 240
C9: Florida Sunbiz | D9: Licenses and Fees | E9: 20 | F9: 20 | G9: 20 | H9: 20 | I9: 20 | J9: 20 | K9: 20 | L9: 20 | M9: 20 | N9: 20 | O9: 20 | P9: 20 | R9: =SUM(E9:G9) -> 60 | S9: =SUM(H9:J9) -> 60 | T9: =SUM(K9:M9) -> 60 | U9: =SUM(N9:P9) -> 60 | W9: =SUM(R9:U9) -> 240
C10: SAM.gov | D10: Licenses and Fees | E10: 0 | F10: 498 | G10: 0 | H10: 0 | I10: 0 | J10: 0 | K10: 597 | L10: 0 | M10: 0 | N10: 0 | O10: 0 | P10: 0 | R10: =SUM(E10:G10) -> 498 | S10: =SUM(H10:J10) -> 0 | T10: =SUM(K10:M10) -> 597 | U10: =SUM(N10:P10) -> 0 | W10: =SUM(R10:U10) -> 1095
C11: North American Securities Administrators Association, Inc. | D11: Licenses and Fees | E11: 0 | F11: 500 | G11: 500 | H11: 500 | I11: 0 | J11: 0 | K11: 0 | L11: 0 | M11: 0 | N11: 0 | O11: 0 | P11: 0 | R11: =SUM(E11:G11) -> 1000 | S11: =SUM(H11:J11) -> 500 | T11: =SUM(K11:M11) -> 0 | U11: =SUM(N11:P11) -> 0 | W11: =SUM(R11:U11) -> 1500
C12: International Organization for Standardization | D12: Licenses and Fees | E12: 40 | F12: 40 | G12: 40 | H12: 40 | I12: 40 | J12: 40 | K12: 40 | L12: 40 | M12: 40 | N12: 40 | O12: 40 | P12: 40 | R12: =SUM(E12:G12) -> 120 | S12: =SUM(H12:J12) -> 120 | T12: =SUM(K12:M12) -> 120 | U12: =SUM(N12:P12) -> 120 | W12: =SUM(R12:U12) -> 480
C13: Checkr Inc. | D13: Licenses and Fees | E13: 30 | F13: 30 | G13: 30 | H13: 30 | I13: 30 | J13: 30 | K13: 30 | L13: 30 | M13: 30 | N13: 30 | O13: 30 | P13: 30 | R13: =SUM(E13:G13) -> 90 | S13: =SUM(H13:J13) -> 90 | T13: =SUM(K13:M13) -> 90 | U13: =SUM(N13:P13) -> 90 | W13: =SUM(R13:U13) -> 360
C14: Marcum Technology LLC | D14: Licenses and Fees | E14: 0 | F14: 0 | G14: 100 | H14: 0 | I14: 0 | J14: 0 | K14: 0 | L14: 0 | M14: 0 | N14: 0 | O14: 0 | P14: 0 | R14: =SUM(E14:H14) -> 100 | S14: =SUM(H14:J14) -> 0 | T14: =SUM(K14:M14) -> 0 | U14: =SUM(N14:P14) -> 0 | W14: =SUM(R14:U14) -> 100
C15: Florida Department of Revenue | D15: Licenses and Fees | E15: 25 | F15: 25 | G15: 25 | H15: 25 | I15: 25 | J15: 25 | K15: 25 | L15: 25 | M15: 25 | N15: 25 | O15: 25 | P15: 25 | R15: =SUM(E15:G15) -> 75 | S15: =SUM(H15:J15) -> 75 | T15: =SUM(K15:M15) -> 75 | U15: =SUM(N15:P15) -> 75 | W15: =SUM(R15:U15) -> 300
C16: The Hartford | D16: Commercial Liability Insurance | E16: 409 | F16: 409 | G16: 409 | H16: 409 | I16: 409 | J16: 409 | K16: 409 | L16: 409 | M16: 409 | N16: 409 | O16: 409 | P16: 409 | R16: =SUM(E16:G16) -> 1227 | S16: =SUM(H16:J16) -> 1227 | T16: =SUM(K16:M16) -> 1227 | U16: =SUM(N16:P16) -> 1227 | W16: =SUM(R16:U16) -> 4908
C17: Travelers | D17: Directors & Officers Liability | E17: 1108 | F17: 1108 | G17: 1108 | H17: 1108 | I17: 1108 | J17: 1108 | K17: 1108 | L17: 1108 | M17: 1108 | N17: 1108 | O17: 1108 | P17: 1108 | R17: =SUM(E17:G17) -> 3324 | S17: =SUM(H17:J17) -> 3324 | T17: =SUM(K17:M17) -> 3324 | U17: =SUM(N17:P17) -> 3324 | W17: =SUM(R17:U17) -> 13296
C18: Workers' Compensation Insurance | D18: Workers' Compensation Insurance | E18: 150 | F18: 150 | G18: 150 | H18: 150 | I18: 150 | J18: 150 | K18: 150 | L18: 150 | M18: 150 | N18: 150 | O18: 150 | P18: 150 | R18: =SUM(E18:G18) -> 450 | S18: =SUM(H18:J18) -> 450 | T18: =SUM(K18:M18) -> 450 | U18: =SUM(N18:P18) -> 450 | W18: =SUM(R18:U18) -> 1800
C19: Credit Card Interest | D19: Credit Card Interest | E19: 0 | F19: 0 | G19: 0 | H19: 500 | I19: 500 | J19: 500 | K19: 500 | L19: 500 | M19: 500 | N19: 500 | O19: 500 | P19: 500 | R19: =SUM(E19:H19) -> 500 | S19: =SUM(H19:J19) -> 1500 | T19: =SUM(K19:M19) -> 1500 | U19: =SUM(N19:P19) -> 1500 | W19: =SUM(R19:U19) -> 5000
C20: FARDA | D20: Office Rent | E20: 350 | F20: 350 | G20: 350 | H20: 350 | I20: 350 | J20: 350 | K20: 350 | L20: 350 | M20: 350 | N20: 350 | O20: 350 | P20: 350 | R20: =SUM(E20:G20) -> 1050 | S20: =SUM(H20:J20) -> 1050 | T20: =SUM(K20:M20) -> 1050 | U20: =SUM(N20:P20) -> 1050 | W20: =SUM(R20:U20) -> 4200
C21: Florida Department of Revenue | D21: FL Reemployment Tax | E21: 60 | F21: 60 | G21: 60 | H21: 60 | I21: 60 | J21: 60 | K21: 60 | L21: 60 | M21: 60 | N21: 60 | O21: 60 | P21: 60 | R21: =SUM(E21:G21) -> 180 | S21: =SUM(H21:J21) -> 180 | T21: =SUM(K21:M21) -> 180 | U21: =SUM(N21:P21) -> 180 | W21: =SUM(R21:U21) -> 720
C22: Total Other Operating Expenses | E22: =SUM(E7:E21) -> 2212 | F22: =SUM(F7:F21) -> 3210 | G22: =SUM(G7:G21) -> 2812 | H22: =SUM(H7:H21) -> 3212 | I22: =SUM(I7:I21) -> 2712 | J22: =SUM(J7:J21) -> 2712 | K22: =SUM(K7:K21) -> 3309 | L22: =SUM(L7:L21) -> 2712 | ... P22: =SUM(P7:P21) -> 2712 | R22: =SUM(R7:R21) -> 8734 | S22: =SUM(S7:S21) -> 8636 | T22: =SUM(T7:T21) -> 8733 | U22: =SUM(U7:U21) -> 8136 | W22: =SUM(W7:W21) -> 34239
